Workbook

Sheet TD MEMO
A3: Unidad de Compra | B3: Proyectos | C3: Monto
A4: Bienes y Servicios | B4: 238 | C4: 1932801598
A5: Activos Fijos | B5: 18 | C5: 4545805005
A6: Administración de Fondos | B6: 47 | C6: 216217147
A7: Bienestar | B7: 1 | C7: 156000000
A8: Compras Convenio GORE Region de Los Lagos | B8: 16 | C8: 1438588008
A9: Obras Civiles | B9: 14 | C9: 7264673295
A10: Proyectos de Arrastre | B10: 59 | C10: 6588447864
A11: Total general | B11: 393 | C11: 22142532917

Sheet TD (2)
A1: PAC | B1: TIPO PAC | C1: ID Proyecto | D1: Nombre Proyecto | E1: Nombre responsable | F1: Cargo responsable | G1: Suma de Monto Total Ítem Año 2026
A2: PC26 | B2: Activos Fijos | C2: 1057922-10-PC26 | D2: REPOSICION CESFAM CON SAR RAHUE ALTO, OSORNO | E2: Maria Elena Muñoz | F2: Jefa (S) Sub. Dpto. De Inversiones De Equipos Y Equipamiento | G2: 1578831000
A3: PC26 | B3: Activos Fijos | C3: 1057922-11-PC26 | D3: HABILITACION ANGIOGRAFO HOSPITAL BASE DE OSORNO | E3: Maria Elena Muñoz | F3: Jefa (S) Sub. Dpto. De Inversiones De Equipos Y Equipamiento | G3: 1969068000
A4: PC26 | B4: Activos Fijos | C4: 1057922-12-PC26 | D4: CONSTRUCCION COSAM RAHUE, COMUNA OSORNO | E4: Maria Elena Muñoz | F4: Jefa (S) Sub. Dpto. De Inversiones De Equipos Y Equipamiento | G4: 18632000
A5: PC26 | B5: Activos Fijos | C5: 1057922-13-PC26 | D5: SUBTÍTULO 29 SECTORIAL 2026 | E5: Maria Elena Muñoz | F5: Jefa (S) Sub. Dpto. De Inversiones De Equipos Y Equipamiento | G5: 280000000
A6: PC26 | B6: Activos Fijos | C6: 1057922-14-PC26 | D6: SUBTÍTULO 29 OPERACIONAL SSO 2026 | E6: Maria Elena Muñoz | F6: Jefa (S) Sub. Dpto. De Inversiones De Equipos Y Equipamiento | G6: 61000000
A7: PC26 | B7: Activos Fijos | C7: 1057922-15-PC26 | D7: Equipamiento Ergonómico - Sillas | E7: Venecia Recabarren | F7: Jefatura Unidad Prev. Riesgos | G7: 1000000
A8: PC26 | B8: Activos Fijos | C8: 1057922-16-PC26 | D8: Adquisición de micrófono y cámara para videoconferencias del Centro Comunitario Kümelen | E8: Luis Flores | F8: Coordinador | G8: 250000
A9: PC26 | B9: Activos Fijos | C9: 1057922-17-PC26 | D9: Adquisición de megáfonos y gabinetes para la comunicación en emergencias, gestión de riesgos y protección de equipos | E9: Yuvit Garcia-Chacur | F9: DIRECTORA | G9: 780000
A10: PC26 | B10: Activos Fijos | C10: 1057922-18-PC26 | D10: REPOSICION CECOSF EL ENCANTO, COMUNA DE PUYEHUE | E10: Maria Elena Muñoz | F10: Jefa (S) Sub. Dpto. De Inversiones De Equipos Y Equipamiento | G10: 6773000
A11: PC26 | B11: Activos Fijos | C11: 1057922-19-PC26 | D11: Adquisición de productos e insumos para el programa de control y eliminación de la Tuberculosis | E11: NMaria Paz Gomez | F11: Referente Programa De Tuberculosis | G11: 19000000
A12: PC26 | B12: Activos Fijos | C12: 1057922-20-PC26 | D12: Adquisición de herramientas | E12: Pedro Fritz | F12: Director | G12: 300000
A13: PC26 | B13: Activos Fijos | C13: 1057922-21-PC26 | D13: Adquisicion equipamiento Servidor NAS y almacenamiento extra para respaldo y seguridad de la información | E13: Alejandro Nuñez | F13: Encargado Gestión De Sistemas | G13: 16000000
... A394: PC26 | B394: Obras Civiles | C394: 1057976-9-PC26 | D394: Contratación de Visita a Obra 2026 de las Consultorías: Especialidades y Arquitectura Obra CESFAM Bahía Mansa | E394: Rodrigo Neira | F394: Itos | G394: 9814756

Sheet TD3
A3: ID Proyecto | B3: PAC | C3: Unidad de Compra | D3: Nombre Proyecto | E3: Nombre ítem | F3: Cantidad de Ítems | G3: Nombre responsable | H3: Fecha de Inicio Compra | I3: Cargo responsable | J3: Cantidad OC | K3: Meses envío OC | L3: Suma de Monto Total Ítem Año 2026
A4: 1057532-156-PC24 | B4: Arrastre | C4: Bienes y Servicios | D4: servicios de control de asistencia del servicio de salud osorno | E4: Servicio Control Asistencia | F4: 2 | G4: Bruno Ojeda Alvarez | H4: 45292 | I4: Jefe Depto. Tecnologías de la Información | J4: 36 | K4: 01-01-2024,01-02-2024,01-03-2024,01-04-2024,01-05-2024,01-06-2024,01-07-2024,01-08-2024,01-09-2024,01-10-2024,01-11-2024,01-12-2024,01-01-2025,01-02-2025,01-03-2025,01-04-2025,01-05-2025,01-06-2025,01-07-2025,01-08-2025,01-09-2025,01-10-2025,01-11-2025,01-12-2025,01-01-2026,01-02-2026,01-03-2026,01-04-2026,01-05-2026,01-06-2026,01-07-2026,01-08-2026,01-09-2026,01-10-2026,01-11-2026,01-12-2026 | L4: 30000000
A5: 1057532-162-PC25 | B5: Arrastre | C5: Bienes y Servicios | D5: Convenio - de Suministro para adquisición de medicamentos faltantes CENABAST para establecimientos dependientes del SSO. | E5: Medicamentos | F5: 1 | G5: ELEUTERIO ROMAN | H5: 45748 | I5: JEFE SUBDEPTO FARMACIA | J5: 24 | K5: 01-05-2025,01-06-2025,01-07-2025,01-08-2025,01-09-2025,01-10-2025,01-11-2025,01-12-2025,01-01-2026,01-02-2026,01-03-2026,01-04-2026,01-05-2026,01-06-2026,01-07-2026,01-08-2026,01-09-2026,01-10-2026,01-11-2026,01-12-2026,01-01-2027,01-02-2027,01-03-2027,01-04-2027 | L5: 75000000
A6: 1057532-163-PC24 | B6: Arrastre | C6: Bienes y Servicios | D6: Servicio gestión flota vehicular SSO | E6: Control Flota | F6: 2 | G6: Bruno Ojeda Alvarez | H6: 45200 | I6: Jefe Depto. | J6: 36 | K6: 01-01-2024,01-02-2024,01-03-2024,01-04-2024,01-05-2024,01-06-2024,01-07-2024,01-08-2024,01-09-2024,01-10-2024,01-11-2024,01-12-2024,01-01-2025,01-02-2025,01-03-2025,01-04-2025,01-05-2025,01-06-2025,01-07-2025,01-08-2025,01-09-2025,01-10-2025,01-11-2025,01-12-2025,01-01-2026,01-02-2026,01-03-2026,01-04-2026,01-05-2026,01-06-2026,01-07-2026,01-08-2026,01-09-2026,01-10-2026,01-11-2026,01-12-2026 | L6: 6711996
A7: 1057532-172-PC25 | B7: Arrastre | C7: Bienes y Servicios | D7: Convenio - CONVENIO SERVICIO DE ASEO POR 18 MESES, PARA LA DIRECCION DEL SSO Y ESTABLECIMIENTOS DEPENDIENTES DE LA RED ASISTENCIAL | E7: Aseo | F7: 1 | G7: Lorena Torres Castillo | H7: 45839 | I7: ENCARGADA (S) SECCIÓN DE ADMINISTRACIÓN DE CONTRATOS | J7: 18 | K7: 01-07-2025,01-08-2025,01-09-2025,01-10-2025,01-11-2025,01-12-2025,01-01-2026,01-02-2026,01-03-2026,01-04-2026,01-05-2026,01-06-2026,01-07-2026,01-08-2026,01-09-2026,01-10-2026,01-11-2026,01-12-2026 | L7: 144000000
A8: 1057532-173-PC25 | B8: Arrastre | C8: Bienes y Servicios | D8: Convenio - CONVENIO DE ADQUISICION DE KIT POINT OF CARE (POC) CON ARRIENDO DE EQUIPO PARA ANALISIS DE MUESTRAS, SSO | E8: Equipo | F8: 1 | G8: Sofia Reyes | H8: 45839 | I8: Encargada | J8: 12 | K8: 01-08-2025,01-09-2025,01-10-2025,01-11-2025,01-12-2025,01-01-2026,01-02-2026,01-03-2026,01-04-2026,01-05-2026,01-06-2026,01-07-2026 | L8: 40833335
A9: 1057532-193-PC25 | B9: Arrastre | C9: Bienes y Servicios | D9: Convenio - ARRIENDO 159 EQUIPOS PC AIO PARA APOYAR LOS PORCESOS CLINICOS Y ADMINISTRATIVOS | E9: Insumos | F9: 2 | G9: Alvaro Montecinos | H9: 45870 | I9: Jefe (S) Subdepto. Soporte TIC | J9: 1 | K9: 01-01-2026,01-02-2026,01-03-2026,01-04-2026,01-05-2026,01-06-2026,01-07-2026,01-08-2026,01-09-2026,01-10-2026,01-11-2026,01-12-2026,01-01-2027,01-02-2027,01-03-2027,01-04-2027,01-05-2027,01-06-2027,01-07-2027,01-08-2027,01-09-2027,01-10-2027,01-11-2027,01-12-2027,01-01-2028,01-02-2028,01-03-2028,01-04-2028,01-05-2028,01-06-2028,01-07-2028,01-08-2028 | L9: 74068560
A10: 1057532-193-PC25 | B10: Arrastre | C10: Bienes y Servicios | D10: Convenio - ARRIENDO 159 EQUIPOS PC AIO PARA APOYAR LOS PROCESOS CLINICOS Y ADMINISTRATIVOS | E10: Insumos | F10: 2 | G10: Alvaro Montecinos | H10: 45992 | I10: Jefe (S) Subdepto. Soporte TIC | J10: 32 | K10: 01-01-2026,01-02-2026,01-03-2026,01-04-2026,01-05-2026,01-06-2026,01-07-2026,01-08-2026,01-09-2026,01-10-2026,01-11-2026,01-12-2026,01-01-2027,01-02-2027,01-03-2027,01-04-2027,01-05-2027,01-06-2027,01-07-2027,01-08-2027,01-09-2027,01-10-2027,01-11-2027,01-12-2027,01-01-2028,01-02-2028,01-03-2028,01-04-2028,01-05-2028,01-06-2028,01-07-2028,01-08-2028 | L10: 37034280
A11: 1057532-195-PC25 | B11: Arrastre | C11: Bienes y Servicios | D11: Convenio - SERVICIO DE ASEO PARA LA DSSO (BASE SAMU, EDIFICIO PLAZA SUR Y EDIFICIO M. RODRIGUEZ) POR 18 MESES (DESDE 01 JULIO 2025) | E11: Aseo | F11: 2 | G11: Lorena Torres Castillo | H11: 45658 | I11: Encargada (S) Sección Administración de Contratos | J11: 18 | K11: 01-07-2025,01-08-2025,01-09-2025,01-10-2025,01-11-2025,01-12-2025,01-01-2026,01-02-2026,01-03-2026,01-04-2026,01-05-2026,01-06-2026,01-07-2026,01-08-2026,01-09-2026,01-10-2026,01-11-2026,01-12-2026 | L11: 70333380
A12: 1057532-196-PC25 | B12: Arrastre | C12: Bienes y Servicios | D12: Convenio - SERVICIO DE SOPORTE Y MANTENCION RPT VHF SSO (PERIODO DOS AÑOS) | E12: Mantenimiento | F12: 2 | G12: ESTEBAN ALARCON BOHLE | H12: 45658 | I12: TECNICO RADIOCOMUNICACIONES | J12: 24 | K12: 01-01-2025,01-02-2025,01-03-2025,01-04-2025,01-05-2025,01-06-2025,01-07-2025,01-08-2025,01-09-2025,01-10-2025,01-11-2025,01-12-2025,01-01-2026,01-02-2026,01-03-2026,01-04-2026,01-05-2026,01-06-2026,01-07-2026,01-08-2026,01-09-2026,01-10-2026,01-11-2026,01-12-2026 | L12: 6255504
A13: 1057532-1-PC24 | B13: Arrastre | C13: Bienes y Servicios | D13: Sistema control de flota vehicular del Servicio de Salud Osorno | E13: Sistema de control de flota | F13: 1 | G13: Felipe Salvo Barriga | H13: 45292 | I13: Enc. Sección Mant. de Vehículos | J13: 36 | K13: 01-01-2024,01-02-2024,01-03-2024,01-04-2024,01-05-2024,01-06-2024,01-07-2024,01-08-2024,01-09-2024,01-10-2024,01-11-2024,01-12-2024,01-01-2025,01-02-2025,01-03-2025,01-04-2025,01-05-2025,01-06-2025,01-07-2025,01-08-2025,01-09-2025,01-10-2025,01-11-2025,01-12-2025,01-01-2026,01-02-2026,01-03-2026,01-04-2026,01-05-2026,01-06-2026,01-07-2026,01-08-2026,01-09-2026,01-10-2026,01-11-2026,01-12-2026 | L13: 6712008
A14: 1057532-209-PC25 | B14: Arrastre | C14: Bienes y Servicios | D14: Convenio - ADQUISICION DE 3 CUPOS DE RESIDENCIA PROTEGIDA PARA EL SERVICIO DE SALUD OSORNO EN LA PROVINCIA DE CONCEPCIÓN | E14: Servicio Residencial | F14: 2 | G14: Angelo Palma | H14: 45658 | I14: Jefe (s) Subdepto. Gestión Clínica y Administrativa Red Temática de Salud Mental de Especialidad | J14: 24 | K14: 01-01-2025,01-02-2025,01-03-2025,01-04-2025,01-05-2025,01-06-2025,01-07-2025,01-08-2025,01-09-2025,01-10-2025,01-11-2025,01-12-2025,01-01-2026,01-02-2026,01-03-2026,01-04-2026,01-05-2026,01-06-2026,01-07-2026,01-08-2026,01-09-2026,01-10-2026,01-11-2026,01-12-2026 | L14: 48115128
A15: 1057532-210-PC25 | B15: Arrastre | C15: Bienes y Servicios | D15: Convenio - ADQUISICION DE 12 CUPOS DE RESIDENCIA PROTEGIDA PARA EL SERVICIO DE SALUD OSORNO EN LA CIUDAD DE OSORNO | E15: Servicio Residencial | F15: 2 | G15: Angelo Palma | H15: 45658 | I15: Jefe (s) Subdepto. Gestión Clínica y Administrativa Red Temática de Salud Mental de Especialidad | J15: 24 | K15: 01-01-2025,01-02-2025,01-03-2025,01-04-2025,01-05-2025,01-06-2025,01-07-2025,01-08-2025,01-09-2025,01-10-2025,01-11-2025,01-12-2025,01-01-2026,01-02-2026,01-03-2026,01-04-2026,01-05-2026,01-06-2026,01-07-2026,01-08-2026,01-09-2026,01-10-2026,01-11-2026,01-12-2026 | L15: 237155100
A16: 1057532-211-PC25 | B16: Arrastre | C16: Bienes y Servicios | D16: Convenio - ADQUISICION DE 10 CUPOS RESIDENCIA PROTEGIDA DE ALTA COMPLEJIDAD PARA EL SERVICIO DE SALUD OSORNO DE LA CIUDAD DE OSORNO | E16: Servicio Residencial | F16: 2 | G16: Angelo Palma | H16: 45658 | I16: Jefe (s) Subdepto. Gestión Clínica y Administrativa Red Temática de Salud Mental de Especialidad | J16: 24 | K16: 01-01-2025,01-02-2025,01-03-2025,01-04-2025,01-05-2025,01-06-2025,01-07-2025,01-08-2025,01-09-2025,01-10-2025,01-11-2025,01-12-2025,01-01-2026,01-02-2026,01-03-2026,01-04-2026,01-05-2026,01-06-2026,01-07-2026,01-08-2026,01-09-2026,01-10-2026,01-11-2026,01-12-2026 | L16: 284700000
A17: 1057532-281-PC26 | B17: PC26 | C17: Bienes y Servicios | D17: Mantención Plotter Canon IPF 770, del depto. de Proyectos. | E17: Mantencion | F17: 1 | G17: Mario Barrientos | H17: 46266 | I17: Jefe Subdepto. Diseño De Infraestructura De Salud | J17: 1 | K17: 46266 | L17: 1250000
A18: 1057532-282-PC26 | B18: PC26 | C18: Bienes y Servicios | D18: Compra rollos papel para impresión del Departamento de Proyectos SSO. | E18: Rollos | F18: 1 | G18: Mario Barrientos | H18: 46174 | I18: Jefe Subdepto. Diseño De Infraestructura De Salud | J18: 1 | K18: 46174 | L18: 300000
A19: 1057532-283-PC26 | B19: PC26 | C19: Bienes y Servicios | D19: Compra Tinta Plotter Canon IPF 770 | E19: Tinta Plotter | F19: 1 | G19: Mario Barrientos | H19: 46204 | I19: Jefe Subdepto. Diseño De Infraestructura De Salud | J19: 1 | K19: 46204 | L19: 1320000
A20: 1057532-284-PC26 | B20: PC26 | C20: Bienes y Servicios | D20: Adquisicición Hojas Prehospitalarias | E20: Talonarios | F20: 1 | G20: Silvia Delgado | H20: 46082 | I20: Encargada Proceso De Urgencia | J20: 1 | K20: 46082 | L20: 2000700
A21: 1057532-285-PC26 | B21: PC26 | C21: Bienes y Servicios | D21: Adquisicición Kit de Triage y Sistema de comando incidente | E21: Kit Sistema | F21: 1 | G21: Silvia Delgado | H21: 46082 | I21: Encargada Proceso De Urgencia | J21: 1 | K21: 46082 | L21: 1510005
A22: 1057532-286-PC26 | B22: PC26 | C22: Bienes y Servicios | D22: II Jornada de Capacitación Red de Urgencia | E22: Cafeteria | F22: 2 | G22: Silvia Delgado | H22: 46082 | I22: Encargada Proceso De Urgencia | J22: 1 | K22: 46082 | L22: 850000
A23: 1057532-286-PC26 | B23: PC26 | C23: Bienes y Servicios | D23: II Jornada de Capacitación Red de Urgencia | E23: Opalina | F23: 2 | G23: Silvia Delgado | H23: 46082 | I23: Encargada Proceso De Urgencia | J23: 1 | K23: 46082 | L23: 22500
A24: 1057532-287-PC26 | B24: PC26 | C24: Bienes y Servicios | D24: ?DIAGNÓSTICO Y DIALOGO PARTICIPATIVO COSAM RAHUE ?NOVIEMBRE 2026? | E24: Cafeteria | F24: 1 | G24: Camilo Martínez | H24: 46327 | I24: Director(S) | J24: 1 | K24: 46327 | L24: 540000
A25: 1057532-288-PC26 | B25: PC26 | C25: Bienes y Servicios | D25: Jornadas de encuentro y autocuidado Para usuarios y cuidadores ?SALUDABLE-MENTE en dispositivo COSAM RAHUE 2026 | E25: Alimentación | F25: 6 | G25: Camilo Martínez | H25: 46113 | I25: Director(S) | J25: 1 | K25: 46113 | L25: 135000
A26: 1057532-288-PC26 | B26: PC26 | C26: Bienes y Servicios | D26: Jornadas de encuentro y autocuidado Para usuarios y cuidadores ?SALUDABLE-MENTE en dispositivo COSAM RAHUE 2026 | E26: Alimentación | F26: 6 | G26: Camilo Martínez | H26: 46204 | I26: Director(S) | J26: 1 | K26: 46204 | L26: 135000
A27: 1057532-288-PC26 | B27: PC26 | C27: Bienes y Servicios | D27: Jornadas de encuentro y autocuidado Para usuarios y cuidadores ?SALUDABLE-MENTE en dispositivo COSAM RAHUE 2026 | E27: Alimentación | F27: 6 | G27: Camilo Martínez | H27: 46266 | I27: Director(S) | J27: 1 | K27: 46266 | L27: 135000
A28: 1057532-288-PC26 | B28: PC26 | C28: Bienes y Servicios | D28: Jornadas de encuentro y autocuidado Para usuarios y cuidadores ?SALUDABLE-MENTE en dispositivo COSAM RAHUE 2026 | E28: Alimentación | F28: 6 | G28: Camilo Martínez | H28: 46357 | I28: Director(S) | J28: 1 | K28: 46357 | L28: 135000
A29: 1057532-288-PC26 | B29: PC26 | C29: Bienes y Servicios | D29: Jornadas de encuentro y autocuidado Para usuarios y cuidadores ?SALUDABLE-MENTE en dispositivo COSAM RAHUE 2026 | E29: Cafeteria | F29: 6 | G29: Camilo Martínez | H29: 46113 | I29: Director(S) | J29: 1 | K29: 46113 | L29: 135000
A30: 1057532-288-PC26 | B30: PC26 | C30: Bienes y Servicios | D30: Jornadas de encuentro y autocuidado Para usuarios y cuidadores ?SALUDABLE-MENTE en dispositivo COSAM RAHUE 2026 | E30: Cafeteria | F30: 6 | G30: Camilo Martínez | H30: 46204 | I30: Director(S) | J30: 3 | K30: 01-07-2026,01-09-2026,01-12-2026 | L30: 405000
A31: 1057532-308-PC24 | B31: Arrastre | C31: Bienes y Servicios | D31: Convenio - 3 cupos Residencia Protegida para el Servicio de Salud Osorno en la Región Metropolitana | E31: Residencia | F31: 1 | G31: Antonia Caifil | H31: 45474 | I31: Jefa Subdepto. Gestión Clinica y Adm. | J31: 24 | K31: 01-01-2025,01-02-2025,01-03-2025,01-04-2025,01-05-2025,01-06-2025,01-07-2025,01-08-2025,01-09-2025,01-10-2025,01-11-2025,01-12-2025,01-01-2026,01-02-2026,01-03-2026,01-04-2026,01-05-2026,01-06-2026,01-07-2026,01-08-2026,01-09-2026,01-10-2026,01-11-2026,01-12-2026 | L31: 40432878
A32: 1057532-30-PC24 | B32: Arrastre | C32: Bienes y Servicios | D32: SISTEMAS DE COMUNICACIONES LTE WAVE PTX SERVICIO DE SALUD OSORNO | E32: Servicio | F32: 1 | G32: CATALINA VERA | H32: 45413 | I32: COORDINADORA EMERGENCIA | J32: 36 | K32: 01-06-2024,01-07-2024,01-08-2024,01-09-2024,01-10-2024,01-11-2024,01-12-2024,01-01-2025,01-02-2025,01-03-2025,01-04-2025,01-05-2025,01-06-2025,01-07-2025,01-08-2025,01-09-2025,01-10-2025,01-11-2025,01-12-2025,01-01-2026,01-02-2026,01-03-2026,01-04-2026,01-05-2026,01-06-2026,01-07-2026,01-08-2026,01-09-2026,01-10-2026,01-11-2026,01-12-2026,01-01-2027,01-02-2027,01-03-2027,01-04-2027,01-05-2024 | L32: 43333332
A33: 1057532-311-PC24 | B33: Arrastre | C33: Bienes y Servicios | D33: Convenio - ( cupos Hogar Protegido Varones para el Servicio de Salud Osorno en la ciudad de Osorno | E33: Residencia | F33: 1 | G33: Antonia Caifil | H33: 45444 | I33: Jefa Subdepto. Gestión Clínica y Adm. | J33: 24 | K33: 01-01-2025,01-02-2025,01-03-2025,01-04-2025,01-05-2025,01-06-2025,01-07-2025,01-08-2025,01-09-2025,01-10-2025,01-11-2025,01-12-2025,01-01-2026,01-02-2026,01-03-2026,01-04-2026,01-05-2026,01-06-2026,01-07-2026,01-08-2026,01-09-2026,01-10-2026,01-11-2026,01-12-2026 | L33: 78361124
A34: 1057532-315-PC24 | B34: Arrastre | C34: Bienes y Servicios | D34: Convenio - 08 Cupos Hogar Protegido Mujeres para el Servicio de Salud Osorno en la ciudad de Osorno | E34: Residencia | F34: 1 | G34: Antonia Caifil | H34: 45444 | I34: Jefa Subdepto. Gestión Clínica y Adm. | J34: 24 | K34: 01-01-2025,01-02-2025,01-03-2025,01-04-2025,01-05-2025,01-06-2025,01-07-2025,01-08-2025,01-09-2025,01-10-2025,01-11-2025,01-12-2025,01-01-2026,01-02-2026,01-03-2026,01-04-2026,01-05-2026,01-06-2026,01-07-2026,01-08-2026,01-09-2026,01-10-2026,01-11-2026,01-12-2026 | L34: 78361124
A35: 1057532-317-PC26 | B35: PC26 | C35: Bienes y Servicios | D35: ?Eco-huerto sustentable -Sistema de acuaponía sin suelo? COSAM RAHUE 2026 | E35: Macetero | F35: 1 | G35: Camilo Martínez | H35: 46082 | I35: Director(S) | J35: 1 | K35: 46082 | L35: 1500000
A36: 1057532-320-PC24 | B36: Arrastre | C36: Bienes y Servicios | D36: Convenio - SERVICIOS DE MANTENCIÓN, RECARGA E INSPECCION PREVENTIVA PARA RED HÚMEDA Y EXTINTORES EN ESTABLECIMIENTOS SSO | E36: Recarga | F36: 1 | G36: KARIN SCHOLZ | H36: 45444 | I36: Jefatura Dpto. de Calidad de Vida | J36: 30 | K36: 01-01-2025,01-02-2025,01-03-2025,01-04-2025,01-05-2025,01-06-2025,01-07-2025,01-08-2025,01-09-2025,01-10-2025,01-11-2025,01-12-2025,01-01-2026,01-02-2026,01-03-2026,01-04-2026,01-05-2026,01-06-2026,01-07-2026,01-08-2026,01-09-2026,01-10-2026,01-11-2026,01-12-2026,01-01-2027,01-02-2027,01-03-2027,01-04-2027,01-05-2027,01-06-2027 | L36: 18060000
A37: 1057532-320-PC26 | B37: PC26 | C37: Bienes y Servicios | D37: Insumos y medicamentos Farmacia COSAM RAHUE | E37: Insumos y Repuestos | F37: 1 | G37: Camilo Martínez | H37: 46023 | I37: Director(S) | J37: 1 | K37: 46023 | L37: 850000
A38: 1057532-321-PC24 | B38: Arrastre | C38: Bienes y Servicios | D38: Convenio - DE SERVICIOS DE MANTENCIÓN PREVENTIVA, CORRECTIVA Y/O REPARATIVA PARA VEHÍCULOS MERCEDES-BENZ DEL SSO Y HOSPITA | E38: Mantenimiento | F38: 1 | G38: Felipe Salvo | H38: 45474 | I38: Encargado Mantenimineto | J38: 24 | K38: 01-01-2025,01-02-2025,01-03-2025,01-04-2025,01-05-2025,01-06-2025,01-07-2025,01-08-2025,01-09-2025,01-10-2025,01-11-2025,01-12-2025,01-01-2026,01-02-2026,01-03-2026,01-04-2026,01-05-2026,01-06-2026,01-07-2026,01-08-2026,01-09-2026,01-10-2026,01-11-2026,01-12-2026 | L38: 150000000
A39: 1057532-321-PC26 | B39: PC26 | C39: Bienes y Servicios | D39: Capacitación en Salud Mental Intercultural COSAM Rahue. | E39: Cafeteria | F39: 2 | G39: Camilo Martínez | H39: 46143 | I39: Director(S) | J39: 1 | K39: 46143 | L39: 450000
A40: 1057532-321-PC26 | B40: PC26 | C40: Bienes y Servicios | D40: Capacitación en Salud Mental Intercultural COSAM Rahue. | E40: Cafeteria | F40: 2 | G40: Camilo Martínez | H40: 46327 | I40: Director(S) | J40: 1 | K40: 46143 | L40: 450000
A41: 1057532-322-PC24 | B41: Arrastre | C41: Bienes y Servicios | D41: Convenio - SERVICIO DE MANEJO, RETIRO, TRANSPORTE Y DISPOSICIÓN FINAL DE RESIDUOS PELIGROSOS Y ESPECIALES | E41: Servicio residuos | F41: 1 | G41: KARIN SCHOLZ | H41: 45505 | I41: JEFA DE DEPTO DE CALIDAD DE VIDA | J41: 24 | K41: 01-01-2025,01-02-2025,01-03-2025,01-04-2025,01-05-2025,01-06-2025,01-07-2025,01-08-2025,01-09-2025,01-10-2025,01-11-2025,01-12-2025,01-01-2026,01-02-2026,01-03-2026,01-04-2026,01-05-2026,01-06-2026,01-07-2026,01-08-2026,01-09-2026,01-10-2026,01-11-2026,01-12-2026 | L41: 397359215
A42: 1057532-322-PC26 | B42: PC26 | C42: Bienes y Servicios | D42: Celebración de We Tripantu en COSAM Rahue 2026 | E42: Cafeteria | F42: 1 | G42: Camilo Martínez | H42: 46174 | I42: Director(S) | J42: 1 | K42: 46174 | L42: 630000
A43: 1057532-323-PC26 | B43: PC26 | C43: Bienes y Servicios | D43: Jornadas de autocuidado equipo profesional PAI COSAM Rahue | E43: Cafeteria | F43: 1 | G43: Camilo Martínez | H43: 46235 | I43: Director(S) | J43: 1 | K43: 46235 | L43: 135000
A44: 1057532-324-PC26 | B44: PC26 | C44: Bienes y Servicios | D44: CONVENIO - ADQUISICION DE 8 CUPOS HOGAR PROTEGIDO MUJERES PARA EL SERVICIO DE SALUD OSORNO POR PERIODO DE 12 MESES | E44: Hogar Protegido 1 | F44: 3 | G44: Angelo Palma | H44: 46082 | I44: Coordinador Unidad de Gestión de Procesos Clínicos de Atención de Especialidad Ambulatoria, Cerrada | J44: 12 | K44: 01-03-2026,01-04-2026,01-05-2026,01-06-2026,01-07-2026,01-08-2026,01-09-2026,01-10-2026,01-11-2026,01-12-2026,01-01-2027,01-02-2027 | L44: 36406019
A45: 1057532-324-PC26 | B45: PC26 | C45: Bienes y Servicios | D45: CONVENIO - ADQUISICION DE 8 CUPOS HOGAR PROTEGIDO MUJERES PARA EL SERVICIO DE SALUD OSORNO POR PERIODO DE 12 MESES | E45: Hogar Protegido 6 | F45: 3 | G45: Angelo Palma | H45: 46082 | I45: Coordinador Unidad de Gestión de Procesos Clínicos de Atención de Especialidad Ambulatoria, Cerrada | J45: 12 | K45: 01-03-2026,01-04-2026,01-05-2026,01-06-2026,01-07-2026,01-08-2026,01-09-2026,01-10-2026,01-11-2026,01-12-2026,01-01-2027,01-02-2027 | L45: 64787500
A46: 1057532-325-PC26 | B46: PC26 | C46: Bienes y Servicios | D46: SERVICIO CAFETERÍA CEREMONIA ANIVERSARIO COSAM RAHUE | E46: Cafeteria | F46: 1 | G46: Camilo Martínez | H46: 46143 | I46: Director(S) | J46: 1 | K46: 46143 | L46: 675000
A47: 1057532-326-PC26 | B47: PC26 | C47: Bienes y Servicios | D47: Adquisición de insumos para la atención en domicilio del Equipo Rehabilitación Rural SSO. (Articulos de Libreria) | E47: Material de Oficina | F47: 1 | G47: Karin Avila | H47: 46082 | I47: Referente Rehabilitación Integral | J47: 1 | K47: 46082 | L47: 190000
A48: 1057532-327-PC26 | B48: PC26 | C48: Bienes y Servicios | D48: Convenio - 3 CUPOS DE RESIDENCIA PROTEGIDA PARA EL SERVICIO DE SALUD OSORNO EN LA PROVINCIA DE CONCEPCIÓN, POR PERIODO DE 24 MESES. | E48: Residencia Protegia | F48: 1 | G48: Angelo Palma | H48: 46082 | I48: Coordinador Unidad de Gestión de Procesos Clínicos de Atención de Especialidad Ambulatoria, Cerrada | J48: 24 | K48: 01-03-2026,01-04-2026,01-05-2026,01-06-2026,01-07-2026,01-08-2026,01-09-2026,01-10-2026,01-11-2026,01-12-2026,01-01-2027,01-02-2027,01-03-2027,01-04-2027,01-05-2027,01-06-2027,01-07-2027,01-08-2027,01-09-2027,01-10-2027,01-11-2027,01-12-2027,01-01-2028,01-02-2028 | L48: 49483210
A49: 1057532-328-PC24 | B49: Arrastre | C49: Bienes y Servicios | D49: Convenio - BENEFICIO ALIMENTACION 2024 | E49: Tarjeta | F49: 1 | G49: JORGE OYARZUN SILVA | H49: 45444 | I49: REFERENTE TARJETA ALIMENTACION | J49: 30 | K49: 01-01-2025,01-02-2025,01-03-2025,01-04-2025,01-05-2025,01-06-2025,01-07-2025,01-08-2025,01-09-2025,01-10-2025,01-11-2025,01-12-2025,01-01-2026,01-02-2026,01-03-2026,01-04-2026,01-05-2026,01-06-2026,01-07-2026,01-08-2026,01-09-2026,01-10-2026,01-11-2026,01-12-2026,01-01-2027,01-02-2027,01-03-2027,01-04-2027,01-05-2027,01-06-2027 | L49: 496977708
A50: 1057532-328-PC26 | B50: PC26 | C50: Bienes y Servicios | D50: Rollos Etiquetas para impresora ZEBRA ZD 220 y rollos de cinta para impresora SOME, COSAM RAHUE | E50: Rollos | F50: 1 | G50: Camilo Martínez | H50: 46023 | I50: Director(S) | J50: 1 | K50: 46023 | L50: 430010
A51: 1057532-329-PC26 | B51: PC26 | C51: Bienes y Servicios | D51: Convenio - 10 CUPOS RESIDENCIA PROTEGIDA DE ALTA COMPLEJIDAD PARA EL SERVICIO DE SALUD OSORNO POR PERIODO DE 12 MESES. | E51: Residencia Protegia | F51: 1 | G51: Angelo Palma | H51: 46082 | I51: Coordinador Unidad de Gestión de Procesos Clínicos de Atención de Especialidad Ambulatoria, Cerrada | J51: 12 | K51: 01-03-2026,01-04-2026,01-05-2026,01-06-2026,01-07-2026,01-08-2026,01-09-2026,01-10-2026,01-11-2026,01-12-2026,01-01-2027,01-02-2027 | L51: 247689000
A52: 1057532-330-PC26 | B52: PC26 | C52: Bienes y Servicios | D52: INSUMOS DE ASEO COSAM RAHUE | E52: Insumos de Aseo | F52: 1 | G52: Camilo Martínez | H52: 46082 | I52: Director(S) | J52: 1 | K52: 46082 | L52: 990002
A53: 1057532-331-PC24 | B53: Arrastre | C53: Bienes y Servicios | D53: Convenio - Suministro de oxígeno medicinal para Red de Hospitales de mediana y baja complejidad y SAMU | E53: Suministro Oxigeno | F53: 1 | G53: Mario Aburto Foitzich | H53: 45474 | I53: Encargado Gestión Salud Respiratoria | J53: 24 | K53: 01-01-2025,01-02-2025,01-03-2025,01-04-2025,01-05-2025,01-06-2025,01-07-2025,01-08-2025,01-09-2025,01-10-2025,01-11-2025,01-12-2025,01-01-2026,01-02-2026,01-03-2026,01-04-2026,01-05-2026,01-06-2026,01-07-2026,01-08-2026,01-09-2026,01-10-2026,01-11-2026,01-12-2026 | L53: 118000004
A54: 1057532-331-PC26 | B54: PC26 | C54: Bienes y Servicios | D54: Compra de Insumos de Cafetería reuniones ordinarias anuales de Salud Pueblos Originarios | E54: Alimentación | F54: 1 | G54: Pedro Huito | H54: 46082 | I54: Apoyo Salud Intercultural | J54: 1 | K54: 46082 | L54: 1352694
A55: 1057532-332-PC26 | B55: PC26 | C55: Bienes y Servicios | D55: Protectores solares FPS 50 para funcionarios y usuarios taller huerto | E55: Protectores Solares | F55: 1 | G55: Camilo Martínez | H55: 46023 | I55: Director(S) | J55: 1 | K55: 46023 | L55: 300000
A56: 1057532-333-PC24 | B56: Arrastre | C56: Bienes y Servicios | D56: Convenio - SOPORTE Y MANTENIMIENTO SISTEMA DE REPETICIÓN VHF SERVICIO DE SALUD OSORNO 2025-2026 | E56: Servicio | F56: 1 | G56: CATALINA VERA CASTRO | H56: 45444 | I56: COORDINADORA EMERGENCIA | J56: 24 | K56: 01-01-2025,01-02-2025,01-03-2025,01-04-2025,01-05-2025,01-06-2025,01-07-2025,01-08-2025,01-09-2025,01-10-2025,01-11-2025,01-12-2025,01-01-2026,01-02-2026,01-03-2026,01-04-2026,01-05-2026,01-06-2026,01-07-2026,01-08-2026,01-09-2026,01-10-2026,01-11-2026,01-12-2026 | L56: 10000004
A57: 1057532-333-PC26 | B57: PC26 | C57: Bienes y Servicios | D57: TEST DE DETECCION DE DROGAS | E57: Test | F57: 1 | G57: Carolina Silva | H57: 46296 | I57: Encargada De Compras | J57: 1 | K57: 46296 | L57: 800000
A58: 1057532-334-PC26 | B58: PC26 | C58: Bienes y Servicios | D58: PAC insumos clínicos unidad de enfermería 2026. | E58: Biombo, pesa | F58: 6 | G58: Pedro Fritz | H58: 46054 | I58: DIRECTOR COSAM | J58: 1 | K58: 46054 | L58: 124000
A59: 1057532-334-PC26 | B59: PC26 | C59: Bienes y Servicios | D59: PAC insumos clínicos unidad de enfermería 2026. | E59: Caja | F59: 6 | G59: Pedro Fritz | H59: 46054 | I59: DIRECTOR COSAM | J59: 1 | K59: 46054 | L59: 8000
A60: 1057532-334-PC26 | B60: PC26 | C60: Bienes y Servicios | D60: PAC insumos clínicos unidad de enfermería 2026. | E60: Cooler | F60: 6 | G60: Pedro Fritz | H60: 46054 | I60: DIRECTOR COSAM | J60: 1 | K60: 46054 | L60: 25000
A61: 1057532-334-PC26 | B61: PC26 | C61: Bienes y Servicios | D61: PAC insumos clínicos unidad de enfermería 2026. | E61: Equipo curación, algodón | F61: 6 | G61: Pedro Fritz | H61: 46054 | I61: DIRECTOR COSAM | J61: 1 | K61: 46054 | L61: 70000
A62: 1057532-334-PC26 | B62: PC26 | C62: Bienes y Servicios | D62: PAC insumos clínicos unidad de enfermería 2026. | E62: Insumos clínicos | F62: 6 | G62: Pedro Fritz | H62: 46054 | I62: DIRECTOR COSAM | J62: 1 | K62: 46054 | L62: 699036
A63: 1057532-334-PC26 | B63: PC26 | C63: Bienes y Servicios | D63: PAC insumos clínicos unidad de enfermería 2026. | E63: Tiras, test rápido, alcohol | F63: 6 | G63: Pedro Fritz | H63: 46054 | I63: DIRECTOR COSAM | J63: 1 | K63: 46054 | L63: 240012
A64: 1057532-335-PC26 | B64: PC26 | C64: Bienes y Servicios | D64: Compra de Insumos de Cafetería reuniones ordinarias anuales Participación, Trato Usuario, Salud Pueblos Originarios | E64: Alimentación | F64: 2 | G64: Daniela Barria | H64: 46082 | I64: Encargada Trato Usuario | J64: 1 | K64: 46082 | L64: 921162
A65: 1057532-335-PC26 | B65: PC26 | C65: Bienes y Servicios | D65: Compra de Insumos de Cafetería reuniones ordinarias anuales Participación, Trato Usuario, Salud Pueblos Originarios | E65: Insumos | F65: 2 | G65: Daniela Barria | H65: 46082 | I65: Encargada Trato Usuario | J65: 1 | K65: 46082 | L65: 86299
A66: 1057532-336-PC26 | B66: PC26 | C66: Bienes y Servicios | D66: Impresión Talonarios de Registro de Solicitudes Ciudadanas | E66: folleteria | F66: 1 | G66: Daniela Barria | H66: 46082 | I66: Encargada Trato Usuario | J66: 1 | K66: 46082 | L66: 400000
A67: 1057532-337-PC26 | B67: PC26 | C67: Bienes y Servicios | D67: INSUMOS DE FARMACIA 2026 | E67: Insumos Computacionales | F67: 5 | G67: Pedro Fritz | H67: 46023 | I67: DIRECTOR COSAM | J67: 1 | K67: 46023 | L67: 104004
A68: 1057532-337-PC26 | B68: PC26 | C68: Bienes y Servicios | D68: INSUMOS DE FARMACIA 2026 | E68: Insumos Computacionales | F68: 5 | G68: Pedro Fritz | H68: 46082 | I68: DIRECTOR COSAM | J68: 1 | K68: 46082 | L68: 1900044
... A87: 1057532-350-PC26 | B87: PC26 | C87: Bienes y Servicios | D87: INSUMOS COMPUTACIONALES | E87: WI FI | F87: 3 | G87: Carolina Silva | H87: 46023 | I87: Encargada De Compras | J87: 1 | K87: 46023 | L87: 900000
A88: 1057532-351-PC26 | B88: PC26 | C88: Bienes y Servicios | D88: Convenio - CONVENIO DE ADQUISICION DE KIT POINT OF CARE (POC) CON ARRIENDO DE EQUIPOS PARA ANALISIS DE MUESTRAS, SSO | E88: Convenio Kit Point | F88: 1 | G88: Sofia Reyes | H88: 46204 | I88: Encargada Apoyo Diagnóstico Laboratorio | J88: 12 | K88: 01-08-2026,01-09-2026,01-10-2026,01-11-2026,01-12-2026,01-01-2027,01-02-2027,01-03-2027,01-04-2027,01-05-2027,01-06-2027,01-07-2027 | L88: 31250000
A89: 1057532-352-PC26 | B89: PC26 | C89: Bienes y Servicios | D89: Muestra tu Pausa Activa | E89: Instrumentos Deportivos | F89: 1 | G89: Marcia Delarze | H89: 46082 | I89: Kinesióloga | J89: 1 | K89: 46082 | L89: 200000
A90: 1057532-353-PC26 | B90: PC26 | C90: Bienes y Servicios | D90: PLAN DE COMPRAS AÑO 2026 LEY N°19.664 Y FORMACION DE ESPECIALISTAS S.S.O | E90: Alimentación | F90: 7 | G90: Jocelyne Prieto | H90: 46054 | I90: Jefa Seccion Gestion Y Desarrollo Ley Medica | J90: 1 | K90: 46054 | L90: 107000
A91: 1057532-353-PC26 | B91: PC26 | C91: Bienes y Servicios | D91: PLAN DE COMPRAS AÑO 2026 LEY N°19.664 Y FORMACION DE ESPECIALISTAS S.S.O | E91: Materiales de Oficina | F91: 7 | G91: Jocelyne Prieto | H91: 46054 | I91: Jefa Seccion Gestion Y Desarrollo Ley Medica | J91: 1 | K91: 46054 | L91: 15000
A92: 1057532-353-PC26 | B92: PC26 | C92: Bienes y Servicios | D92: PLAN DE COMPRAS AÑO 2026 LEY N°19.664 Y FORMACION DE ESPECIALISTAS S.S.O | E92: Menaje Cafeteria | F92: 7 | G92: Jocelyne Prieto | H92: 46054 | I92: Jefa Seccion Gestion Y Desarrollo Ley Medica | J92: 1 | K92: 46054 | L92: 10000
A93: 1057532-353-PC26 | B93: PC26 | C93: Bienes y Servicios | D93: PLAN DE COMPRAS AÑO 2026 LEY N°19.664 Y FORMACION DE ESPECIALISTAS S.S.O | E93: Pendrive | F93: 7 | G93: Jocelyne Prieto | H93: 46143 | I93: Jefa Seccion Gestion Y Desarrollo Ley Medica | J93: 1 | K93: 46143 | L93: 25000
A94: 1057532-353-PC26 | B94: PC26 | C94: Bienes y Servicios | D94: PLAN DE COMPRAS AÑO 2026 LEY N°19.664 Y FORMACION DE ESPECIALISTAS S.S.O | E94: Publicación Diario | F94: 7 | G94: Jocelyne Prieto | H94: 46327 | I94: Jefa Seccion Gestion Y Desarrollo Ley Medica | J94: 1 | K94: 46327 | L94: 120000
A95: 1057532-353-PC26 | B95: PC26 | C95: Bienes y Servicios | D95: PLAN DE COMPRAS AÑO 2026 LEY N°19.664 Y FORMACION DE ESPECIALISTAS S.S.O | E95: Servicio Cafeteria | F95: 7 | G95: Jocelyne Prieto | H95: 46143 | I95: Jefa Seccion Gestion Y Desarrollo Ley Medica | J95: 1 | K95: 46143 | L95: 1400001
A96: 1057532-353-PC26 | B96: PC26 | C96: Bienes y Servicios | D96: PLAN DE COMPRAS AÑO 2026 LEY N°19.664 Y FORMACION DE ESPECIALISTAS S.S.O | E96: Servicio Traslado | F96: 7 | G96: Jocelyne Prieto | H96: 46143 | I96: Jefa Seccion Gestion Y Desarrollo Ley Medica | J96: 1 | K96: 46143 | L96: 45000000
A97: 1057532-354-PC26 | B97: PC26 | C97: Bienes y Servicios | D97: Convenio - COMPRA DE KITS PARA DETECCION DE VIRUS Y BACTERIAS RESPIRATORIAS POR METODO MOLECULAR RAPIDO (POC MOLECULAR) | E97: Convenio Kit Point | F97: 1 | G97: Daniela Soto | H97: 46143 | I97: Encargada Apoyo Diagnóstico Laboratorio | J97: 12 | K97: 01-05-2026,01-06-2026,01-07-2026,01-08-2026,01-09-2026,01-10-2026,01-11-2026,01-12-2026,01-01-2027,01-02-2027,01-03-2027,01-04-2027 | L97: 23333328
A98: 1057532-355-PC26 | B98: PC26 | C98: Bienes y Servicios | D98: MEDICINA INTEGRATIVA SAFU | E98: Aromaterapia | F98: 1 | G98: Lhya Kortmann | H98: 46023 | I98: Enfermera | J98: 1 | K98: 46023 | L98: 681264
A99: 1057532-356-PC24 | B99: Arrastre | C99: Bienes y Servicios | D99: Convenio servicio de guardias para la DSSO y sus establecimientos y dispositivos dependientes | E99: Servicio de guardias | F99: 1 | G99: Lorena Torres Castillo | H99: 45444 | I99: Encargada (S) Sección Administración de Contratos | J99: 24 | K99: 01-01-2025,01-02-2025,01-03-2025,01-04-2025,01-05-2025,01-06-2025,01-07-2025,01-08-2025,01-09-2025,01-10-2025,01-11-2025,01-12-2025,01-01-2026,01-02-2026,01-03-2026,01-04-2026,01-05-2026,01-06-2026,01-07-2026,01-08-2026,01-09-2026,01-10-2026,01-11-2026,01-12-2026 | L99: 905196910
A100: 1057532-356-PC26 | B100: PC26 | C100: Bienes y Servicios | D100: Adquisición Insumos para realizar el aseo y confort de usuarios/as con Dependencia Severa. | E100: Crema | F100: 3 | G100: Camila Alvarez | H100: 46113 | I100: Kinesióloga Encargada Programa Atencion Domiciliaria Para Personas Con Dependencia Severa | J100: 1 | K100: 46113 | L100: 2175000
A101: 1057532-356-PC26 | B101: PC26 | C101: Bienes y Servicios | D101: Adquisición Insumos para realizar el aseo y confort de usuarios/as con Dependencia Severa. | E101: Pañales | F101: 3 | G101: Camila Alvarez | H101: 46113 | I101: Kinesióloga Encargada Programa Atencion Domiciliaria Para Personas Con Dependencia Severa | J101: 1 | K101: 46113 | L101: 8155836
A102: 1057532-356-PC26 | B102: PC26 | C102: Bienes y Servicios | D102: Adquisición Insumos para realizar el aseo y confort de usuarios/as con Dependencia Severa. | E102: Producto de Aseo | F102: 3 | G102: Camila Alvarez | H102: 46113 | I102: Kinesióloga Encargada Programa Atencion Domiciliaria Para Personas Con Dependencia Severa | J102: 1 | K102: 46113 | L102: 1672500
A103: 1057532-357-PC26 | B103: PC26 | C103: Bienes y Servicios | D103: INSUMOS LEY 20.000 | E103: Material de Oficina | F103: 2 | G103: Fernando Roman | H103: 46082 | I103: Jefe Subdepartamento Farmacia | J103: 1 | K103: 46082 | L103: 509936
A104: 1057532-357-PC26 | B104: PC26 | C104: Bienes y Servicios | D104: INSUMOS LEY 20.000 | E104: Toner | F104: 2 | G104: Fernando Roman | H104: 46082 | I104: Jefe Subdepartamento Farmacia | J104: 1 | K104: 46082 | L104: 48000
A105: 1057532-358-PC26 | B105: PC26 | C105: Bienes y Servicios | D105: Zumba a todo corazón | E105: Alimentación | F105: 3 | G105: Daniela Cancino | H105: 46235 | I105: Nutricionista | J105: 1 | K105: 46235 | L105: 185040
A106: 1057532-358-PC26 | B106: PC26 | C106: Bienes y Servicios | D106: Zumba a todo corazón | E106: Decoración | F106: 3 | G106: Daniela Cancino | H106: 46235 | I106: Nutricionista | J106: 1 | K106: 46235 | L106: 270160
A107: 1057532-358-PC26 | B107: PC26 | C107: Bienes y Servicios | D107: Zumba a todo corazón | E107: Instructora | F107: 3 | G107: Daniela Cancino | H107: 46235 | I107: Nutricionista | J107: 1 | K107: 46235 | L107: 220000
A108: 1057532-359-PC26 | B108: PC26 | C108: Bienes y Servicios | D108: Mantenimiento baños y camarines | E108: Mantencion | F108: 1 | G108: Pedro Fritz | H108: 46054 | I108: Director | J108: 1 | K108: 46054 | L108: 700002
A109: 1057532-360-PC26 | B109: PC26 | C109: Bienes y Servicios | D109: Construcción de radieres en estacionamiento | E109: Mantencion | F109: 1 | G109: Pedro Fritz | H109: 46054 | I109: Director | J109: 1 | K109: 46054 | L109: 7000008
A110: 1057532-361-PC26 | B110: PC26 | C110: Bienes y Servicios | D110: Mantención comedor lado patio interior | E110: Mantencion | F110: 1 | G110: Pedro Fritz | H110: 46082 | I110: Director | J110: 1 | K110: 46082 | L110: 800000
A111: 1057532-362-PC26 | B111: PC26 | C111: Bienes y Servicios | D111: Pintado de muros perimetrales de edificio. | E111: Mantencion | F111: 1 | G111: Pedro Fritz | H111: 46054 | I111: Director | J111: 1 | K111: 46054 | L111: 3500000
... A119: 1057532-371-PC26 | B119: PC26 | C119: Bienes y Servicios | D119: Mantenimiento planta elevadora aguas servidas | E119: Mantencion | F119: 1 | G119: Pedro Fritz | H119: 46204 | I119: Director | J119: 1 | K119: 46174 | L119: 1500000
A120: 1057532-372-PC26 | B120: PC26 | C120: Bienes y Servicios | D120: Suministro de Pellet para sistema de calefacción | E120: Pellet | F120: 1 | G120: Pedro Fritz | H120: 46082 | I120: Director | J120: 4 | K120: 01-03-2026,01-05-2026,01-07-2026,01-09-2026 | L120: 17500000
A121: 1057532-373-PC25 | B121: Arrastre | C121: Bienes y Servicios | D121: Convenio - Movilización para el traslado de usuarios y funcionarios CDR adulto mayor Kumelen año 2026 | E121: Movilizacion Kumelen | F121: 1 | G121: Luis Flores Merino | H121: 45839 | I121: Coordinador | J121: 12 | K121: 01-02-2026,01-03-2026,01-04-2026,01-05-2026,01-06-2026,01-07-2026,01-08-2026,01-09-2026,01-10-2026,01-11-2026,01-12-2026,01-01-2027 | L121: 36208337
A122: 1057532-373-PC26 | B122: PC26 | C122: Bienes y Servicios | D122: Suministro de diesel para generador eléctrico | E122: Combustibles | F122: 1 | G122: Pedro Fritz | H122: 46143 | I122: Director | J122: 1 | K122: 46143 | L122: 1820000
A123: 1057532-374-PC25 | B123: Arrastre | C123: Bienes y Servicios | D123: Convenio - Movilizacion para el traslado de funcionarios CDR Adulto Mayor KÜMELEN 2026 | E123: Movilizacion | F123: 1 | G123: Luis Flores Merino | H123: 45870 | I123: Coordinador | J123: 12 | K123: 01-02-2026,01-03-2026,01-04-2026,01-05-2026,01-06-2026,01-07-2026,01-08-2026,01-09-2026,01-10-2026,01-11-2026,01-12-2026,01-01-2027 | L123: 28875000
A124: 1057532-374-PC26 | B124: PC26 | C124: Bienes y Servicios | D124: Reemplazo de equipo iluminación interior. | E124: Mantencion | F124: 1 | G124: Pedro Fritz | H124: 46082 | I124: Director | J124: 1 | K124: 46082 | L124: 1200000
A125: 1057532-375-PC25 | B125: Arrastre | C125: Bienes y Servicios | D125: Convenio - ADQUISICION DE KIT POINT OF CARE (POC) CON ARRIENDO DE EQUIPO PARA ANALISIS DE MUESTRAS POR 12 MESES, SSO | E125: Suministro KIT Point | F125: 1 | G125: SOFIA REYES ALARCON | H125: 45839 | I125: COMPRADOR | J125: 12 | K125: 01-08-2025,01-09-2025,01-10-2025,01-11-2025,01-12-2025,01-01-2026,01-02-2026,01-03-2026,01-04-2026,01-05-2026,01-06-2026,01-07-2026 | L125: 52500000
A126: 1057532-375-PC26 | B126: PC26 | C126: Bienes y Servicios | D126: Mantenimiento sensores de humo | E126: Mantencion | F126: 1 | G126: Pedro Fritz | H126: 46174 | I126: Director | J126: 1 | K126: 46174 | L126: 2500020
A127: 1057532-376-PC25 | B127: Arrastre | C127: Bienes y Servicios | D127: Convenio - Pac PASAJES 2025-2026 DSSO | E127: Pasajes | F127: 1 | G127: Sandra Espinoza | H127: 45809 | I127: PAC Pasajes DSSO 2025-2026 | J127: 18 | K127: 01-07-2025,01-08-2025,01-09-2025,01-10-2025,01-11-2025,01-12-2025,01-01-2026,01-02-2026,01-03-2026,01-04-2026,01-05-2026,01-06-2026,01-07-2026,01-08-2026,01-09-2026,01-10-2026,01-11-2026,01-12-2026 | L127: 11000004
...

Sheet Hoja6
A1: PAC | B1: TIPO PAC | C1: ID Proyecto | D1: Nombre Proyecto | E1: Nombre responsable | F1: Cargo responsable | G1: Cantidad OC | H1: Meses envío OC | I1: Suma de Monto Total Ítem Año 2026
A2: Arrastre | B2: Arrastre | C2: 1057532-156-PC24 | D2: servicios de control de asistencia del servicio de salud osorno | E2: Bruno Ojeda Alvarez | F2: Jefe Depto. Tecnologías de la Información | G2: 36 | H2: 01-01-2024,01-02-2024,01-03-2024,01-04-2024,01-05-2024,01-06-2024,01-07-2024,01-08-2024,01-09-2024,01-10-2024,01-11-2024,01-12-2024,01-01-2025,01-02-2025,01-03-2025,01-04-2025,01-05-2025,01-06-2025,01-07-2025,01-08-2025,01-09-2025,01-10-2025,01-11-2025,01-12-2025,01-01-2026,01-02-2026,01-03-2026,01-04-2026,01-05-2026,01-06-2026,01-07-2026,01-08-2026,01-09-2026,01-10-2026,01-11-2026,01-12-2026 | I2: 30000000
A3: Arrastre | B3: Arrastre | C3: 1057532-162-PC25 | D3: Convenio - de Suministro para adquisición de medicamentos faltantes CENABAST para establecimientos dependientes del SSO. | E3: ELEUTERIO ROMAN | F3: JEFE SUBDEPTO FARMACIA | G3: 24 | H3: 01-05-2025,01-06-2025,01-07-2025,01-08-2025,01-09-2025,01-10-2025,01-11-2025,01-12-2025,01-01-2026,01-02-2026,01-03-2026,01-04-2026,01-05-2026,01-06-2026,01-07-2026,01-08-2026,01-09-2026,01-10-2026,01-11-2026,01-12-2026,01-01-2027,01-02-2027,01-03-2027,01-04-2027 | I3: 75000000
A4: Arrastre | B4: Arrastre | C4: 1057532-163-PC24 | D4: Servicio gestión flota vehicular SSO | E4: Bruno Ojeda Alvarez | F4: Jefe Depto. | G4: 36 | H4: 01-01-2024,01-02-2024,01-03-2024,01-04-2024,01-05-2024,01-06-2024,01-07-2024,01-08-2024,01-09-2024,01-10-2024,01-11-2024,01-12-2024,01-01-2025,01-02-2025,01-03-2025,01-04-2025,01-05-2025,01-06-2025,01-07-2025,01-08-2025,01-09-2025,01-10-2025,01-11-2025,01-12-2025,01-01-2026,01-02-2026,01-03-2026,01-04-2026,01-05-2026,01-06-2026,01-07-2026,01-08-2026,01-09-2026,01-10-2026,01-11-2026,01-12-2026 | I4: 6711996
A5: Arrastre | B5: Arrastre | C5: 1057532-172-PC25 | D5: Convenio - CONVENIO SERVICIO DE ASEO POR 18 MESES, PARA LA DIRECCION DEL SSO Y ESTABLECIMIENTOS DEPENDIENTES DE LA RED ASISTENCIAL | E5: Lorena Torres Castillo | F5: ENCARGADA (S) SECCIÓN DE ADMINISTRACIÓN DE CONTRATOS | G5: 18 | H5: 01-07-2025,01-08-2025,01-09-2025,01-10-2025,01-11-2025,01-12-2025,01-01-2026,01-02-2026,01-03-2026,01-04-2026,01-05-2026,01-06-2026,01-07-2026,01-08-2026,01-09-2026,01-10-2026,01-11-2026,01-12-2026 | I5: 144000000
A6: Arrastre | B6: Arrastre | C6: 1057532-173-PC25 | D6: Convenio - CONVENIO DE ADQUISICION DE KIT POINT OF CARE (POC) CON ARRIENDO DE EQUIPO PARA ANALISIS DE MUESTRAS, SSO | E6: Sofia Reyes | F6: Encargada | G6: 12 | H6: 01-08-2025,01-09-2025,01-10-2025,01-11-2025,01-12-2025,01-01-2026,01-02-2026,01-03-2026,01-04-2026,01-05-2026,01-06-2026,01-07-2026 | I6: 40833335
A7: Arrastre | B7: Arrastre | C7: 1057532-193-PC25 | D7: Convenio - ARRIENDO 159 EQUIPOS PC AIO PARA APOYAR LOS PORCESOS CLINICOS Y ADMINISTRATIVOS | E7: Alvaro Montecinos | F7: Jefe (S) Subdepto. Soporte TIC | G7: 1 | H7: 01-01-2026,01-02-2026,01-03-2026,01-04-2026,01-05-2026,01-06-2026,01-07-2026,01-08-2026,01-09-2026,01-10-2026,01-11-2026,01-12-2026,01-01-2027,01-02-2027,01-03-2027,01-04-2027,01-05-2027,01-06-2027,01-07-2027,01-08-2027,01-09-2027,01-10-2027,01-11-2027,01-12-2027,01-01-2028,01-02-2028,01-03-2028,01-04-2028,01-05-2028,01-06-2028,01-07-2028,01-08-2028 | I7: 74068560
A8: Arrastre | B8: Arrastre | C8: 1057532-193-PC25 | D8: Convenio - ARRIENDO 159 EQUIPOS PC AIO PARA APOYAR LOS PROCESOS CLINICOS Y ADMINISTRATIVOS | E8: Alvaro Montecinos | F8: Jefe (S) Subdepto. Soporte TIC | G8: 32 | H8: 01-01-2026,01-02-2026,01-03-2026,01-04-2026,01-05-2026,01-06-2026,01-07-2026,01-08-2026,01-09-2026,01-10-2026,01-11-2026,01-12-2026,01-01-2027,01-02-2027,01-03-2027,01-04-2027,01-05-2027,01-06-2027,01-07-2027,01-08-2027,01-09-2027,01-10-2027,01-11-2027,01-12-2027,01-01-2028,01-02-2028,01-03-2028,01-04-2028,01-05-2028,01-06-2028,01-07-2028,01-08-2028 | I8: 37034280
A9: Arrastre | B9: Arrastre | C9: 1057532-195-PC25 | D9: Convenio - SERVICIO DE ASEO PARA LA DSSO (BASE SAMU, EDIFICIO PLAZA SUR Y EDIFICIO M. RODRIGUEZ) POR 18 MESES (DESDE 01 JULIO 2025) | E9: Lorena Torres Castillo | F9: Encargada (S) Sección Administración de Contratos | G9: 18 | H9: 01-07-2025,01-08-2025,01-09-2025,01-10-2025,01-11-2025,01-12-2025,01-01-2026,01-02-2026,01-03-2026,01-04-2026,01-05-2026,01-06-2026,01-07-2026,01-08-2026,01-09-2026,01-10-2026,01-11-2026,01-12-2026 | I9: 70333380
A10: Arrastre | B10: Arrastre | C10: 1057532-196-PC25 | D10: Convenio - SERVICIO DE SOPORTE Y MANTENCION RPT VHF SSO (PERIODO DOS AÑOS) | E10: ESTEBAN ALARCON BOHLE | F10: TECNICO RADIOCOMUNICACIONES | G10: 24 | H10: 01-01-2025,01-02-2025,01-03-2025,01-04-2025,01-05-2025,01-06-2025,01-07-2025,01-08-2025,01-09-2025,01-10-2025,01-11-2025,01-12-2025,01-01-2026,01-02-2026,01-03-2026,01-04-2026,01-05-2026,01-06-2026,01-07-2026,01-08-2026,01-09-2026,01-10-2026,01-11-2026,01-12-2026 | I10: 6255504
A11: Arrastre | B11: Arrastre | C11: 1057532-1-PC24 | D11: Sistema control de flota vehicular del Servicio de Salud Osorno | E11: Felipe Salvo Barriga | F11: Enc. Sección Mant. de Vehículos | G11: 36 | H11: 01-01-2024,01-02-2024,01-03-2024,01-04-2024,01-05-2024,01-06-2024,01-07-2024,01-08-2024,01-09-2024,01-10-2024,01-11-2024,01-12-2024,01-01-2025,01-02-2025,01-03-2025,01-04-2025,01-05-2025,01-06-2025,01-07-2025,01-08-2025,01-09-2025,01-10-2025,01-11-2025,01-12-2025,01-01-2026,01-02-2026,01-03-2026,01-04-2026,01-05-2026,01-06-2026,01-07-2026,01-08-2026,01-09-2026,01-10-2026,01-11-2026,01-12-2026 | I11: 6712008
A12: Arrastre | B12: Arrastre | C12: 1057532-209-PC25 | D12: Convenio - ADQUISICION DE 3 CUPOS DE RESIDENCIA PROTEGIDA PARA EL SERVICIO DE SALUD OSORNO EN LA PROVINCIA DE CONCEPCIÓN | E12: Angelo Palma | F12: Jefe (s) Subdepto. Gestión Clínica y Administrativa Red Temática de Salud Mental de Especialidad | G12: 24 | H12: 01-01-2025,01-02-2025,01-03-2025,01-04-2025,01-05-2025,01-06-2025,01-07-2025,01-08-2025,01-09-2025,01-10-2025,01-11-2025,01-12-2025,01-01-2026,01-02-2026,01-03-2026,01-04-2026,01-05-2026,01-06-2026,01-07-2026,01-08-2026,01-09-2026,01-10-2026,01-11-2026,01-12-2026 | I12: 48115128
A13: Arrastre | B13: Arrastre | C13: 1057532-210-PC25 | D13: Convenio - ADQUISICION DE 12 CUPOS DE RESIDENCIA PROTEGIDA PARA EL SERVICIO DE SALUD OSORNO EN LA CIUDAD DE OSORNO | E13: Angelo Palma | F13: Jefe (s) Subdepto. Gestión Clínica y Administrativa Red Temática de Salud Mental de Especialidad | G13: 24 | H13: 01-01-2025,01-02-2025,01-03-2025,01-04-2025,01-05-2025,01-06-2025,01-07-2025,01-08-2025,01-09-2025,01-10-2025,01-11-2025,01-12-2025,01-01-2026,01-02-2026,01-03-2026,01-04-2026,01-05-2026,01-06-2026,01-07-2026,01-08-2026,01-09-2026,01-10-2026,01-11-2026,01-12-2026 | I13: 237155100
... A71: Arrastre | B71: Arrastre | C71: 1077241-53-PC25 | D71: Convenio - Servicio de arriendo e informes de teleelectrocardiografía (sospecha IAM), para 13 establecimientos de urgencia de APS | E71: Consuelo Cordova | F71: jefa subdepto gestión de programas en curso de vida | G71: 12 | H71: 01-02-2026,01-03-2026,01-04-2026,01-05-2026,01-06-2026,01-07-2026,01-08-2026,01-09-2026,01-10-2026,01-11-2026,01-12-2026,01-01-2027 | I71: 30800000
A72: PC26 | B72: Activos Fijos | C72: 1057922-10-PC26 | D72: REPOSICION CESFAM CON SAR RAHUE ALTO, OSORNO | E72: Maria Elena Muñoz | F72: Jefa (S) Sub. Dpto. De Inversiones De Equipos Y Equipamiento | G72: 1 | H72: 46113 | I72: 1578831000
A73: PC26 | B73: Activos Fijos | C73: 1057922-11-PC26 | D73: HABILITACION ANGIOGRAFO HOSPITAL BASE DE OSORNO | E73: Maria Elena Muñoz | F73: Jefa (S) Sub. Dpto. De Inversiones De Equipos Y Equipamiento | G73: 1 | H73: 46113 | I73: 1969068000
A74: PC26 | B74: Activos Fijos | C74: 1057922-12-PC26 | D74: CONSTRUCCION COSAM RAHUE, COMUNA OSORNO | E74: Maria Elena Muñoz | F74: Jefa (S) Sub. Dpto. De Inversiones De Equipos Y Equipamiento | G74: 1 | H74: 46113 | I74: 18632000
A75: PC26 | B75: Activos Fijos | C75: 1057922-13-PC26 | D75: SUBTÍTULO 29 SECTORIAL 2026 | E75: Maria Elena Muñoz | F75: Jefa (S) Sub. Dpto. De Inversiones De Equipos Y Equipamiento | G75: 1 | H75: 46113 | I75: 280000000
A76: PC26 | B76: Activos Fijos | C76: 1057922-14-PC26 | D76: SUBTÍTULO 29 OPERACIONAL SSO 2026 | E76: Maria Elena Muñoz | F76: Jefa (S) Sub. Dpto. De Inversiones De Equipos Y Equipamiento | G76: 1 | H76: 46143 | I76: 61000000
A77: PC26 | B77: Activos Fijos | C77: 1057922-15-PC26 | D77: Equipamiento Ergonómico - Sillas | E77: Venecia Recabarren | F77: Jefatura Unidad Prev. Riesgos | G77: 1 | H77: 46023 | I77: 1000000
A78: PC26 | B78: Activos Fijos | C78: 1057922-16-PC26 | D78: Adquisición de micrófono y cámara para videoconferencias del Centro Comunitario Kümelen | E78: Luis Flores | F78: Coordinador | G78: 1 | H78: 46054 | I78: 250000
A79: PC26 | B79: Activos Fijos | C79: 1057922-17-PC26 | D79: Adquisición de megáfonos y gabinetes para la comunicación en emergencias, gestión de riesgos y protección de equipos | E79: Yuvit Garcia-Chacur | F79: DIRECTORA | G79: 1 | H79: 46023 | I79: 780000
A80: PC26 | B80: Activos Fijos | C80: 1057922-18-PC26 | D80: REPOSICION CECOSF EL ENCANTO, COMUNA DE PUYEHUE | E80: Maria Elena Muñoz | F80: Jefa (S) Sub. Dpto. De Inversiones De Equipos Y Equipamiento | G80: 1 | H80: 46113 | I80: 6773000
A81: PC26 | B81: Activos Fijos | C81: 1057922-19-PC26 | D81: Adquisición de productos e insumos para el programa de control y eliminación de la Tuberculosis | E81: NMaria Paz Gomez | F81: Referente Programa De Tuberculosis | G81: 1 | H81: 46174 | I81: 19000000
A82: PC26 | B82: Activos Fijos | C82: 1057922-20-PC26 | D82: Adquisición de herramientas | E82: Pedro Fritz | F82: Director | G82: 1 | H82: 46023 | I82: 300000
A83: PC26 | B83: Activos Fijos | C83: 1057922-21-PC26 | D83: Adquisicion equipamiento Servidor NAS y almacenamiento extra para respaldo y seguridad de la información | E83: Alejandro Nuñez | F83: Encargado Gestión De Sistemas | G83: 1 | H83: 46082 | I83: 16000000
... A106: PC26 | B106: Administración de Fondos | C106: 1077241-112-PC26 | D106: ARTICULOS DE COCINA RESIDENCIAL ? CONVENIO SENDA | E106: Carolina Silva | F106: Encargada De Compras | G106: 1 | H106: 46143 | I106: 280008
A107: PC26 | B107: Administración de Fondos | C107: 1077241-61-PC26 | D107: Adquisición de prestaciones de rehabilitación integral a niños, niñas y adolescentes con Trastorno del Espectro Autista | E107: Karin Avila | F107: Referente Rehabilitación Integral | G107: 10 | H107: 01-03-2026,01-04-2026,01-05-2026,01-06-2026,01-07-2026,01-08-2026,01-09-2026,01-10-2026,01-11-2026,01-12-2026 | I107: 56320000
A108: PC26 | B108: Administración de Fondos | C108: 1077241-62-PC26 | D108: PRAPS Fondo de Farmacia para enfermedades crónicas no transmisibles en APS (FOFAR) | E108: Chessarina Tuchie Fischer | F108: Encargada Programa Fofar | G108: 1 | H108: 46113 | I108: 30000000
A109: PC26 | B109: Administración de Fondos | C109: 1077241-62-PC26 | D109: PRAPS Fondo de Farmacia para enfermedades crónicas no transmisibles en APS (FOFAR) | E109: Chessarina Tuchie Fischer | F109: Encargada Programa Fofar | G109: 1 | H109: 46143 | I109: 30000000
A110: PC26 | B110: Administración de Fondos | C110: 1077241-63-PC26 | D110: Adquisición de insumos para la atención en domicilio del Equipo Rehabilitación Rural SSO. | E110: Karin Avila | F110: Referente Rehabilitación Integral | G110: 1 | H110: 46082 | I110: 410000
A111: PC26 | B111: Administración de Fondos | C111: 1077241-64-PC26 | D111: Ceremonia de alta SENDA-PAI COSAM Rahue 2026 | E111: Camilo Martínez | F111: Director(S) | G111: 1 | H111: 46235 | I111: 225000
A112: PC26 | B112: Administración de Fondos | C112: 1077241-65-PC26 | D112: Anilladora e insumos para preparación de material Cosam Rahue. Fondo extrapresupuestarios SENDA PAI | E112: Camilo Martínez | F112: Director(S) | G112: 1 | H112: 46054 | I112: 260000
A113: PC26 | B113: Administración de Fondos | C113: 1077241-66-PC26 | D113: Jornada de Autocuidado funcionarios COSAM Rahue, con cargo a fondo extrapresupuestario SENDA-PAI | E113: Camilo Martínez | F113: Director(S) | G113: 1 | H113: 46174 | I113: 450000
A114: PC26 | B114: Administración de Fondos | C114: 1077241-66-PC26 | D114: Jornada de Autocuidado funcionarios COSAM Rahue, con cargo a fondo extrapresupuestario SENDA-PAI | E114: Camilo Martínez | F114: Director(S) | G114: 1 | H114: 46357 | I114: 450000
A115: PC26 | B115: Administración de Fondos | C115: 1077241-67-PC26 | D115: Celebración fiestas patrias usuarios y cuidadores COSAM RAHUE. | E115: Camilo Martínez | F115: Director(S) | G115: 1 | H115: 46266 | I115: 625000
A116: PC26 | B116: Administración de Fondos | C116: 1077241-68-PC26 | D116: Adquisición de insumos para la atención en domicilio del Equipo Rehabilitación Rural SSO (material Ergoterapia) | E116: Karin Avila | F116: Referente Rehabilitación Integral | G116: 1 | H116: 46082 | I116: 150000
A117: PC26 | B117: Administración de Fondos | C117: 1077241-69-PC26 | D117: Insumos cafetería actividades con usuarios Cosam Rahue y comunidad 2026, fondo extrapresupuestario SENDA PAI | E117: Camilo Martínez | F117: Director(S) | G117: 1 | H117: 46023 | I117: 2772880
A118: PC26 | B118: Administración de Fondos | C118: 1077241-70-PC26 | D118: INSUMOS ESCRITORIO COSAM RAHUE, FONDO EXTRAPRESUPUESTARIO SENDA-PAI | E118: Camilo Martínez | F118: Director(S) | G118: 1 | H118: 46082 | I118: 1468231
A119: PC26 | B119: Administración de Fondos | C119: 1077241-71-PC26 | D119: Compra de tintas de repuesto impresoras Cosam Rahue | E119: Camilo Martínez | F119: Director(S) | G119: 1 | H119: 46113 | I119: 350000
... A153: PC26 | B153: Bienes y Servicios | C153: 1057532-288-PC26 | D153: Jornadas de encuentro y autocuidado Para usuarios y cuidadores ?SALUDABLE-MENTE en dispositivo COSAM RAHUE 2026 | E153: Camilo Martínez | F153: Director(S) | G153: 1 | H153: 46357 | I153: 135000
A154: PC26 | B154: Bienes y Servicios | C154: 1057532-288-PC26 | D154: Jornadas de encuentro y autocuidado Para usuarios y cuidadores ?SALUDABLE-MENTE en dispositivo COSAM RAHUE 2026 | E154: Camilo Martínez | F154: Director(S) | G154: 3 | H154: 01-07-2026,01-09-2026,01-12-2026 | I154: 405000
A155: PC26 | B155: Bienes y Servicios | C155: 1057532-317-PC26 | D155: ?Eco-huerto sustentable -Sistema de acuaponía sin suelo? COSAM RAHUE 2026 | E155: Camilo Martínez | F155: Director(S) | G155: 1 | H155: 46082 | I155: 1500000
A156: PC26 | B156: Bienes y Servicios | C156: 1057532-320-PC26 | D156: Insumos y medicamentos Farmacia COSAM RAHUE | E156: Camilo Martínez | F156: Director(S) | G156: 1 | H156: 46023 | I156: 850000
A157: PC26 | B157: Bienes y Servicios | C157: 1057532-321-PC26 | D157: Capacitación en Salud Mental Intercultural COSAM Rahue. | E157: Camilo Martínez | F157: Director(S) | G157: 1 | H157: 46143 | I157: 900000
A158: PC26 | B158: Bienes y Servicios | C158: 1057532-322-PC26 | D158: Celebración de We Tripantu en COSAM Rahue 2026 | E158: Camilo Martínez | F158: Director(S) | G158: 1 | H158: 46174 | I158: 630000
A159: PC26 | B159: Bienes y Servicios | C159: 1057532-323-PC26 | D159: Jornadas de autocuidado equipo profesional PAI COSAM Rahue | E159: Camilo Martínez | F159: Director(S) | G159: 1 | H159: 46235 | I159: 135000
A160: PC26 | B160: Bienes y Servicios | C160: 1057532-324-PC26 | D160: CONVENIO - ADQUISICION DE 8 CUPOS HOGAR PROTEGIDO MUJERES PARA EL SERVICIO DE SALUD OSORNO POR PERIODO DE 12 MESES | E160: Angelo Palma | F160: Coordinador Unidad de Gestión de Procesos Clínicos de Atención de Especialidad Ambulatoria, Cerrada | G160: 12 | H160: 01-03-2026,01-04-2026,01-05-2026,01-06-2026,01-07-2026,01-08-2026,01-09-2026,01-10-2026,01-11-2026,01-12-2026,01-01-2027,01-02-2027 | I160: 101193519
A161: PC26 | B161: Bienes y Servicios | C161: 1057532-325-PC26 | D161: SERVICIO CAFETERÍA CEREMONIA ANIVERSARIO COSAM RAHUE | E161: Camilo Martínez | F161: Director(S) | G161: 1 | H161: 46143 | I161: 675000
A162: PC26 | B162: Bienes y Servicios | C162: 1057532-326-PC26 | D162: Adquisición de insumos para la atención en domicilio del Equipo Rehabilitación Rural SSO. (Articulos de Libreria) | E162: Karin Avila | F162: Referente Rehabilitación Integral | G162: 1 | H162: 46082 | I162: 190000
A163: PC26 | B163: Bienes y Servicios | C163: 1057532-327-PC26 | D163: Convenio - 3 CUPOS DE RESIDENCIA PROTEGIDA PARA EL SERVICIO DE SALUD OSORNO EN LA PROVINCIA DE CONCEPCIÓN, POR PERIODO DE 24 MESES. | E163: Angelo Palma | F163: Coordinador Unidad de Gestión de Procesos Clínicos de Atención de Especialidad Ambulatoria, Cerrada | G163: 24 | H163: 01-03-2026,01-04-2026,01-05-2026,01-06-2026,01-07-2026,01-08-2026,01-09-2026,01-10-2026,01-11-2026,01-12-2026,01-01-2027,01-02-2027,01-03-2027,01-04-2027,01-05-2027,01-06-2027,01-07-2027,01-08-2027,01-09-2027,01-10-2027,01-11-2027,01-12-2027,01-01-2028,01-02-2028 | I163: 49483210
A164: PC26 | B164: Bienes y Servicios | C164: 1057532-328-PC26 | D164: Rollos Etiquetas para impresora ZEBRA ZD 220 y rollos de cinta para impresora SOME, COSAM RAHUE | E164: Camilo Martínez | F164: Director(S) | G164: 1 | H164: 46023 | I164: 430010
A165: PC26 | B165: Bienes y Servicios | C165: 1057532-329-PC26 | D165: Convenio - 10 CUPOS RESIDENCIA PROTEGIDA DE ALTA COMPLEJIDAD PARA EL SERVICIO DE SALUD OSORNO POR PERIODO DE 12 MESES. | E165: Angelo Palma | F165: Coordinador Unidad de Gestión de Procesos Clínicos de Atención de Especialidad Ambulatoria, Cerrada | G165: 12 | H165: 01-03-2026,01-04-2026,01-05-2026,01-06-2026,01-07-2026,01-08-2026,01-09-2026,01-10-2026,01-11-2026,01-12-2026,01-01-2027,01-02-2027 | I165: 247689000
A166: PC26 | B166: Bienes y Servicios | C166: 1057532-330-PC26 | D166: INSUMOS DE ASEO COSAM RAHUE | E166: Camilo Martínez | F166: Director(S) | G166: 1 | H166: 46082 | I166: 990002
A167: PC26 | B167: Bienes y Servicios | C167: 1057532-331-PC26 | D167: Compra de Insumos de Cafetería reuniones ordinarias anuales de Salud Pueblos Originarios | E167: Pedro Huito | F167: Apoyo Salud Intercultural | G167: 1 | H167: 46082 | I167: 1352694
A168: PC26 | B168: Bienes y Servicios | C168: 1057532-332-PC26 | D168: Protectores solares FPS 50 para funcionarios y usuarios taller huerto | E168: Camilo Martínez | F168: Director(S) | G168: 1 | H168: 46023 | I168: 300000
A169: PC26 | B169: Bienes y Servicios | C169: 1057532-333-PC26 | D169: TEST DE DETECCION DE DROGAS | E169: Carolina Silva | F169: Encargada De Compras | G169: 1 | H169: 46296 | I169: 800000
A170: PC26 | B170: Bienes y Servicios | C170: 1057532-334-PC26 | D170: PAC insumos clínicos unidad de enfermería 2026. | E170: Pedro Fritz | F170: DIRECTOR COSAM | G170: 1 | H170: 46054 | I170: 1166048
A171: PC26 | B171: Bienes y Servicios | C171: 1057532-335-PC26 | D171: Compra de Insumos de Cafetería reuniones ordinarias anuales Participación, Trato Usuario, Salud Pueblos Originarios | E171: Daniela Barria | F171: Encargada Trato Usuario | G171: 1 | H171: 46082 | I171: 1007461
A172: PC26 | B172: Bienes y Servicios | C172: 1057532-336-PC26 | D172: Impresión Talonarios de Registro de Solicitudes Ciudadanas | E172: Daniela Barria | F172: Encargada Trato Usuario | G172: 1 | H172: 46082 | I172: 400000
A173: PC26 | B173: Bienes y Servicios | C173: 1057532-337-PC26 | D173: INSUMOS DE FARMACIA 2026 | E173: Pedro Fritz | F173: DIRECTOR COSAM | G173: 1 | H173: 46023 | I173: 1854004
A174: PC26 | B174: Bienes y Servicios | C174: 1057532-337-PC26 | D174: INSUMOS DE FARMACIA 2026 | E174: Pedro Fritz | F174: DIRECTOR COSAM | G174: 1 | H174: 46082 | I174: 1900044
A175: PC26 | B175: Bienes y Servicios | C175: 1057532-337-PC26 | D175: INSUMOS DE FARMACIA 2026 | E175: Pedro Fritz | F175: DIRECTOR COSAM | G175: 1 | H175: 46113 | I175: 1450010
A176: PC26 | B176: Bienes y Servicios | C176: 1057532-338-PC26 | D176: ACTIVIDADES DE DIFUSIÓN Y DE PREVENCIÓN EN LA PROVINCIA DE OSORNO | E176: Carolina Silva | F176: Encargada De Compras | G176: 1 | H176: 46023 | I176: 150000
A177: PC26 | B177: Bienes y Servicios | C177: 1057532-338-PC26 | D177: ACTIVIDADES DE DIFUSIÓN Y DE PREVENCIÓN EN LA PROVINCIA DE OSORNO | E177: Carolina Silva | F177: Encargada De Compras | G177: 1 | H177: 46082 | I177: 1547066
... A187: PC26 | B187: Bienes y Servicios | C187: 1057532-350-PC26 | D187: INSUMOS COMPUTACIONALES | E187: Carolina Silva | F187: Encargada De Compras | G187: 1 | H187: 46174 | I187: 800000
A188: PC26 | B188: Bienes y Servicios | C188: 1057532-351-PC26 | D188: Convenio - CONVENIO DE ADQUISICION DE KIT POINT OF CARE (POC) CON ARRIENDO DE EQUIPOS PARA ANALISIS DE MUESTRAS, SSO | E188: Sofia Reyes | F188: Encargada Apoyo Diagnóstico Laboratorio | G188: 12 | H188: 01-08-2026,01-09-2026,01-10-2026,01-11-2026,01-12-2026,01-01-2027,01-02-2027,01-03-2027,01-04-2027,01-05-2027,01-06-2027,01-07-2027 | I188: 31250000
A189: PC26 | B189: Bienes y Servicios | C189: 1057532-352-PC26 | D189: Muestra tu Pausa Activa | E189: Marcia Delarze | F189: Kinesióloga | G189: 1 | H189: 46082 | I189: 200000
A190: PC26 | B190: Bienes y Servicios | C190: 1057532-353-PC26 | D190: PLAN DE COMPRAS AÑO 2026 LEY N°19.664 Y FORMACION DE ESPECIALISTAS S.S.O | E190: Jocelyne Prieto | F190: Jefa Seccion Gestion Y Desarrollo Ley Medica | G190: 1 | H190: 46054 | I190: 132000
A191: PC26 | B191: Bienes y Servicios | C191: 1057532-353-PC26 | D191: PLAN DE COMPRAS AÑO 2026 LEY N°19.664 Y FORMACION DE ESPECIALISTAS S.S.O | E191: Jocelyne Prieto | F191: Jefa Seccion Gestion Y Desarrollo Ley Medica | G191: 1 | H191: 46143 | I191: 46425001
A192: PC26 | B192: Bienes y Servicios | C192: 1057532-353-PC26 | D192: PLAN DE COMPRAS AÑO 2026 LEY N°19.664 Y FORMACION DE ESPECIALISTAS S.S.O | E192: Jocelyne Prieto | F192: Jefa Seccion Gestion Y Desarrollo Ley Medica | G192: 1 | H192: 46327 | I192: 120000
A193: PC26 | B193: Bienes y Servicios | C193: 1057532-354-PC26 | D193: Convenio - COMPRA DE KITS PARA DETECCION DE VIRUS Y BACTERIAS RESPIRATORIAS POR METODO MOLECULAR RAPIDO (POC MOLECULAR) | E193: Daniela Soto | F193: Encargada Apoyo Diagnóstico Laboratorio | G193: 12 | H193: 01-05-2026,01-06-2026,01-07-2026,01-08-2026,01-09-2026,01-10-2026,01-11-2026,01-12-2026,01-01-2027,01-02-2027,01-03-2027,01-04-2027 | I193: 23333328
A194: PC26 | B194: Bienes y Servicios | C194: 1057532-355-PC26 | D194: MEDICINA INTEGRATIVA SAFU | E194: Lhya Kortmann | F194: Enfermera | G194: 1 | H194: 46023 | I194: 681264
A195: PC26 | B195: Bienes y Servicios | C195: 1057532-356-PC26 | D195: Adquisición Insumos para realizar el aseo y confort de usuarios/as con Dependencia Severa. | E195: Camila Alvarez | F195: Kinesióloga Encargada Programa Atencion Domiciliaria Para Personas Con Dependencia Severa | G195: 1 | H195: 46113 | I195: 12003336
A196: PC26 | B196: Bienes y Servicios | C196: 1057532-357-PC26 | D196: INSUMOS LEY 20.000 | E196: Fernando Roman | F196: Jefe Subdepartamento Farmacia | G196: 1 | H196: 46082 | I196: 557936
A197: PC26 | B197: Bienes y Servicios | C197: 1057532-358-PC26 | D197: Zumba a todo corazón | E197: Daniela Cancino | F197: Nutricionista | G197: 1 | H197: 46235 | I197: 675200
A198: PC26 | B198: Bienes y Servicios | C198: 1057532-359-PC26 | D198: Mantenimiento baños y camarines | E198: Pedro Fritz | F198: Director | G198: 1 | H198: 46054 | I198: 700002
A199: PC26 | B199: Bienes y Servicios | C199: 1057532-360-PC26 | D199: Construcción de radieres en estacionamiento | E199: Pedro Fritz | F199: Director | G199: 1 | H199: 46054 | I199: 7000008
A200: PC26 | B200: Bienes y Servicios | C200: 1057532-361-PC26 | D200: Mantención comedor lado patio interior | E200: Pedro Fritz | F200: Director | G200: 1 | H200: 46082 | I200: 800000
A201: PC26 | B201: Bienes y Servicios | C201: 1057532-362-PC26 | D201: Pintado de muros perimetrales de edificio. | E201: Pedro Fritz | F201: Director | G201: 1 | H201: 46054 | I201: 3500000
A202: PC26 | B202: Bienes y Servicios | C202: 1057532-363-PC26 | D202: Mantenimiento caseta de guardias | E202: Pedro Fritz | F202: Director | G202: 1 | H202: 46082 | I202: 2000000
A203: PC26 | B203: Bienes y Servicios | C203: 1057532-364-PC26 | D203: Instalación de manillas en puertas metálicas de sala REAS, Caldera, Generador | E203: Pedro Fritz | F203: Director | G203: 1 | H203: 46113 | I203: 800004
A204: PC26 | B204: Bienes y Servicios | C204: 1057532-366-PC26 | D204: Reparar fuga red de agua alimentación invernadero. | E204: Pedro Fritz | F204: Director | G204: 1 | H204: 46023 | I204: 600000
A205: PC26 | B205: Bienes y Servicios | C205: 1057532-367-PC26 | D205: Habilitación de sala pagoda como sala de recuperación pacientes. | E205: Pedro Fritz | F205: Director | G205: 1 | H205: 46204 | I205: 4000000
... A209: PC26 | B209: Bienes y Servicios | C209: 1057532-371-PC26 | D209: Mantenimiento planta elevadora aguas servidas | E209: Pedro Fritz | F209: Director | G209: 1 | H209: 46174 | I209: 1500000
A210: PC26 | B210: Bienes y Servicios | C210: 1057532-372-PC26 | D210: Suministro de Pellet para sistema de calefacción | E210: Pedro Fritz | F210: Director | G210: 4 | H210: 01-03-2026,01-05-2026,01-07-2026,01-09-2026 | I210: 17500000
A211: PC26 | B211: Bienes y Servicios | C211: 1057532-373-PC26 | D211: Suministro de diesel para generador eléctrico | E211: Pedro Fritz | F211: Director | G211: 1 | H211: 46143 | I211: 1820000
A212: PC26 | B212: Bienes y Servicios | C212: 1057532-374-PC26 | D212: Reemplazo de equipo iluminación interior. | E212: Pedro Fritz | F212: Director | G212: 1 | H212: 46082 | I212: 1200000
A213: PC26 | B213: Bienes y Servicios | C213: 1057532-375-PC26 | D213: Mantenimiento sensores de humo | E213: Pedro Fritz | F213: Director | G213: 1 | H213: 46174 | I213: 2500020
A214: PC26 | B214: Bienes y Servicios | C214: 1057532-376-PC26 | D214: Mantenimiento sistema de cierre/apertura puertas de PVC | E214: Pedro Fritz | F214: Director | G214: 1 | H214: 46235 | I214: 2500000
A215: PC26 | B215: Bienes y Servicios | C215: 1057532-377-PC26 | D215: Mantención de enchufes e interruptores lampistería instalación interior. | E215: Pedro Fritz | F215: Director | G215: 1 | H215: 46235 | I215: 2500000
A216: PC26 | B216: Bienes y Servicios | C216: 1057532-378-PC26 | D216: MOVIL AÑO 2027 | E216: Pedro Fritz | F216: DIRECTOR COSAM | G216: 12 | H216: 01-01-2027,01-02-2027,01-03-2027,01-04-2027,01-05-2027,01-06-2027,01-07-2027,01-08-2027,01-09-2027,01-10-2027,01-11-2027,01-12-2027 | I216: 0
A217: PC26 | B217: Bienes y Servicios | C217: 1057532-379-PC26 | D217: Materiales de Secretaria para uso del Cosam 2026 | E217: Pedro Fritz | F217: DIRECTOR COSAM | G217: 1 | H217: 46082 | I217: 816730
A218: PC26 | B218: Bienes y Servicios | C218: 1057532-380-PC26 | D218: Convenio - Convenio Adquisición de combustible móviles de la DSSO y Ambulancias SAMU año 2026 | E218: Pablo Oyarzo | F218: Encargado (S) Administracion Interna | G218: 12 | H218: 01-01-2026,01-02-2026,01-03-2026,01-04-2026,01-05-2026,01-06-2026,01-07-2026,01-08-2026,01-09-2026,01-10-2026,01-11-2026,01-12-2026 | I218: 60000000
A219: PC26 | B219: Bienes y Servicios | C219: 1057532-381-PC26 | D219: Convenio - Convenio Adquisición de combustible Diesel para equipos generadores dispositivos del SSO Cosam Rahue y Cosam Oriente | E219: Pablo Oyarzo | F219: Encargado (S) Administración Interna | G219: 12 | H219: 01-01-2026,01-02-2026,01-03-2026,01-04-2026,01-05-2026,01-06-2026,01-07-2026,01-08-2026,01-09-2026,01-10-2026,01-11-2026,01-12-2026 | I219: 11000000
A220: PC26 | B220: Bienes y Servicios | C220: 1057532-383-PC26 | D220: Jornada de Buenas Prácticas en Hospital Amigo y Ley Mila 2026 | E220: Daniela Barria | F220: Encargada Trato Usuario | G220: 1 | H220: 46296 | I220: 510006
A221: PC26 | B221: Bienes y Servicios | C221: 1057532-384-PC26 | D221: Jornada de Evaluación Comité de Gestión Usuaria 2026 | E221: Daniela Barria | F221: Encargada Trato Usuario | G221: 1 | H221: 46296 | I221: 450000
A222: PC26 | B222: Bienes y Servicios | C222: 1057532-385-PC26 | D222: Recetarios Médicos SAFU | E222: Lhya Kortmann | F222: Enfermera | G222: 1 | H222: 46023 | I222: 450000
A223: PC26 | B223: Bienes y Servicios | C223: 1057532-386-PC26 | D223: MATERIALES DE OFICINA | E223: Venecia Recabarren | F223: Jefatura Unidad Prev. Riesgos | G223: 1 | H223: 46054 | I223: 169000
A224: PC26 | B224: Bienes y Servicios | C224: 1057532-387-PC26 | D224: Vestuario y equipamiento Tecnico Referentes Prevención de Riesgos DSSO | E224: Venecia Recabarren | F224: Jefatura Unidad Prev. Riesgos | G224: 1 | H224: 46082 | I224: 100000
...

Sheet Hoja16
A3: Unidad de Compra | B3: Proyectos | C3: Monto
A4: Bienes y Servicios | B4: 238 | C4: 1932801598
A5: Activos Fijos | B5: 18 | C5: 4545805005
A6: Administración de Fondos | B6: 47 | C6: 216217147
A7: Bienestar | B7: 1 | C7: 156000000
A8: Compras Convenio GORE Region de Los Lagos | B8: 16 | C8: 1438588008
A9: Obras Civiles | B9: 14 | C9: 7264673295
A10: Proyectos de Arrastre | B10: 59 | C10: 6588447864
A11: Total general | B11: 393 | C11: 22142532917

Sheet TD
A1: PAC | B1: TIPO PAC | C1: ID Proyecto | D1: Nombre Proyecto | E1: Nombre responsable | F1: Cargo responsable | G1: Suma de Monto Total Ítem Año 2026
A2: Arrastre | B2: Arrastre | C2: 1057532-156-PC24 | D2: servicios de control de asistencia del servicio de salud osorno | E2: Bruno Ojeda Alvarez | F2: Jefe Depto. Tecnologías de la Información | G2: 30000000
A3: Arrastre | B3: Arrastre | C3: 1057532-162-PC25 | D3: Convenio - de Suministro para adquisición de medicamentos faltantes CENABAST para establecimientos dependientes del SSO. | E3: ELEUTERIO ROMAN | F3: JEFE SUBDEPTO FARMACIA | G3: 75000000
A4: Arrastre | B4: Arrastre | C4: 1057532-163-PC24 | D4: Servicio gestión flota vehicular SSO | E4: Bruno Ojeda Alvarez | F4: Jefe Depto. | G4: 6711996
A5: Arrastre | B5: Arrastre | C5: 1057532-172-PC25 | D5: Convenio - CONVENIO SERVICIO DE ASEO POR 18 MESES, PARA LA DIRECCION DEL SSO Y ESTABLECIMIENTOS DEPENDIENTES DE LA RED ASISTENCIAL | E5: Lorena Torres Castillo | F5: ENCARGADA (S) SECCIÓN DE ADMINISTRACIÓN DE CONTRATOS | G5: 144000000
A6: Arrastre | B6: Arrastre | C6: 1057532-173-PC25 | D6: Convenio - CONVENIO DE ADQUISICION DE KIT POINT OF CARE (POC) CON ARRIENDO DE EQUIPO PARA ANALISIS DE MUESTRAS, SSO | E6: Sofia Reyes | F6: Encargada | G6: 40833335
A7: Arrastre | B7: Arrastre | C7: 1057532-193-PC25 | D7: Convenio - ARRIENDO 159 EQUIPOS PC AIO PARA APOYAR LOS PORCESOS CLINICOS Y ADMINISTRATIVOS | E7: Alvaro Montecinos | F7: Jefe (S) Subdepto. Soporte TIC | G7: 111102840
A8: Arrastre | B8: Arrastre | C8: 1057532-195-PC25 | D8: Convenio - SERVICIO DE ASEO PARA LA DSSO (BASE SAMU, EDIFICIO PLAZA SUR Y EDIFICIO M. RODRIGUEZ) POR 18 MESES (DESDE 01 JULIO 2025) | E8: Lorena Torres Castillo | F8: Encargada (S) Sección Administración de Contratos | G8: 70333380
A9: Arrastre | B9: Arrastre | C9: 1057532-196-PC25 | D9: Convenio - SERVICIO DE SOPORTE Y MANTENCION RPT VHF SSO (PERIODO DOS AÑOS) | E9: ESTEBAN ALARCON BOHLE | F9: TECNICO RADIOCOMUNICACIONES | G9: 6255504
A10: Arrastre | B10: Arrastre | C10: 1057532-1-PC24 | D10: Sistema control de flota vehicular del Servicio de Salud Osorno | E10: Felipe Salvo Barriga | F10: Enc. Sección Mant. de Vehículos | G10: 6712008
A11: Arrastre | B11: Arrastre | C11: 1057532-209-PC25 | D11: Convenio - ADQUISICION DE 3 CUPOS DE RESIDENCIA PROTEGIDA PARA EL SERVICIO DE SALUD OSORNO EN LA PROVINCIA DE CONCEPCIÓN | E11: Angelo Palma | F11: Jefe (s) Subdepto. Gestión Clínica y Administrativa Red Temática de Salud Mental de Especialidad | G11: 48115128
A12: Arrastre | B12: Arrastre | C12: 1057532-210-PC25 | D12: Convenio - ADQUISICION DE 12 CUPOS DE RESIDENCIA PROTEGIDA PARA EL SERVICIO DE SALUD OSORNO EN LA CIUDAD DE OSORNO | E12: Angelo Palma | F12: Jefe (s) Subdepto. Gestión Clínica y Administrativa Red Temática de Salud Mental de Especialidad | G12: 237155100
A13: Arrastre | B13: Arrastre | C13: 1057532-211-PC25 | D13: Convenio - ADQUISICION DE 10 CUPOS RESIDENCIA PROTEGIDA DE ALTA COMPLEJIDAD PARA EL SERVICIO DE SALUD OSORNO DE LA CIUDAD DE OSORNO | E13: Angelo Palma | F13: Jefe (s) Subdepto. Gestión Clínica y Administrativa Red Temática de Salud Mental de Especialidad | G13: 284700000
... A394: PC26 | B394: Obras Civiles | C394: 1057976-9-PC26 | D394: Contratación de Visita a Obra 2026 de las Consultorías: Especialidades y Arquitectura Obra CESFAM Bahía Mansa | E394: Rodrigo Neira | F394: Itos | G394: 9814756

Sheet Oficial Panel
A1: ID Proyecto | B1: Nombre Proyecto | C1: Nombre responsable | D1: Cargo responsable
A2: 1057532-156-PC24 | B2: servicios de control de asistencia del servicio de salud osorno | C2: Bruno Ojeda Alvarez | D2: Jefe Depto. Tecnologías de la Información
A3: 1057532-162-PC25 | B3: Convenio - de Suministro para adquisición de medicamentos faltantes CENABAST para establecimientos dependientes del SSO. | C3: ELEUTERIO ROMAN | D3: JEFE SUBDEPTO FARMACIA
A4: 1057532-163-PC24 | B4: Servicio gestión flota vehicular SSO | C4: Bruno Ojeda Alvarez | D4: Jefe Depto.
A5: 1057532-172-PC25 | B5: Convenio - CONVENIO SERVICIO DE ASEO POR 18 MESES, PARA LA DIRECCION DEL SSO Y ESTABLECIMIENTOS DEPENDIENTES DE LA RED ASISTENCIAL | C5: Lorena Torres Castillo | D5: ENCARGADA (S) SECCIÓN DE ADMINISTRACIÓN DE CONTRATOS
A6: 1057532-173-PC25 | B6: Convenio - CONVENIO DE ADQUISICION DE KIT POINT OF CARE (POC) CON ARRIENDO DE EQUIPO PARA ANALISIS DE MUESTRAS, SSO | C6: Sofia Reyes | D6: Encargada
A7: 1057532-193-PC25 | B7: Convenio - ARRIENDO 159 EQUIPOS PC AIO PARA APOYAR LOS PORCESOS CLINICOS Y ADMINISTRATIVOS | C7: Alvaro Montecinos | D7: Jefe (S) Subdepto. Soporte TIC
A8: 1057532-193-PC25 | B8: Convenio - ARRIENDO 159 EQUIPOS PC AIO PARA APOYAR LOS PROCESOS CLINICOS Y ADMINISTRATIVOS | C8: Alvaro Montecinos | D8: Jefe (S) Subdepto. Soporte TIC
A9: 1057532-195-PC25 | B9: Convenio - SERVICIO DE ASEO PARA LA DSSO (BASE SAMU, EDIFICIO PLAZA SUR Y EDIFICIO M. RODRIGUEZ) POR 18 MESES (DESDE 01 JULIO 2025) | C9: Lorena Torres Castillo | D9: Encargada (S) Sección Administración de Contratos
A10: 1057532-196-PC25 | B10: Convenio - SERVICIO DE SOPORTE Y MANTENCION RPT VHF SSO (PERIODO DOS AÑOS) | C10: ESTEBAN ALARCON BOHLE | D10: TECNICO RADIOCOMUNICACIONES
A11: 1057532-1-PC24 | B11: Sistema control de flota vehicular del Servicio de Salud Osorno | C11: Felipe Salvo Barriga | D11: Enc. Sección Mant. de Vehículos
A12: 1057532-209-PC25 | B12: Convenio - ADQUISICION DE 3 CUPOS DE RESIDENCIA PROTEGIDA PARA EL SERVICIO DE SALUD OSORNO EN LA PROVINCIA DE CONCEPCIÓN | C12: Angelo Palma | D12: Jefe (s) Subdepto. Gestión Clínica y Administrativa Red Temática de Salud Mental de Especialidad
... A395: 1180747-9-PC26 | B395: Consultorías adecuación Diseño PSR Hueyusca, comuna de Purranque. | C395: Mario Barrientos | D395: Jefe Subdepto. Diseño De Infraestructura De Salud

Sheet Oficial
A1: ID Proyecto | B1: Tipo PAC | C1: Memo | D1: Unidad de Compra | E1: Nombre Proyecto | F1: Fecha de Compra | G1: Cantidad de Ítems | H1: Nombre ítem | I1: Monto Total item | J1: Nombre responsable | K1: Cargo responsable | L1: Departamento | M1: Subdirección | N1: Departamento_SHORT | O1: CANT OC | P1: FECHA OC
A2: 1057532-496-PC26 | B2: PC26 | C2: Bienes y Servicios | D2: Bienes y Servicios | E2: Adquisicion Licencias de Software GstarCAD por 24 meses | F2: 46174 | G2: 1 | H2: Software | I2: 15000018 | J2: Alejandro Nuñez | K2: Encargado Gestión De Sistemas | L2: DEPARTAMENTO DE TECNOLOGIAS DE LA INFORMACION Y COMUNICACION | M2: SUBDIRECCION ADMINISTRATIVA | N2: TIC
A3: 1057532-497-PC26 | B3: PC26 | C3: Bienes y Servicios | D3: Bienes y Servicios | E3: Adquisicion Licencias de Software ArchiCAD por 24 meses | F3: 46174 | G3: 1 | H3: Licencia | I3: 30000000 | J3: Alejandro Nuñez | K3: Encargado Gestión De Sistemas | L3: DEPARTAMENTO DE TECNOLOGIAS DE LA INFORMACION Y COMUNICACION | M3: SUBDIRECCION ADMINISTRATIVA | N3: TIC
A4: 1057532-525-PC26 | B4: PC26 | C4: Bienes y Servicios | D4: Bienes y Servicios | E4: ADQUISICIÓN DISPOSITIVOS DE ALMACENAMIENTO PARA HABILITACION DE EQUIPOS COMPUTACIONALES | F4: 46082 | G4: 1 | H4: Disco Duros | I4: 3550000 | J4: Alejandro Nuñez | K4: Encargado Gestión De Sistemas | L4: DEPARTAMENTO DE TECNOLOGIAS DE LA INFORMACION Y COMUNICACION | M4: SUBDIRECCION ADMINISTRATIVA | N4: TIC
A5: 1057922-21-PC26 | B5: PC26 | C5: Activos Fijos | D5: Activos Fijos | E5: Adquisicion equipamiento Servidor NAS y almacenamiento extra para respaldo y seguridad de la información | F5: 46082 | G5: 2 | H5: Disco Duro | I5: 1000000 | J5: Alejandro Nuñez | K5: Encargado Gestión De Sistemas | L5: DEPARTAMENTO DE TECNOLOGIAS DE LA INFORMACION Y COMUNICACION | M5: SUBDIRECCION ADMINISTRATIVA | N5: TIC
A6: 1057922-21-PC26 | B6: PC26 | C6: Activos Fijos | D6: Activos Fijos | E6: Adquisicion equipamiento Servidor NAS y almacenamiento extra para respaldo y seguridad de la información | F6: 46082 | G6: 2 | H6: Servidor | I6: 15000000 | J6: Alejandro Nuñez | K6: Encargado Gestión De Sistemas | L6: DEPARTAMENTO DE TECNOLOGIAS DE LA INFORMACION Y COMUNICACION | M6: SUBDIRECCION ADMINISTRATIVA | N6: TIC
A7: 1057532-193-PC25 | B7: Arrastre | C7: Arrastre | D7: Bienes y Servicios | E7: Convenio - ARRIENDO 159 EQUIPOS PC AIO PARA APOYAR LOS PORCESOS CLINICOS Y ADMINISTRATIVOS | F7: 45870 | G7: 2 | H7: Insumos | I7: 74068560 | J7: Alvaro Montecinos | K7: Jefe (S) Subdepto. Soporte TIC | L7: DEPARTAMENTO DE TECNOLOGIAS DE LA INFORMACION Y COMUNICACION | M7: SUBDIRECCION ADMINISTRATIVA | N7: TIC
A8: 1057532-193-PC25 | B8: Arrastre | C8: Arrastre | D8: Bienes y Servicios | E8: Convenio - ARRIENDO 159 EQUIPOS PC AIO PARA APOYAR LOS PROCESOS CLINICOS Y ADMINISTRATIVOS | F8: 45992 | G8: 2 | H8: Insumos | I8: 37034280 | J8: Alvaro Montecinos | K8: Jefe (S) Subdepto. Soporte TIC | L8: DEPARTAMENTO DE TECNOLOGIAS DE LA INFORMACION Y COMUNICACION | M8: SUBDIRECCION ADMINISTRATIVA | N8: TIC
A9: 1057532-581-PC26 | B9: PC26 | C9: Bienes y Servicios | D9: Bienes y Servicios | E9: CONTRIBUYENDO A LA POLITICA PÚBLICA EN REPARACIÓN CON USUARIOS/AS PRAIS | F9: 46082 | G9: 23 | H9: Alcohol gel | I9: 35000 | J9: Ana María Diaz | K9: Coordinadora | L9: PRAIS | M9: SUBDIRECCION DE GESTION ASISTENCIAL | N9: PRAIS
A10: 1057532-581-PC26 | B10: PC26 | C10: Bienes y Servicios | D10: Bienes y Servicios | E10: CONTRIBUYENDO A LA POLITICA PÚBLICA EN REPARACIÓN CON USUARIOS/AS PRAIS | F10: 46082 | G10: 23 | H10: Alimentación | I10: 490000 | J10: Ana María Diaz | K10: Coordinadora | L10: PRAIS | M10: SUBDIRECCION DE GESTION ASISTENCIAL | N10: PRAIS
A11: 1057532-581-PC26 | B11: PC26 | C11: Bienes y Servicios | D11: Bienes y Servicios | E11: CONTRIBUYENDO A LA POLITICA PÚBLICA EN REPARACIÓN CON USUARIOS/AS PRAIS | F11: 46082 | G11: 23 | H11: Artículos de librería | I11: 308000 | J11: Ana María Diaz | K11: Coordinadora | L11: PRAIS | M11: SUBDIRECCION DE GESTION ASISTENCIAL | N11: PRAIS
A12: 1057532-581-PC26 | B12: PC26 | C12: Bienes y Servicios | D12: Bienes y Servicios | E12: CONTRIBUYENDO A LA POLITICA PÚBLICA EN REPARACIÓN CON USUARIOS/AS PRAIS | F12: 46082 | G12: 23 | H12: Artículos de Oficina | I12: 145040 | J12: Ana María Diaz | K12: Coordinadora | L12: PRAIS | M12: SUBDIRECCION DE GESTION ASISTENCIAL | N12: PRAIS
A13: 1057532-581-PC26 | B13: PC26 | C13: Bienes y Servicios | D13: Bienes y Servicios | E13: CONTRIBUYENDO A LA POLITICA PÚBLICA EN REPARACIÓN CON USUARIOS/AS PRAIS | F13: 46082 | G13: 23 | H13: Bloqueador solar | I13: 35000 | J13: Ana María Diaz | K13: Coordinadora | L13: PRAIS | M13: SUBDIRECCION DE GESTION ASISTENCIAL | N13: PRAIS
... A704: 1077241-51-PC25 | B704: Arrastre | C704: Arrastre | D704: Administración de Fondos | E704: Convenio - Servicio movilización COSAM Rahue periodo 2026. (Financiamiento a través de fondo extrapresupuestario SENDA PAI) | F704: 45839 | G704: 1 | H704: Movilizacion | I704: 17416663 | J704: Yuvit García-Chacur | K704: DIRECTORA | L704: CENTRO DE SALUD MENTAL COMUNITARIO COSAM RAHUE | M704: SUBDIRECCION DE GESTION ASISTENCIAL | N704: SALUD MENTAL

Sheet OficialReal
A1: ID Proyecto | B1: PAC | C1: Unidad de Compra | D1: Nombre Proyecto | E1: Nombre ítem | F1: Cantidad de Ítems | G1: Nombre responsable | H1: Fecha de Inicio Compra | I1: Cargo responsable | J1: Cantidad OC | K1: Meses envío OC | L1: Suma de Monto Total Ítem Año 2026 | M1: Departamento | N1: Subdirección | O1: Departamento_SHORT | P1: Ejecución
A2: 1057532-156-PC24 | B2: Arrastre | C2: Bienes y Servicios | D2: servicios de control de asistencia del servicio de salud osorno | E2: Servicio Control Asistencia | F2: 2 | G2: Bruno Ojeda Alvarez | H2: 45292 | I2: Jefe Depto. Tecnologías de la Información | J2: 36 | K2: 01-01-2024,01-02-2024,01-03-2024,01-04-2024,01-05-2024,01-06-2024,01-07-2024,01-08-2024,01-09-2024,01-10-2024,01-11-2024,01-12-2024,01-01-2025,01-02-2025,01-03-2025,01-04-2025,01-05-2025,01-06-2025,01-07-2025,01-08-2025,01-09-2025,01-10-2025,01-11-2025,01-12-2025,01-01-2026,01-02-2026,01-03-2026,01-04-2026,01-05-2026,01-06-2026,01-07-2026,01-08-2026,01-09-2026,01-10-2026,01-11-2026,01-12-2026 | L2: 30000000 | M2: DEPARTAMENTO DE TECNOLOGIAS DE LA INFORMACION Y COMUNICACION | N2: SUBDIRECCION ADMINISTRATIVA | O2: TIC | P2: No Ejecutado
A3: 1057532-162-PC25 | B3: Arrastre | C3: Bienes y Servicios | D3: Convenio - de Suministro para adquisición de medicamentos faltantes CENABAST para establecimientos dependientes del SSO. | E3: Medicamentos | F3: 1 | G3: ELEUTERIO ROMAN | H3: 45748 | I3: JEFE SUBDEPTO FARMACIA | J3: 24 | K3: 01-05-2025,01-06-2025,01-07-2025,01-08-2025,01-09-2025,01-10-2025,01-11-2025,01-12-2025,01-01-2026,01-02-2026,01-03-2026,01-04-2026,01-05-2026,01-06-2026,01-07-2026,01-08-2026,01-09-2026,01-10-2026,01-11-2026,01-12-2026,01-01-2027,01-02-2027,01-03-2027,01-04-2027 | L3: 75000000 | M3: DEPARTAMENTO DE OBRAS Y GESTION FINANCIERA DE INVERSIONES | N3: SUBDIRECCION ADMINISTRATIVA | O3: OBRAS Y GESTIÓN FINANCIERA DE INVERSIONES | P3: No Ejecutado
A4: 1057532-163-PC24 | B4: Arrastre | C4: Bienes y Servicios | D4: Servicio gestión flota vehicular SSO | E4: Control Flota | F4: 2 | G4: Bruno Ojeda Alvarez | H4: 45200 | I4: Jefe Depto. | J4: 36 | K4: 01-01-2024,01-02-2024,01-03-2024,01-04-2024,01-05-2024,01-06-2024,01-07-2024,01-08-2024,01-09-2024,01-10-2024,01-11-2024,01-12-2024,01-01-2025,01-02-2025,01-03-2025,01-04-2025,01-05-2025,01-06-2025,01-07-2025,01-08-2025,01-09-2025,01-10-2025,01-11-2025,01-12-2025,01-01-2026,01-02-2026,01-03-2026,01-04-2026,01-05-2026,01-06-2026,01-07-2026,01-08-2026,01-09-2026,01-10-2026,01-11-2026,01-12-2026 | L4: 6711996 | M4: DEPARTAMENTO DE TECNOLOGIAS DE LA INFORMACION Y COMUNICACION | N4: SUBDIRECCION ADMINISTRATIVA | O4: TIC | P4: No Ejecutado
A5: 1057532-172-PC25 | B5: Arrastre | C5: Bienes y Servicios | D5: Convenio - CONVENIO SERVICIO DE ASEO POR 18 MESES, PARA LA DIRECCION DEL SSO Y ESTABLECIMIENTOS DEPENDIENTES DE LA RED ASISTENCIAL | E5: Aseo | F5: 1 | G5: Lorena Torres Castillo | H5: 45839 | I5: ENCARGADA (S) SECCIÓN DE ADMINISTRACIÓN DE CONTRATOS | J5: 18 | K5: 01-07-2025,01-08-2025,01-09-2025,01-10-2025,01-11-2025,01-12-2025,01-01-2026,01-02-2026,01-03-2026,01-04-2026,01-05-2026,01-06-2026,01-07-2026,01-08-2026,01-09-2026,01-10-2026,01-11-2026,01-12-2026 | L5: 144000000 | M5: DEPARTAMENTO DE ABASTECIMIENTO Y OPERACIONES | N5: SUBDIRECCION ADMINISTRATIVA | O5: ABASTECIMIENTO Y OPERACIONES | P5: No Ejecutado
A6: 1057532-173-PC25 | B6: Arrastre | C6: Bienes y Servicios | D6: Convenio - CONVENIO DE ADQUISICION DE KIT POINT OF CARE (POC) CON ARRIENDO DE EQUIPO PARA ANALISIS DE MUESTRAS, SSO | E6: Equipo | F6: 1 | G6: Sofia Reyes | H6: 45839 | I6: Encargada | J6: 12 | K6: 01-08-2025,01-09-2025,01-10-2025,01-11-2025,01-12-2025,01-01-2026,01-02-2026,01-03-2026,01-04-2026,01-05-2026,01-06-2026,01-07-2026 | L6: 40833335 | M6: DEPARTAMENTO ARTICULACION DE LA RED ASISTENCIAL | N6: SUBDIRECCION DE GESTION ASISTENCIAL | O6: ARTICULACION DE LA RED ASISTENCIAL | P6: No Ejecutado
A7: 1057532-193-PC25 | B7: Arrastre | C7: Bienes y Servicios | D7: Convenio - ARRIENDO 159 EQUIPOS PC AIO PARA APOYAR LOS PORCESOS CLINICOS Y ADMINISTRATIVOS | E7: Insumos | F7: 2 | G7: Alvaro Montecinos | H7: 45870 | I7: Jefe (S) Subdepto. Soporte TIC | J7: 1 | K7: 01-01-2026,01-02-2026,01-03-2026,01-04-2026,01-05-2026,01-06-2026,01-07-2026,01-08-2026,01-09-2026,01-10-2026,01-11-2026,01-12-2026,01-01-2027,01-02-2027,01-03-2027,01-04-2027,01-05-2027,01-06-2027,01-07-2027,01-08-2027,01-09-2027,01-10-2027,01-11-2027,01-12-2027,01-01-2028,01-02-2028,01-03-2028,01-04-2028,01-05-2028,01-06-2028,01-07-2028,01-08-2028 | L7: 74068560 | M7: DEPARTAMENTO DE TECNOLOGIAS DE LA INFORMACION Y COMUNICACION | N7: SUBDIRECCION ADMINISTRATIVA | O7: TIC | P7: No Ejecutado
A8: 1057532-193-PC25 | B8: Arrastre | C8: Bienes y Servicios | D8: Convenio - ARRIENDO 159 EQUIPOS PC AIO PARA APOYAR LOS PROCESOS CLINICOS Y ADMINISTRATIVOS | E8: Insumos | F8: 2 | G8: Alvaro Montecinos | H8: 45992 | I8: Jefe (S) Subdepto. Soporte TIC | J8: 32 | K8: 01-01-2026,01-02-2026,01-03-2026,01-04-2026,01-05-2026,01-06-2026,01-07-2026,01-08-2026,01-09-2026,01-10-2026,01-11-2026,01-12-2026,01-01-2027,01-02-2027,01-03-2027,01-04-2027,01-05-2027,01-06-2027,01-07-2027,01-08-2027,01-09-2027,01-10-2027,01-11-2027,01-12-2027,01-01-2028,01-02-2028,01-03-2028,01-04-2028,01-05-2028,01-06-2028,01-07-2028,01-08-2028 | L8: 37034280 | M8: DEPARTAMENTO DE TECNOLOGIAS DE LA INFORMACION Y COMUNICACION | N8: SUBDIRECCION ADMINISTRATIVA | O8: TIC | P8: No Ejecutado
A9: 1057532-195-PC25 | B9: Arrastre | C9: Bienes y Servicios | D9: Convenio - SERVICIO DE ASEO PARA LA DSSO (BASE SAMU, EDIFICIO PLAZA SUR Y EDIFICIO M. RODRIGUEZ) POR 18 MESES (DESDE 01 JULIO 2025) | E9: Aseo | F9: 2 | G9: Lorena Torres Castillo | H9: 45658 | I9: Encargada (S) Sección Administración de Contratos | J9: 18 | K9: 01-07-2025,01-08-2025,01-09-2025,01-10-2025,01-11-2025,01-12-2025,01-01-2026,01-02-2026,01-03-2026,01-04-2026,01-05-2026,01-06-2026,01-07-2026,01-08-2026,01-09-2026,01-10-2026,01-11-2026,01-12-2026 | L9: 70333380 | M9: DEPARTAMENTO DE ABASTECIMIENTO Y OPERACIONES | N9: SUBDIRECCION ADMINISTRATIVA | O9: ABASTECIMIENTO Y OPERACIONES | P9: No Ejecutado
A10: 1057532-196-PC25 | B10: Arrastre | C10: Bienes y Servicios | D10: Convenio - SERVICIO DE SOPORTE Y MANTENCION RPT VHF SSO (PERIODO DOS AÑOS) | E10: Mantenimiento | F10: 2 | G10: ESTEBAN ALARCON BOHLE | H10: 45658 | I10: TECNICO RADIOCOMUNICACIONES | J10: 24 | K10: 01-01-2025,01-02-2025,01-03-2025,01-04-2025,01-05-2025,01-06-2025,01-07-2025,01-08-2025,01-09-2025,01-10-2025,01-11-2025,01-12-2025,01-01-2026,01-02-2026,01-03-2026,01-04-2026,01-05-2026,01-06-2026,01-07-2026,01-08-2026,01-09-2026,01-10-2026,01-11-2026,01-12-2026 | L10: 6255504 | M10: SUB. DPTO. GESTION DEL RIESGO EN EMERGENCIAS, DESASTRES Y TELECOMUNICACIONES | N10: DIRECCIÓN | O10: SUB. DPTO. GESTION DEL RIESGO EN EMERGENCIAS, DESASTRES Y TELECOMUNICACIONES | P10: No Ejecutado
A11: 1057532-1-PC24 | B11: Arrastre | C11: Bienes y Servicios | D11: Sistema control de flota vehicular del Servicio de Salud Osorno | E11: Sistema de control de flota | F11: 1 | G11: Felipe Salvo Barriga | H11: 45292 | I11: Enc. Sección Mant. de Vehículos | J11: 36 | K11: 01-01-2024,01-02-2024,01-03-2024,01-04-2024,01-05-2024,01-06-2024,01-07-2024,01-08-2024,01-09-2024,01-10-2024,01-11-2024,01-12-2024,01-01-2025,01-02-2025,01-03-2025,01-04-2025,01-05-2025,01-06-2025,01-07-2025,01-08-2025,01-09-2025,01-10-2025,01-11-2025,01-12-2025,01-01-2026,01-02-2026,01-03-2026,01-04-2026,01-05-2026,01-06-2026,01-07-2026,01-08-2026,01-09-2026,01-10-2026,01-11-2026,01-12-2026 | L11: 6712008 | M11: SECCION DE MANTENIMIENTO DE VEHICULOS | N11: SUBDIRECCION ADMINISTRATIVA | O11: ABASTECIMIENTO Y OPERACIONES | P11: No Ejecutado
A12: 1057532-209-PC25 | B12: Arrastre | C12: Bienes y Servicios | D12: Convenio - ADQUISICION DE 3 CUPOS DE RESIDENCIA PROTEGIDA PARA EL SERVICIO DE SALUD OSORNO EN LA PROVINCIA DE CONCEPCIÓN | E12: Servicio Residencial | F12: 2 | G12: Angelo Palma | H12: 45658 | I12: Jefe (s) Subdepto. Gestión Clínica y Administrativa Red Temática de Salud Mental de Especialidad | J12: 24 | K12: 01-01-2025,01-02-2025,01-03-2025,01-04-2025,01-05-2025,01-06-2025,01-07-2025,01-08-2025,01-09-2025,01-10-2025,01-11-2025,01-12-2025,01-01-2026,01-02-2026,01-03-2026,01-04-2026,01-05-2026,01-06-2026,01-07-2026,01-08-2026,01-09-2026,01-10-2026,01-11-2026,01-12-2026 | L12: 48115128 | M12: DEPARTAMENTO DE SALUD MENTAL | N12: SUBDIRECCION DE GESTION ASISTENCIAL | O12: SALUD MENTAL | P12: No Ejecutado
A13: 1057532-210-PC25 | B13: Arrastre | C13: Bienes y Servicios | D13: Convenio - ADQUISICION DE 12 CUPOS DE RESIDENCIA PROTEGIDA PARA EL SERVICIO DE SALUD OSORNO EN LA CIUDAD DE OSORNO | E13: Servicio Residencial | F13: 2 | G13: Angelo Palma | H13: 45658 | I13: Jefe (s) Subdepto. Gestión Clínica y Administrativa Red Temática de Salud Mental de Especialidad | J13: 24 | K13: 01-01-2025,01-02-2025,01-03-2025,01-04-2025,01-05-2025,01-06-2025,01-07-2025,01-08-2025,01-09-2025,01-10-2025,01-11-2025,01-12-2025,01-01-2026,01-02-2026,01-03-2026,01-04-2026,01-05-2026,01-06-2026,01-07-2026,01-08-2026,01-09-2026,01-10-2026,01-11-2026,01-12-2026 | L13: 237155100 | M13: DEPARTAMENTO DE SALUD MENTAL | N13: SUBDIRECCION DE GESTION ASISTENCIAL | O13: SALUD MENTAL | P13: No Ejecutado
A14: 1057532-211-PC25 | B14: Arrastre | C14: Bienes y Servicios | D14: Convenio - ADQUISICION DE 10 CUPOS RESIDENCIA PROTEGIDA DE ALTA COMPLEJIDAD PARA EL SERVICIO DE SALUD OSORNO DE LA CIUDAD DE OSORNO | E14: Servicio Residencial | F14: 2 | G14: Angelo Palma | H14: 45658 | I14: Jefe (s) Subdepto. Gestión Clínica y Administrativa Red Temática de Salud Mental de Especialidad | J14: 24 | K14: 01-01-2025,01-02-2025,01-03-2025,01-04-2025,01-05-2025,01-06-2025,01-07-2025,01-08-2025,01-09-2025,01-10-2025,01-11-2025,01-12-2025,01-01-2026,01-02-2026,01-03-2026,01-04-2026,01-05-2026,01-06-2026,01-07-2026,01-08-2026,01-09-2026,01-10-2026,01-11-2026,01-12-2026 | L14: 284700000 | M14: DEPARTAMENTO DE SALUD MENTAL | N14: SUBDIRECCION DE GESTION ASISTENCIAL | O14: SALUD MENTAL | P14: No Ejecutado
A15: 1057532-281-PC26 | B15: PC26 | C15: Bienes y Servicios | D15: Mantención Plotter Canon IPF 770, del depto. de Proyectos. | E15: Mantencion | F15: 1 | G15: Mario Barrientos | H15: 46266 | I15: Jefe Subdepto. Diseño De Infraestructura De Salud | J15: 1 | K15: 46266 | L15: 1250000 | M15: DEPARTAMENTO DE PROYECTOS | N15: SUBDIRECCION ADMINISTRATIVA | O15: PROYECTOS | P15: No Ejecutado
A16: 1057532-282-PC26 | B16: PC26 | C16: Bienes y Servicios | D16: Compra rollos papel para impresión del Departamento de Proyectos SSO. | E16: Rollos | F16: 1 | G16: Mario Barrientos | H16: 46174 | I16: Jefe Subdepto. Diseño De Infraestructura De Salud | J16: 1 | K16: 46174 | L16: 300000 | M16: DEPARTAMENTO DE PROYECTOS | N16: SUBDIRECCION ADMINISTRATIVA | O16: PROYECTOS | P16: No Ejecutado
A17: 1057532-283-PC26 | B17: PC26 | C17: Bienes y Servicios | D17: Compra Tinta Plotter Canon IPF 770 | E17: Tinta Plotter | F17: 1 | G17: Mario Barrientos | H17: 46204 | I17: Jefe Subdepto. Diseño De Infraestructura De Salud | J17: 1 | K17: 46204 | L17: 1320000 | M17: DEPARTAMENTO DE PROYECTOS | N17: SUBDIRECCION ADMINISTRATIVA | O17: PROYECTOS | P17: No Ejecutado
A18: 1057532-284-PC26 | B18: PC26 | C18: Bienes y Servicios | D18: Adquisicición Hojas Prehospitalarias | E18: Talonarios | F18: 1 | G18: Silvia Delgado | H18: 46082 | I18: Encargada Proceso De Urgencia | J18: 1 | K18: 46082 | L18: 2000700 | M18: DEPARTAMENTO ARTICULACION DE LA RED ASISTENCIAL | N18: SUBDIRECCION DE GESTION ASISTENCIAL | O18: ARTICULACION DE LA RED ASISTENCIAL | P18: No Ejecutado
A19: 1057532-285-PC26 | B19: PC26 | C19: Bienes y Servicios | D19: Adquisicición Kit de Triage y Sistema de comando incidente | E19: Kit Sistema | F19: 1 | G19: Silvia Delgado | H19: 46082 | I19: Encargada Proceso De Urgencia | J19: 1 | K19: 46082 | L19: 1510005 | M19: DEPARTAMENTO ARTICULACION DE LA RED ASISTENCIAL | N19: SUBDIRECCION DE GESTION ASISTENCIAL | O19: ARTICULACION DE LA RED ASISTENCIAL | P19: No Ejecutado
A20: 1057532-286-PC26 | B20: PC26 | C20: Bienes y Servicios | D20: II Jornada de Capacitación Red de Urgencia | E20: Cafeteria | F20: 2 | G20: Silvia Delgado | H20: 46082 | I20: Encargada Proceso De Urgencia | J20: 1 | K20: 46082 | L20: 850000 | M20: DEPARTAMENTO ARTICULACION DE LA RED ASISTENCIAL | N20: SUBDIRECCION DE GESTION ASISTENCIAL | O20: ARTICULACION DE LA RED ASISTENCIAL | P20: No Ejecutado
A21: 1057532-286-PC26 | B21: PC26 | C21: Bienes y Servicios | D21: II Jornada de Capacitación Red de Urgencia | E21: Opalina | F21: 2 | G21: Silvia Delgado | H21: 46082 | I21: Encargada Proceso De Urgencia | J21: 1 | K21: 46082 | L21: 22500 | M21: DEPARTAMENTO ARTICULACION DE LA RED ASISTENCIAL | N21: SUBDIRECCION DE GESTION ASISTENCIAL | O21: ARTICULACION DE LA RED ASISTENCIAL | P21: No Ejecutado
A22: 1057532-287-PC26 | B22: PC26 | C22: Bienes y Servicios | D22: ?DIAGNÓSTICO Y DIALOGO PARTICIPATIVO COSAM RAHUE ?NOVIEMBRE 2026? | E22: Cafeteria | F22: 1 | G22: Camilo Martínez | H22: 46327 | I22: Director(S) | J22: 1 | K22: 46327 | L22: 540000 | M22: DEPARTAMENTO DE SALUD MENTAL | N22: SUBDIRECCION DE GESTION ASISTENCIAL | O22: SALUD MENTAL | P22: No Ejecutado
A23: 1057532-288-PC26 | B23: PC26 | C23: Bienes y Servicios | D23: Jornadas de encuentro y autocuidado Para usuarios y cuidadores ?SALUDABLE-MENTE en dispositivo COSAM RAHUE 2026 | E23: Alimentación | F23: 6 | G23: Camilo Martínez | H23: 46113 | I23: Director(S) | J23: 1 | K23: 46113 | L23: 135000 | M23: DEPARTAMENTO DE SALUD MENTAL | N23: SUBDIRECCION DE GESTION ASISTENCIAL | O23: SALUD MENTAL | P23: No Ejecutado
A24: 1057532-288-PC26 | B24: PC26 | C24: Bienes y Servicios | D24: Jornadas de encuentro y autocuidado Para usuarios y cuidadores ?SALUDABLE-MENTE en dispositivo COSAM RAHUE 2026 | E24: Alimentación | F24: 6 | G24: Camilo Martínez | H24: 46204 | I24: Director(S) | J24: 1 | K24: 46204 | L24: 135000 | M24: DEPARTAMENTO DE SALUD MENTAL | N24: SUBDIRECCION DE GESTION ASISTENCIAL | O24: SALUD MENTAL | P24: No Ejecutado
A25: 1057532-288-PC26 | B25: PC26 | C25: Bienes y Servicios | D25: Jornadas de encuentro y autocuidado Para usuarios y cuidadores ?SALUDABLE-MENTE en dispositivo COSAM RAHUE 2026 | E25: Alimentación | F25: 6 | G25: Camilo Martínez | H25: 46266 | I25: Director(S) | J25: 1 | K25: 46266 | L25: 135000 | M25: DEPARTAMENTO DE SALUD MENTAL | N25: SUBDIRECCION DE GESTION ASISTENCIAL | O25: SALUD MENTAL | P25: No Ejecutado
A26: 1057532-288-PC26 | B26: PC26 | C26: Bienes y Servicios | D26: Jornadas de encuentro y autocuidado Para usuarios y cuidadores ?SALUDABLE-MENTE en dispositivo COSAM RAHUE 2026 | E26: Alimentación | F26: 6 | G26: Camilo Martínez | H26: 46357 | I26: Director(S) | J26: 1 | K26: 46357 | L26: 135000 | M26: DEPARTAMENTO DE SALUD MENTAL | N26: SUBDIRECCION DE GESTION ASISTENCIAL | O26: SALUD MENTAL | P26: No Ejecutado
A27: 1057532-288-PC26 | B27: PC26 | C27: Bienes y Servicios | D27: Jornadas de encuentro y autocuidado Para usuarios y cuidadores ?SALUDABLE-MENTE en dispositivo COSAM RAHUE 2026 | E27: Cafeteria | F27: 6 | G27: Camilo Martínez | H27: 46113 | I27: Director(S) | J27: 1 | K27: 46113 | L27: 135000 | M27: DEPARTAMENTO DE SALUD MENTAL | N27: SUBDIRECCION DE GESTION ASISTENCIAL | O27: SALUD MENTAL | P27: No Ejecutado
A28: 1057532-288-PC26 | B28: PC26 | C28: Bienes y Servicios | D28: Jornadas de encuentro y autocuidado Para usuarios y cuidadores ?SALUDABLE-MENTE en dispositivo COSAM RAHUE 2026 | E28: Cafeteria | F28: 6 | G28: Camilo Martínez | H28: 46204 | I28: Director(S) | J28: 3 | K28: 01-07-2026,01-09-2026,01-12-2026 | L28: 405000 | M28: DEPARTAMENTO DE SALUD MENTAL | N28: SUBDIRECCION DE GESTION ASISTENCIAL | O28: SALUD MENTAL | P28: No Ejecutado
A29: 1057532-308-PC24 | B29: Arrastre | C29: Bienes y Servicios | D29: Convenio - 3 cupos Residencia Protegida para el Servicio de Salud Osorno en la Región Metropolitana | E29: Residencia | F29: 1 | G29: Antonia Caifil | H29: 45474 | I29: Jefa Subdepto. Gestión Clinica y Adm. | J29: 24 | K29: 01-01-2025,01-02-2025,01-03-2025,01-04-2025,01-05-2025,01-06-2025,01-07-2025,01-08-2025,01-09-2025,01-10-2025,01-11-2025,01-12-2025,01-01-2026,01-02-2026,01-03-2026,01-04-2026,01-05-2026,01-06-2026,01-07-2026,01-08-2026,01-09-2026,01-10-2026,01-11-2026,01-12-2026 | L29: 40432878 | M29: DEPARTAMENTO DE SALUD MENTAL | N29: SUBDIRECCION DE GESTION ASISTENCIAL | O29: SALUD MENTAL | P29: No Ejecutado
A30: 1057532-30-PC24 | B30: Arrastre | C30: Bienes y Servicios | D30: SISTEMAS DE COMUNICACIONES LTE WAVE PTX SERVICIO DE SALUD OSORNO | E30: Servicio | F30: 1 | G30: CATALINA VERA | H30: 45413 | I30: COORDINADORA EMERGENCIA | J30: 36 | K30: 01-06-2024,01-07-2024,01-08-2024,01-09-2024,01-10-2024,01-11-2024,01-12-2024,01-01-2025,01-02-2025,01-03-2025,01-04-2025,01-05-2025,01-06-2025,01-07-2025,01-08-2025,01-09-2025,01-10-2025,01-11-2025,01-12-2025,01-01-2026,01-02-2026,01-03-2026,01-04-2026,01-05-2026,01-06-2026,01-07-2026,01-08-2026,01-09-2026,01-10-2026,01-11-2026,01-12-2026,01-01-2027,01-02-2027,01-03-2027,01-04-2027,01-05-2024 | L30: 43333332 | M30: SUB. DPTO. GESTION DEL RIESGO EN EMERGENCIAS, DESASTRES Y TELECOMUNICACIONES | N30: DIRECCIÓN | O30: SUB. DPTO. GESTION DEL RIESGO EN EMERGENCIAS, DESASTRES Y TELECOMUNICACIONES | P30: No Ejecutado
A31: 1057532-311-PC24 | B31: Arrastre | C31: Bienes y Servicios | D31: Convenio - ( cupos Hogar Protegido Varones para el Servicio de Salud Osorno en la ciudad de Osorno | E31: Residencia | F31: 1 | G31: Antonia Caifil | H31: 45444 | I31: Jefa Subdepto. Gestión Clínica y Adm. | J31: 24 | K31: 01-01-2025,01-02-2025,01-03-2025,01-04-2025,01-05-2025,01-06-2025,01-07-2025,01-08-2025,01-09-2025,01-10-2025,01-11-2025,01-12-2025,01-01-2026,01-02-2026,01-03-2026,01-04-2026,01-05-2026,01-06-2026,01-07-2026,01-08-2026,01-09-2026,01-10-2026,01-11-2026,01-12-2026 | L31: 78361124 | M31: DEPARTAMENTO DE SALUD MENTAL | N31: SUBDIRECCION DE GESTION ASISTENCIAL | O31: SALUD MENTAL | P31: No Ejecutado
A32: 1057532-315-PC24 | B32: Arrastre | C32: Bienes y Servicios | D32: Convenio - 08 Cupos Hogar Protegido Mujeres para el Servicio de Salud Osorno en la ciudad de Osorno | E32: Residencia | F32: 1 | G32: Antonia Caifil | H32: 45444 | I32: Jefa Subdepto. Gestión Clínica y Adm. | J32: 24 | K32: 01-01-2025,01-02-2025,01-03-2025,01-04-2025,01-05-2025,01-06-2025,01-07-2025,01-08-2025,01-09-2025,01-10-2025,01-11-2025,01-12-2025,01-01-2026,01-02-2026,01-03-2026,01-04-2026,01-05-2026,01-06-2026,01-07-2026,01-08-2026,01-09-2026,01-10-2026,01-11-2026,01-12-2026 | L32: 78361124 | M32: DEPARTAMENTO DE SALUD MENTAL | N32: SUBDIRECCION DE GESTION ASISTENCIAL | O32: SALUD MENTAL | P32: No Ejecutado
A33: 1057532-317-PC26 | B33: PC26 | C33: Bienes y Servicios | D33: ?Eco-huerto sustentable -Sistema de acuaponía sin suelo? COSAM RAHUE 2026 | E33: Macetero | F33: 1 | G33: Camilo Martínez | H33: 46082 | I33: Director(S) | J33: 1 | K33: 46082 | L33: 1500000 | M33: DEPARTAMENTO DE SALUD MENTAL | N33: SUBDIRECCION DE GESTION ASISTENCIAL | O33: SALUD MENTAL | P33: No Ejecutado
A34: 1057532-320-PC24 | B34: Arrastre | C34: Bienes y Servicios | D34: Convenio - SERVICIOS DE MANTENCIÓN, RECARGA E INSPECCION PREVENTIVA PARA RED HÚMEDA Y EXTINTORES EN ESTABLECIMIENTOS SSO | E34: Recarga | F34: 1 | G34: KARIN SCHOLZ | H34: 45444 | I34: Jefatura Dpto. de Calidad de Vida | J34: 30 | K34: 01-01-2025,01-02-2025,01-03-2025,01-04-2025,01-05-2025,01-06-2025,01-07-2025,01-08-2025,01-09-2025,01-10-2025,01-11-2025,01-12-2025,01-01-2026,01-02-2026,01-03-2026,01-04-2026,01-05-2026,01-06-2026,01-07-2026,01-08-2026,01-09-2026,01-10-2026,01-11-2026,01-12-2026,01-01-2027,01-02-2027,01-03-2027,01-04-2027,01-05-2027,01-06-2027 | L34: 18060000 | M34: DEPARTAMENTO DE CALIDAD DE VIDA | N34: SUBDIRECCION DE GESTION Y DESARROLLO DE LAS PERSONAS | O34: CALIDAD DE VIDA | P34: No Ejecutado
A35: 1057532-320-PC26 | B35: PC26 | C35: Bienes y Servicios | D35: Insumos y medicamentos Farmacia COSAM RAHUE | E35: Insumos y Repuestos | F35: 1 | G35: Camilo Martínez | H35: 46023 | I35: Director(S) | J35: 1 | K35: 46023 | L35: 850000 | M35: DEPARTAMENTO DE SALUD MENTAL | N35: SUBDIRECCION DE GESTION ASISTENCIAL | O35: SALUD MENTAL | P35: No Ejecutado
A36: 1057532-321-PC24 | B36: Arrastre | C36: Bienes y Servicios | D36: Convenio - DE SERVICIOS DE MANTENCIÓN PREVENTIVA, CORRECTIVA Y/O REPARATIVA PARA VEHÍCULOS MERCEDES-BENZ DEL SSO Y HOSPITA | E36: Mantenimiento | F36: 1 | G36: Felipe Salvo | H36: 45474 | I36: Encargado Mantenimineto | J36: 24 | K36: 01-01-2025,01-02-2025,01-03-2025,01-04-2025,01-05-2025,01-06-2025,01-07-2025,01-08-2025,01-09-2025,01-10-2025,01-11-2025,01-12-2025,01-01-2026,01-02-2026,01-03-2026,01-04-2026,01-05-2026,01-06-2026,01-07-2026,01-08-2026,01-09-2026,01-10-2026,01-11-2026,01-12-2026 | L36: 150000000 | M36: SECCION DE MANTENIMIENTO DE VEHICULOS | N36: SUBDIRECCION ADMINISTRATIVA | O36: ABASTECIMIENTO Y OPERACIONES | P36: No Ejecutado
A37: 1057532-321-PC26 | B37: PC26 | C37: Bienes y Servicios | D37: Capacitación en Salud Mental Intercultural COSAM Rahue. | E37: Cafeteria | F37: 2 | G37: Camilo Martínez | H37: 46143 | I37: Director(S) | J37: 1 | K37: 46143 | L37: 450000 | M37: DEPARTAMENTO DE SALUD MENTAL | N37: SUBDIRECCION DE GESTION ASISTENCIAL | O37: SALUD MENTAL | P37: No Ejecutado
A38: 1057532-321-PC26 | B38: PC26 | C38: Bienes y Servicios | D38: Capacitación en Salud Mental Intercultural COSAM Rahue. | E38: Cafeteria | F38: 2 | G38: Camilo Martínez | H38: 46327 | I38: Director(S) | J38: 1 | K38: 46143 | L38: 450000 | M38: DEPARTAMENTO DE SALUD MENTAL | N38: SUBDIRECCION DE GESTION ASISTENCIAL | O38: SALUD MENTAL | P38: No Ejecutado
A39: 1057532-322-PC24 | B39: Arrastre | C39: Bienes y Servicios | D39: Convenio - SERVICIO DE MANEJO, RETIRO, TRANSPORTE Y DISPOSICIÓN FINAL DE RESIDUOS PELIGROSOS Y ESPECIALES | E39: Servicio residuos | F39: 1 | G39: KARIN SCHOLZ | H39: 45505 | I39: JEFA DE DEPTO DE CALIDAD DE VIDA | J39: 24 | K39: 01-01-2025,01-02-2025,01-03-2025,01-04-2025,01-05-2025,01-06-2025,01-07-2025,01-08-2025,01-09-2025,01-10-2025,01-11-2025,01-12-2025,01-01-2026,01-02-2026,01-03-2026,01-04-2026,01-05-2026,01-06-2026,01-07-2026,01-08-2026,01-09-2026,01-10-2026,01-11-2026,01-12-2026 | L39: 397359215 | M39: DEPARTAMENTO DE CALIDAD DE VIDA | N39: SUBDIRECCION DE GESTION Y DESARROLLO DE LAS PERSONAS | O39: CALIDAD DE VIDA | P39: No Ejecutado
A40: 1057532-322-PC26 | B40: PC26 | C40: Bienes y Servicios | D40: Celebración de We Tripantu en COSAM Rahue 2026 | E40: Cafeteria | F40: 1 | G40: Camilo Martínez | H40: 46174 | I40: Director(S) | J40: 1 | K40: 46174 | L40: 630000 | M40: DEPARTAMENTO DE SALUD MENTAL | N40: SUBDIRECCION DE GESTION ASISTENCIAL | O40: SALUD MENTAL | P40: No Ejecutado
A41: 1057532-323-PC26 | B41: PC26 | C41: Bienes y Servicios | D41: Jornadas de autocuidado equipo profesional PAI COSAM Rahue | E41: Cafeteria | F41: 1 | G41: Camilo Martínez | H41: 46235 | I41: Director(S) | J41: 1 | K41: 46235 | L41: 135000 | M41: DEPARTAMENTO DE SALUD MENTAL | N41: SUBDIRECCION DE GESTION ASISTENCIAL | O41: SALUD MENTAL | P41: No Ejecutado
A42: 1057532-324-PC26 | B42: PC26 | C42: Bienes y Servicios | D42: CONVENIO - ADQUISICION DE 8 CUPOS HOGAR PROTEGIDO MUJERES PARA EL SERVICIO DE SALUD OSORNO POR PERIODO DE 12 MESES | E42: Hogar Protegido 1 | F42: 3 | G42: Angelo Palma | H42: 46082 | I42: Coordinador Unidad de Gestión de Procesos Clínicos de Atención de Especialidad Ambulatoria, Cerrada | J42: 12 | K42: 01-03-2026,01-04-2026,01-05-2026,01-06-2026,01-07-2026,01-08-2026,01-09-2026,01-10-2026,01-11-2026,01-12-2026,01-01-2027,01-02-2027 | L42: 36406019 | M42: DEPARTAMENTO DE SALUD MENTAL | N42: SUBDIRECCION DE GESTION ASISTENCIAL | O42: SALUD MENTAL | P42: No Ejecutado
A43: 1057532-324-PC26 | B43: PC26 | C43: Bienes y Servicios | D43: CONVENIO - ADQUISICION DE 8 CUPOS HOGAR PROTEGIDO MUJERES PARA EL SERVICIO DE SALUD OSORNO POR PERIODO DE 12 MESES | E43: Hogar Protegido 6 | F43: 3 | G43: Angelo Palma | H43: 46082 | I43: Coordinador Unidad de Gestión de Procesos Clínicos de Atención de Especialidad Ambulatoria, Cerrada | J43: 12 | K43: 01-03-2026,01-04-2026,01-05-2026,01-06-2026,01-07-2026,01-08-2026,01-09-2026,01-10-2026,01-11-2026,01-12-2026,01-01-2027,01-02-2027 | L43: 64787500 | M43: DEPARTAMENTO DE SALUD MENTAL | N43: SUBDIRECCION DE GESTION ASISTENCIAL | O43: SALUD MENTAL | P43: No Ejecutado
A44: 1057532-325-PC26 | B44: PC26 | C44: Bienes y Servicios | D44: SERVICIO CAFETERÍA CEREMONIA ANIVERSARIO COSAM RAHUE | E44: Cafeteria | F44: 1 | G44: Camilo Martínez | H44: 46143 | I44: Director(S) | J44: 1 | K44: 46143 | L44: 675000 | M44: DEPARTAMENTO DE SALUD MENTAL | N44: SUBDIRECCION DE GESTION ASISTENCIAL | O44: SALUD MENTAL | P44: No Ejecutado
A45: 1057532-326-PC26 | B45: PC26 | C45: Bienes y Servicios | D45: Adquisición de insumos para la atención en domicilio del Equipo Rehabilitación Rural SSO. (Articulos de Libreria) | E45: Material de Oficina | F45: 1 | G45: Karin Avila | H45: 46082 | I45: Referente Rehabilitación Integral | J45: 1 | K45: 46082 | L45: 190000 | M45: DEPARTAMENTO ATENCION PRIMARIA | N45: SUBDIRECCION DE GESTION ASISTENCIAL | O45: ATENCION PRIMARIA | P45: No Ejecutado
A46: 1057532-327-PC26 | B46: PC26 | C46: Bienes y Servicios | D46: Convenio - 3 CUPOS DE RESIDENCIA PROTEGIDA PARA EL SERVICIO DE SALUD OSORNO EN LA PROVINCIA DE CONCEPCIÓN, POR PERIODO DE 24 MESES. | E46: Residencia Protegia | F46: 1 | G46: Angelo Palma | H46: 46082 | I46: Coordinador Unidad de Gestión de Procesos Clínicos de Atención de Especialidad Ambulatoria, Cerrada | J46: 24 | K46: 01-03-2026,01-04-2026,01-05-2026,01-06-2026,01-07-2026,01-08-2026,01-09-2026,01-10-2026,01-11-2026,01-12-2026,01-01-2027,01-02-2027,01-03-2027,01-04-2027,01-05-2027,01-06-2027,01-07-2027,01-08-2027,01-09-2027,01-10-2027,01-11-2027,01-12-2027,01-01-2028,01-02-2028 | L46: 49483210 | M46: DEPARTAMENTO DE SALUD MENTAL | N46: SUBDIRECCION DE GESTION ASISTENCIAL | O46: SALUD MENTAL | P46: No Ejecutado
A47: 1057532-328-PC24 | B47: Arrastre | C47: Bienes y Servicios | D47: Convenio - BENEFICIO ALIMENTACION 2024 | E47: Tarjeta | F47: 1 | G47: JORGE OYARZUN SILVA | H47: 45444 | I47: REFERENTE TARJETA ALIMENTACION | J47: 30 | K47: 01-01-2025,01-02-2025,01-03-2025,01-04-2025,01-05-2025,01-06-2025,01-07-2025,01-08-2025,01-09-2025,01-10-2025,01-11-2025,01-12-2025,01-01-2026,01-02-2026,01-03-2026,01-04-2026,01-05-2026,01-06-2026,01-07-2026,01-08-2026,01-09-2026,01-10-2026,01-11-2026,01-12-2026,01-01-2027,01-02-2027,01-03-2027,01-04-2027,01-05-2027,01-06-2027 | L47: 496977708 | M47: DEPARTAMENTO DE CALIDAD DE VIDA | N47: SUBDIRECCION DE GESTION Y DESARROLLO DE LAS PERSONAS | O47: CALIDAD DE VIDA | P47: No Ejecutado
A48: 1057532-328-PC26 | B48: PC26 | C48: Bienes y Servicios | D48: Rollos Etiquetas para impresora ZEBRA ZD 220 y rollos de cinta para impresora SOME, COSAM RAHUE | E48: Rollos | F48: 1 | G48: Camilo Martínez | H48: 46023 | I48: Director(S) | J48: 1 | K48: 46023 | L48: 430010 | M48: DEPARTAMENTO DE SALUD MENTAL | N48: SUBDIRECCION DE GESTION ASISTENCIAL | O48: SALUD MENTAL | P48: No Ejecutado
A49: 1057532-329-PC26 | B49: PC26 | C49: Bienes y Servicios | D49: Convenio - 10 CUPOS RESIDENCIA PROTEGIDA DE ALTA COMPLEJIDAD PARA EL SERVICIO DE SALUD OSORNO POR PERIODO DE 12 MESES. | E49: Residencia Protegia | F49: 1 | G49: Angelo Palma | H49: 46082 | I49: Coordinador Unidad de Gestión de Procesos Clínicos de Atención de Especialidad Ambulatoria, Cerrada | J49: 12 | K49: 01-03-2026,01-04-2026,01-05-2026,01-06-2026,01-07-2026,01-08-2026,01-09-2026,01-10-2026,01-11-2026,01-12-2026,01-01-2027,01-02-2027 | L49: 247689000 | M49: DEPARTAMENTO DE SALUD MENTAL | N49: SUBDIRECCION DE GESTION ASISTENCIAL | O49: SALUD MENTAL | P49: No Ejecutado
A50: 1057532-330-PC26 | B50: PC26 | C50: Bienes y Servicios | D50: INSUMOS DE ASEO COSAM RAHUE | E50: Insumos de Aseo | F50: 1 | G50: Camilo Martínez | H50: 46082 | I50: Director(S) | J50: 1 | K50: 46082 | L50: 990002 | M50: DEPARTAMENTO DE SALUD MENTAL | N50: SUBDIRECCION DE GESTION ASISTENCIAL | O50: SALUD MENTAL | P50: No Ejecutado
A51: 1057532-331-PC24 | B51: Arrastre | C51: Bienes y Servicios | D51: Convenio - Suministro de oxígeno medicinal para Red de Hospitales de mediana y baja complejidad y SAMU | E51: Suministro Oxigeno | F51: 1 | G51: Mario Aburto Foitzich | H51: 45474 | I51: Encargado Gestión Salud Respiratoria | J51: 24 | K51: 01-01-2025,01-02-2025,01-03-2025,01-04-2025,01-05-2025,01-06-2025,01-07-2025,01-08-2025,01-09-2025,01-10-2025,01-11-2025,01-12-2025,01-01-2026,01-02-2026,01-03-2026,01-04-2026,01-05-2026,01-06-2026,01-07-2026,01-08-2026,01-09-2026,01-10-2026,01-11-2026,01-12-2026 | L51: 118000004 | M51: DEPARTAMENTO ARTICULACION DE LA RED ASISTENCIAL | N51: SUBDIRECCION DE GESTION ASISTENCIAL | O51: ARTICULACION DE LA RED ASISTENCIAL | P51: No Ejecutado
A52: 1057532-331-PC26 | B52: PC26 | C52: Bienes y Servicios | D52: Compra de Insumos de Cafetería reuniones ordinarias anuales de Salud Pueblos Originarios | E52: Alimentación | F52: 1 | G52: Pedro Huito | H52: 46082 | I52: Apoyo Salud Intercultural | J52: 1 | K52: 46082 | L52: 1352694 | M52: DEPARTAMENTO DE PARTICIPACION CIUDADANA, SATISFACCION USUARIA Y SALUD PUEBLOS OR | N52: SUBDIRECCION DE GESTION ASISTENCIAL | O52: PARTICIPACION CIUDADANA, SATISFACCION USUARIA Y SALUD PUEBLOS OR | P52: No Ejecutado
A53: 1057532-332-PC26 | B53: PC26 | C53: Bienes y Servicios | D53: Protectores solares FPS 50 para funcionarios y usuarios taller huerto | E53: Protectores Solares | F53: 1 | G53: Camilo Martínez | H53: 46023 | I53: Director(S) | J53: 1 | K53: 46023 | L53: 300000 | M53: DEPARTAMENTO DE SALUD MENTAL | N53: SUBDIRECCION DE GESTION ASISTENCIAL | O53: SALUD MENTAL | P53: No Ejecutado
A54: 1057532-333-PC24 | B54: Arrastre | C54: Bienes y Servicios | D54: Convenio - SOPORTE Y MANTENIMIENTO SISTEMA DE REPETICIÓN VHF SERVICIO DE SALUD OSORNO 2025-2026 | E54: Servicio | F54: 1 | G54: CATALINA VERA CASTRO | H54: 45444 | I54: COORDINADORA EMERGENCIA | J54: 24 | K54: 01-01-2025,01-02-2025,01-03-2025,01-04-2025,01-05-2025,01-06-2025,01-07-2025,01-08-2025,01-09-2025,01-10-2025,01-11-2025,01-12-2025,01-01-2026,01-02-2026,01-03-2026,01-04-2026,01-05-2026,01-06-2026,01-07-2026,01-08-2026,01-09-2026,01-10-2026,01-11-2026,01-12-2026 | L54: 10000004 | M54: SUB. DPTO. GESTION DEL RIESGO EN EMERGENCIAS, DESASTRES Y TELECOMUNICACIONES | N54: DIRECCIÓN | O54: SUB. DPTO. GESTION DEL RIESGO EN EMERGENCIAS, DESASTRES Y TELECOMUNICACIONES | P54: No Ejecutado
A55: 1057532-333-PC26 | B55: PC26 | C55: Bienes y Servicios | D55: TEST DE DETECCION DE DROGAS | E55: Test | F55: 1 | G55: Carolina Silva | H55: 46296 | I55: Encargada De Compras | J55: 1 | K55: 46296 | L55: 800000 | M55: DEPARTAMENTO DE SALUD MENTAL | N55: SUBDIRECCION DE GESTION ASISTENCIAL | O55: SALUD MENTAL | P55: No Ejecutado
A56: 1057532-334-PC26 | B56: PC26 | C56: Bienes y Servicios | D56: PAC insumos clínicos unidad de enfermería 2026. | E56: Biombo, pesa | F56: 6 | G56: Pedro Fritz | H56: 46054 | I56: DIRECTOR COSAM | J56: 1 | K56: 46054 | L56: 124000 | M56: CENTRO DE SALUD MENTAL COMUNITARIO COSAM ORIENTE | N56: SUBDIRECCION DE GESTION ASISTENCIAL | O56: SALUD MENTAL | P56: No Ejecutado
A57: 1057532-334-PC26 | B57: PC26 | C57: Bienes y Servicios | D57: PAC insumos clínicos unidad de enfermería 2026. | E57: Caja | F57: 6 | G57: Pedro Fritz | H57: 46054 | I57: DIRECTOR COSAM | J57: 1 | K57: 46054 | L57: 8000 | M57: CENTRO DE SALUD MENTAL COMUNITARIO COSAM ORIENTE | N57: SUBDIRECCION DE GESTION ASISTENCIAL | O57: SALUD MENTAL | P57: No Ejecutado
A58: 1057532-334-PC26 | B58: PC26 | C58: Bienes y Servicios | D58: PAC insumos clínicos unidad de enfermería 2026. | E58: Cooler | F58: 6 | G58: Pedro Fritz | H58: 46054 | I58: DIRECTOR COSAM | J58: 1 | K58: 46054 | L58: 25000 | M58: CENTRO DE SALUD MENTAL COMUNITARIO COSAM ORIENTE | N58: SUBDIRECCION DE GESTION ASISTENCIAL | O58: SALUD MENTAL | P58: No Ejecutado
A59: 1057532-334-PC26 | B59: PC26 | C59: Bienes y Servicios | D59: PAC insumos clínicos unidad de enfermería 2026. | E59: Equipo curación, algodón | F59: 6 | G59: Pedro Fritz | H59: 46054 | I59: DIRECTOR COSAM | J59: 1 | K59: 46054 | L59: 70000 | M59: CENTRO DE SALUD MENTAL COMUNITARIO COSAM ORIENTE | N59: SUBDIRECCION DE GESTION ASISTENCIAL | O59: SALUD MENTAL | P59: No Ejecutado
A60: 1057532-334-PC26 | B60: PC26 | C60: Bienes y Servicios | D60: PAC insumos clínicos unidad de enfermería 2026. | E60: Insumos clínicos | F60: 6 | G60: Pedro Fritz | H60: 46054 | I60: DIRECTOR COSAM | J60: 1 | K60: 46054 | L60: 699036 | M60: CENTRO DE SALUD MENTAL COMUNITARIO COSAM ORIENTE | N60: SUBDIRECCION DE GESTION ASISTENCIAL | O60: SALUD MENTAL | P60: No Ejecutado
A61: 1057532-334-PC26 | B61: PC26 | C61: Bienes y Servicios | D61: PAC insumos clínicos unidad de enfermería 2026. | E61: Tiras, test rápido, alcohol | F61: 6 | G61: Pedro Fritz | H61: 46054 | I61: DIRECTOR COSAM | J61: 1 | K61: 46054 | L61: 240012 | M61: CENTRO DE SALUD MENTAL COMUNITARIO COSAM ORIENTE | N61: SUBDIRECCION DE GESTION ASISTENCIAL | O61: SALUD MENTAL | P61: No Ejecutado
A62: 1057532-335-PC26 | B62: PC26 | C62: Bienes y Servicios | D62: Compra de Insumos de Cafetería reuniones ordinarias anuales Participación, Trato Usuario, Salud Pueblos Originarios | E62: Alimentación | F62: 2 | G62: Daniela Barria | H62: 46082 | I62: Encargada Trato Usuario | J62: 1 | K62: 46082 | L62: 921162 | M62: DEPARTAMENTO DE PARTICIPACION CIUDADANA, SATISFACCION USUARIA Y SALUD PUEBLOS OR | N62: SUBDIRECCION DE GESTION ASISTENCIAL | O62: PARTICIPACION CIUDADANA, SATISFACCION USUARIA Y SALUD PUEBLOS OR | P62: No Ejecutado
A63: 1057532-335-PC26 | B63: PC26 | C63: Bienes y Servicios | D63: Compra de Insumos de Cafetería reuniones ordinarias anuales Participación, Trato Usuario, Salud Pueblos Originarios | E63: Insumos | F63: 2 | G63: Daniela Barria | H63: 46082 | I63: Encargada Trato Usuario | J63: 1 | K63: 46082 | L63: 86299 | M63: DEPARTAMENTO DE PARTICIPACION CIUDADANA, SATISFACCION USUARIA Y SALUD PUEBLOS OR | N63: SUBDIRECCION DE GESTION ASISTENCIAL | O63: PARTICIPACION CIUDADANA, SATISFACCION USUARIA Y SALUD PUEBLOS OR | P63: No Ejecutado
A64: 1057532-336-PC26 | B64: PC26 | C64: Bienes y Servicios | D64: Impresión Talonarios de Registro de Solicitudes Ciudadanas | E64: folleteria | F64: 1 | G64: Daniela Barria | H64: 46082 | I64: Encargada Trato Usuario | J64: 1 | K64: 46082 | L64: 400000 | M64: DEPARTAMENTO DE PARTICIPACION CIUDADANA, SATISFACCION USUARIA Y SALUD PUEBLOS OR | N64: SUBDIRECCION DE GESTION ASISTENCIAL | O64: PARTICIPACION CIUDADANA, SATISFACCION USUARIA Y SALUD PUEBLOS OR | P64: No Ejecutado
A65: 1057532-337-PC26 | B65: PC26 | C65: Bienes y Servicios | D65: INSUMOS DE FARMACIA 2026 | E65: Insumos Computacionales | F65: 5 | G65: Pedro Fritz | H65: 46023 | I65: DIRECTOR COSAM | J65: 1 | K65: 46023 | L65: 104004 | M65: CENTRO DE SALUD MENTAL COMUNITARIO COSAM ORIENTE | N65: SUBDIRECCION DE GESTION ASISTENCIAL | O65: SALUD MENTAL | P65: No Ejecutado
A66: 1057532-337-PC26 | B66: PC26 | C66: Bienes y Servicios | D66: INSUMOS DE FARMACIA 2026 | E66: Insumos Computacionales | F66: 5 | G66: Pedro Fritz | H66: 46082 | I66: DIRECTOR COSAM | J66: 1 | K66: 46082 | L66: 1900044 | M66: CENTRO DE SALUD MENTAL COMUNITARIO COSAM ORIENTE | N66: SUBDIRECCION DE GESTION ASISTENCIAL | O66: SALUD MENTAL | P66: No Ejecutado
... A85: 1057532-350-PC26 | B85: PC26 | C85: Bienes y Servicios | D85: INSUMOS COMPUTACIONALES | E85: WI FI | F85: 3 | G85: Carolina Silva | H85: 46023 | I85: Encargada De Compras | J85: 1 | K85: 46023 | L85: 900000 | M85: DEPARTAMENTO DE SALUD MENTAL | N85: SUBDIRECCION DE GESTION ASISTENCIAL | O85: SALUD MENTAL | P85: No Ejecutado
A86: 1057532-351-PC26 | B86: PC26 | C86: Bienes y Servicios | D86: Convenio - CONVENIO DE ADQUISICION DE KIT POINT OF CARE (POC) CON ARRIENDO DE EQUIPOS PARA ANALISIS DE MUESTRAS, SSO | E86: Convenio Kit Point | F86: 1 | G86: Sofia Reyes | H86: 46204 | I86: Encargada Apoyo Diagnóstico Laboratorio | J86: 12 | K86: 01-08-2026,01-09-2026,01-10-2026,01-11-2026,01-12-2026,01-01-2027,01-02-2027,01-03-2027,01-04-2027,01-05-2027,01-06-2027,01-07-2027 | L86: 31250000 | M86: DEPARTAMENTO ARTICULACION DE LA RED ASISTENCIAL | N86: SUBDIRECCION DE GESTION ASISTENCIAL | O86: ARTICULACION DE LA RED ASISTENCIAL | P86: No Ejecutado
A87: 1057532-352-PC26 | B87: PC26 | C87: Bienes y Servicios | D87: Muestra tu Pausa Activa | E87: Instrumentos Deportivos | F87: 1 | G87: Marcia Delarze | H87: 46082 | I87: Kinesióloga | J87: 1 | K87: 46082 | L87: 200000 | M87: UNIDAD SAFU | N87: SUBDIRECCION DE GESTION Y DESARROLLO DE LAS PERSONAS | O87: CALIDAD DE VIDA | P87: No Ejecutado
A88: 1057532-353-PC26 | B88: PC26 | C88: Bienes y Servicios | D88: PLAN DE COMPRAS AÑO 2026 LEY N°19.664 Y FORMACION DE ESPECIALISTAS S.S.O | E88: Alimentación | F88: 7 | G88: Jocelyne Prieto | H88: 46054 | I88: Jefa Seccion Gestion Y Desarrollo Ley Medica | J88: 1 | K88: 46054 | L88: 107000 | M88: SECCION GESTION Y DESARROLLO LEY MEDICA | N88: SUBDIRECCION DE GESTION Y DESARROLLO DE LAS PERSONAS | O88: GESTION DE LAS PERSONAS | P88: No Ejecutado
A89: 1057532-353-PC26 | B89: PC26 | C89: Bienes y Servicios | D89: PLAN DE COMPRAS AÑO 2026 LEY N°19.664 Y FORMACION DE ESPECIALISTAS S.S.O | E89: Materiales de Oficina | F89: 7 | G89: Jocelyne Prieto | H89: 46054 | I89: Jefa Seccion Gestion Y Desarrollo Ley Medica | J89: 1 | K89: 46054 | L89: 15000 | M89: SECCION GESTION Y DESARROLLO LEY MEDICA | N89: SUBDIRECCION DE GESTION Y DESARROLLO DE LAS PERSONAS | O89: GESTION DE LAS PERSONAS | P89: No Ejecutado
A90: 1057532-353-PC26 | B90: PC26 | C90: Bienes y Servicios | D90: PLAN DE COMPRAS AÑO 2026 LEY N°19.664 Y FORMACION DE ESPECIALISTAS S.S.O | E90: Menaje Cafeteria | F90: 7 | G90: Jocelyne Prieto | H90: 46054 | I90: Jefa Seccion Gestion Y Desarrollo Ley Medica | J90: 1 | K90: 46054 | L90: 10000 | M90: SECCION GESTION Y DESARROLLO LEY MEDICA | N90: SUBDIRECCION DE GESTION Y DESARROLLO DE LAS PERSONAS | O90: GESTION DE LAS PERSONAS | P90: No Ejecutado
A91: 1057532-353-PC26 | B91: PC26 | C91: Bienes y Servicios | D91: PLAN DE COMPRAS AÑO 2026 LEY N°19.664 Y FORMACION DE ESPECIALISTAS S.S.O | E91: Pendrive | F91: 7 | G91: Jocelyne Prieto | H91: 46143 | I91: Jefa Seccion Gestion Y Desarrollo Ley Medica | J91: 1 | K91: 46143 | L91: 25000 | M91: SECCION GESTION Y DESARROLLO LEY MEDICA | N91: SUBDIRECCION DE GESTION Y DESARROLLO DE LAS PERSONAS | O91: GESTION DE LAS PERSONAS | P91: No Ejecutado
A92: 1057532-353-PC26 | B92: PC26 | C92: Bienes y Servicios | D92: PLAN DE COMPRAS AÑO 2026 LEY N°19.664 Y FORMACION DE ESPECIALISTAS S.S.O | E92: Publicación Diario | F92: 7 | G92: Jocelyne Prieto | H92: 46327 | I92: Jefa Seccion Gestion Y Desarrollo Ley Medica | J92: 1 | K92: 46327 | L92: 120000 | M92: SECCION GESTION Y DESARROLLO LEY MEDICA | N92: SUBDIRECCION DE GESTION Y DESARROLLO DE LAS PERSONAS | O92: GESTION DE LAS PERSONAS | P92: No Ejecutado
A93: 1057532-353-PC26 | B93: PC26 | C93: Bienes y Servicios | D93: PLAN DE COMPRAS AÑO 2026 LEY N°19.664 Y FORMACION DE ESPECIALISTAS S.S.O | E93: Servicio Cafeteria | F93: 7 | G93: Jocelyne Prieto | H93: 46143 | I93: Jefa Seccion Gestion Y Desarrollo Ley Medica | J93: 1 | K93: 46143 | L93: 1400001 | M93: SECCION GESTION Y DESARROLLO LEY MEDICA | N93: SUBDIRECCION DE GESTION Y DESARROLLO DE LAS PERSONAS | O93: GESTION DE LAS PERSONAS | P93: No Ejecutado
A94: 1057532-353-PC26 | B94: PC26 | C94: Bienes y Servicios | D94: PLAN DE COMPRAS AÑO 2026 LEY N°19.664 Y FORMACION DE ESPECIALISTAS S.S.O | E94: Servicio Traslado | F94: 7 | G94: Jocelyne Prieto | H94: 46143 | I94: Jefa Seccion Gestion Y Desarrollo Ley Medica | J94: 1 | K94: 46143 | L94: 45000000 | M94: SECCION GESTION Y DESARROLLO LEY MEDICA | N94: SUBDIRECCION DE GESTION Y DESARROLLO DE LAS PERSONAS | O94: GESTION DE LAS PERSONAS | P94: No Ejecutado
A95: 1057532-354-PC26 | B95: PC26 | C95: Bienes y Servicios | D95: Convenio - COMPRA DE KITS PARA DETECCION DE VIRUS Y BACTERIAS RESPIRATORIAS POR METODO MOLECULAR RAPIDO (POC MOLECULAR) | E95: Convenio Kit Point | F95: 1 | G95: Daniela Soto | H95: 46143 | I95: Encargada Apoyo Diagnóstico Laboratorio | J95: 12 | K95: 01-05-2026,01-06-2026,01-07-2026,01-08-2026,01-09-2026,01-10-2026,01-11-2026,01-12-2026,01-01-2027,01-02-2027,01-03-2027,01-04-2027 | L95: 23333328 | M95: DEPARTAMENTO ARTICULACION DE LA RED ASISTENCIAL | N95: SUBDIRECCION DE GESTION ASISTENCIAL | O95: ARTICULACION DE LA RED ASISTENCIAL | P95: No Ejecutado
A96: 1057532-355-PC26 | B96: PC26 | C96: Bienes y Servicios | D96: MEDICINA INTEGRATIVA SAFU | E96: Aromaterapia | F96: 1 | G96: Lhya Kortmann | H96: 46023 | I96: Enfermera | J96: 1 | K96: 46023 | L96: 681264 | M96: UNIDAD SAFU | N96: SUBDIRECCION DE GESTION Y DESARROLLO DE LAS PERSONAS | O96: CALIDAD DE VIDA | P96: No Ejecutado
A97: 1057532-356-PC24 | B97: Arrastre | C97: Bienes y Servicios | D97: Convenio servicio de guardias para la DSSO y sus establecimientos y dispositivos dependientes | E97: Servicio de guardias | F97: 1 | G97: Lorena Torres Castillo | H97: 45444 | I97: Encargada (S) Sección Administración de Contratos | J97: 24 | K97: 01-01-2025,01-02-2025,01-03-2025,01-04-2025,01-05-2025,01-06-2025,01-07-2025,01-08-2025,01-09-2025,01-10-2025,01-11-2025,01-12-2025,01-01-2026,01-02-2026,01-03-2026,01-04-2026,01-05-2026,01-06-2026,01-07-2026,01-08-2026,01-09-2026,01-10-2026,01-11-2026,01-12-2026 | L97: 905196910 | M97: DEPARTAMENTO DE ABASTECIMIENTO Y OPERACIONES | N97: SUBDIRECCION ADMINISTRATIVA | O97: ABASTECIMIENTO Y OPERACIONES | P97: No Ejecutado
A98: 1057532-356-PC26 | B98: PC26 | C98: Bienes y Servicios | D98: Adquisición Insumos para realizar el aseo y confort de usuarios/as con Dependencia Severa. | E98: Crema | F98: 3 | G98: Camila Alvarez | H98: 46113 | I98: Kinesióloga Encargada Programa Atencion Domiciliaria Para Personas Con Dependencia Severa | J98: 1 | K98: 46113 | L98: 2175000 | M98: DEPARTAMENTO ATENCION PRIMARIA | N98: SUBDIRECCION DE GESTION ASISTENCIAL | O98: ATENCION PRIMARIA | P98: No Ejecutado
A99: 1057532-356-PC26 | B99: PC26 | C99: Bienes y Servicios | D99: Adquisición Insumos para realizar el aseo y confort de usuarios/as con Dependencia Severa. | E99: Pañales | F99: 3 | G99: Camila Alvarez | H99: 46113 | I99: Kinesióloga Encargada Programa Atencion Domiciliaria Para Personas Con Dependencia Severa | J99: 1 | K99: 46113 | L99: 8155836 | M99: DEPARTAMENTO ATENCION PRIMARIA | N99: SUBDIRECCION DE GESTION ASISTENCIAL | O99: ATENCION PRIMARIA | P99: No Ejecutado
A100: 1057532-356-PC26 | B100: PC26 | C100: Bienes y Servicios | D100: Adquisición Insumos para realizar el aseo y confort de usuarios/as con Dependencia Severa. | E100: Producto de Aseo | F100: 3 | G100: Camila Alvarez | H100: 46113 | I100: Kinesióloga Encargada Programa Atencion Domiciliaria Para Personas Con Dependencia Severa | J100: 1 | K100: 46113 | L100: 1672500 | M100: DEPARTAMENTO ATENCION PRIMARIA | N100: SUBDIRECCION DE GESTION ASISTENCIAL | O100: ATENCION PRIMARIA | P100: No Ejecutado
A101: 1057532-357-PC26 | B101: PC26 | C101: Bienes y Servicios | D101: INSUMOS LEY 20.000 | E101: Material de Oficina | F101: 2 | G101: Fernando Roman | H101: 46082 | I101: Jefe Subdepartamento Farmacia | J101: 1 | K101: 46082 | L101: 509936 | M101: SUB. DPTO. DE FARMACIA | N101: SUBDIRECCION DE GESTION ASISTENCIAL | O101: ARTICULACION DE LA RED ASISTENCIAL | P101: No Ejecutado
A102: 1057532-357-PC26 | B102: PC26 | C102: Bienes y Servicios | D102: INSUMOS LEY 20.000 | E102: Toner | F102: 2 | G102: Fernando Roman | H102: 46082 | I102: Jefe Subdepartamento Farmacia | J102: 1 | K102: 46082 | L102: 48000 | M102: SUB. DPTO. DE FARMACIA | N102: SUBDIRECCION DE GESTION ASISTENCIAL | O102: ARTICULACION DE LA RED ASISTENCIAL | P102: No Ejecutado
A103: 1057532-358-PC26 | B103: PC26 | C103: Bienes y Servicios | D103: Zumba a todo corazón | E103: Alimentación | F103: 3 | G103: Daniela Cancino | H103: 46235 | I103: Nutricionista | J103: 1 | K103: 46235 | L103: 185040 | M103: UNIDAD SAFU | N103: SUBDIRECCION DE GESTION Y DESARROLLO DE LAS PERSONAS | O103: CALIDAD DE VIDA | P103: No Ejecutado
A104: 1057532-358-PC26 | B104: PC26 | C104: Bienes y Servicios | D104: Zumba a todo corazón | E104: Decoración | F104: 3 | G104: Daniela Cancino | H104: 46235 | I104: Nutricionista | J104: 1 | K104: 46235 | L104: 270160 | M104: UNIDAD SAFU | N104: SUBDIRECCION DE GESTION Y DESARROLLO DE LAS PERSONAS | O104: CALIDAD DE VIDA | P104: No Ejecutado
A105: 1057532-358-PC26 | B105: PC26 | C105: Bienes y Servicios | D105: Zumba a todo corazón | E105: Instructora | F105: 3 | G105: Daniela Cancino | H105: 46235 | I105: Nutricionista | J105: 1 | K105: 46235 | L105: 220000 | M105: UNIDAD SAFU | N105: SUBDIRECCION DE GESTION Y DESARROLLO DE LAS PERSONAS | O105: CALIDAD DE VIDA | P105: No Ejecutado
A106: 1057532-359-PC26 | B106: PC26 | C106: Bienes y Servicios | D106: Mantenimiento baños y camarines | E106: Mantencion | F106: 1 | G106: Pedro Fritz | H106: 46054 | I106: Director | J106: 1 | K106: 46054 | L106: 700002 | M106: CENTRO DE SALUD MENTAL COMUNITARIO COSAM ORIENTE | N106: SUBDIRECCION DE GESTION ASISTENCIAL | O106: SALUD MENTAL | P106: No Ejecutado
A107: 1057532-360-PC26 | B107: PC26 | C107: Bienes y Servicios | D107: Construcción de radieres en estacionamiento | E107: Mantencion | F107: 1 | G107: Pedro Fritz | H107: 46054 | I107: Director | J107: 1 | K107: 46054 | L107: 7000008 | M107: CENTRO DE SALUD MENTAL COMUNITARIO COSAM ORIENTE | N107: SUBDIRECCION DE GESTION ASISTENCIAL | O107: SALUD MENTAL | P107: No Ejecutado
A108: 1057532-361-PC26 | B108: PC26 | C108: Bienes y Servicios | D108: Mantención comedor lado patio interior | E108: Mantencion | F108: 1 | G108: Pedro Fritz | H108: 46082 | I108: Director | J108: 1 | K108: 46082 | L108: 800000 | M108: CENTRO DE SALUD MENTAL COMUNITARIO COSAM ORIENTE | N108: SUBDIRECCION DE GESTION ASISTENCIAL | O108: SALUD MENTAL | P108: No Ejecutado
A109: 1057532-362-PC26 | B109: PC26 | C109: Bienes y Servicios | D109: Pintado de muros perimetrales de edificio. | E109: Mantencion | F109: 1 | G109: Pedro Fritz | H109: 46054 | I109: Director | J109: 1 | K109: 46054 | L109: 3500000 | M109: CENTRO DE SALUD MENTAL COMUNITARIO COSAM ORIENTE | N109: SUBDIRECCION DE GESTION ASISTENCIAL | O109: SALUD MENTAL | P109: No Ejecutado
... A117: 1057532-371-PC26 | B117: PC26 | C117: Bienes y Servicios | D117: Mantenimiento planta elevadora aguas servidas | E117: Mantencion | F117: 1 | G117: Pedro Fritz | H117: 46204 | I117: Director | J117: 1 | K117: 46174 | L117: 1500000 | M117: CENTRO DE SALUD MENTAL COMUNITARIO COSAM ORIENTE | N117: SUBDIRECCION DE GESTION ASISTENCIAL | O117: SALUD MENTAL | P117: No Ejecutado
A118: 1057532-372-PC26 | B118: PC26 | C118: Bienes y Servicios | D118: Suministro de Pellet para sistema de calefacción | E118: Pellet | F118: 1 | G118: Pedro Fritz | H118: 46082 | I118: Director | J118: 4 | K118: 01-03-2026,01-05-2026,01-07-2026,01-09-2026 | L118: 17500000 | M118: CENTRO DE SALUD MENTAL COMUNITARIO COSAM ORIENTE | N118: SUBDIRECCION DE GESTION ASISTENCIAL | O118: SALUD MENTAL | P118: No Ejecutado
A119: 1057532-373-PC25 | B119: Arrastre | C119: Bienes y Servicios | D119: Convenio - Movilización para el traslado de usuarios y funcionarios CDR adulto mayor Kumelen año 2026 | E119: Movilizacion Kumelen | F119: 1 | G119: Luis Flores Merino | H119: 45839 | I119: Coordinador | J119: 12 | K119: 01-02-2026,01-03-2026,01-04-2026,01-05-2026,01-06-2026,01-07-2026,01-08-2026,01-09-2026,01-10-2026,01-11-2026,01-12-2026,01-01-2027 | L119: 36208337 | M119: CDR KUMELEN | N119: SUBDIRECCION DE GESTION ASISTENCIAL | O119: SALUD MENTAL | P119: No Ejecutado
A120: 1057532-373-PC26 | B120: PC26 | C120: Bienes y Servicios | D120: Suministro de diesel para generador eléctrico | E120: Combustibles | F120: 1 | G120: Pedro Fritz | H120: 46143 | I120: Director | J120: 1 | K120: 46143 | L120: 1820000 | M120: CENTRO DE SALUD MENTAL COMUNITARIO COSAM ORIENTE | N120: SUBDIRECCION DE GESTION ASISTENCIAL | O120: SALUD MENTAL | P120: No Ejecutado
A121: 1057532-374-PC25 | B121: Arrastre | C121: Bienes y Servicios | D121: Convenio - Movilizacion para el traslado de funcionarios CDR Adulto Mayor KÜMELEN 2026 | E121: Movilizacion | F121: 1 | G121: Luis Flores Merino | H121: 45870 | I121: Coordinador | J121: 12 | K121: 01-02-2026,01-03-2026,01-04-2026,01-05-2026,01-06-2026,01-07-2026,01-08-2026,01-09-2026,01-10-2026,01-11-2026,01-12-2026,01-01-2027 | L121: 28875000 | M121: CDR KUMELEN | N121: SUBDIRECCION DE GESTION ASISTENCIAL | O121: SALUD MENTAL | P121: No Ejecutado
A122: 1057532-374-PC26 | B122: PC26 | C122: Bienes y Servicios | D122: Reemplazo de equipo iluminación interior. | E122: Mantencion | F122: 1 | G122: Pedro Fritz | H122: 46082 | I122: Director | J122: 1 | K122: 46082 | L122: 1200000 | M122: CENTRO DE SALUD MENTAL COMUNITARIO COSAM ORIENTE | N122: SUBDIRECCION DE GESTION ASISTENCIAL | O122: SALUD MENTAL | P122: No Ejecutado
A123: 1057532-375-PC25 | B123: Arrastre | C123: Bienes y Servicios | D123: Convenio - ADQUISICION DE KIT POINT OF CARE (POC) CON ARRIENDO DE EQUIPO PARA ANALISIS DE MUESTRAS POR 12 MESES, SSO | E123: Suministro KIT Point | F123: 1 | G123: SOFIA REYES ALARCON | H123: 45839 | I123: COMPRADOR | J123: 12 | K123: 01-08-2025,01-09-2025,01-10-2025,01-11-2025,01-12-2025,01-01-2026,01-02-2026,01-03-2026,01-04-2026,01-05-2026,01-06-2026,01-07-2026 | L123: 52500000 | M123: DEPARTAMENTO ARTICULACION DE LA RED ASISTENCIAL | N123: SUBDIRECCION DE GESTION ASISTENCIAL | O123: ARTICULACION DE LA RED ASISTENCIAL | P123: No Ejecutado
A124: 1057532-375-PC26 | B124: PC26 | C124: Bienes y Servicios | D124: Mantenimiento sensores de humo | E124: Mantencion | F124: 1 | G124: Pedro Fritz | H124: 46174 | I124: Director | J124: 1 | K124: 46174 | L124: 2500020 | M124: CENTRO DE SALUD MENTAL COMUNITARIO COSAM ORIENTE | N124: SUBDIRECCION DE GESTION ASISTENCIAL | O124: SALUD MENTAL | P124: No Ejecutado
A125: 1057532-376-PC25 | B125: Arrastre | C125: Bienes y Servicios | D125: Convenio - Pac PASAJES 2025-2026 DSSO | E125: Pasajes | F125: 1 | G125: Sandra Espinoza | H125: 45809 | I125: PAC Pasajes DSSO 2025-2026 | J125: 18 | K125: 01-07-2025,01-08-2025,01-09-2025,01-10-2025,01-11-2025,01-12-2025,01-01-2026,01-02-2026,01-03-2026,01-04-2026,01-05-2026,01-06-2026,01-07-2026,01-08-2026,01-09-2026,01-10-2026,01-11-2026,01-12-2026 | L125: 11000004 | M125: DEPARTAMENTO DE ABASTECIMIENTO Y OPERACIONES | N125: SUBDIRECCION ADMINISTRATIVA | O125: ABASTECIMIENTO Y OPERACIONES | P125: No Ejecutado
...

Sheet ListadoProyectos (10)
A1: Organismo | B1: ID Proyecto | C1: Unidad de Compra | D1: ID Proyecto | E1: Tipo Proyecto | F1: Estado Proyecto | G1: Código presupuestario | H1: Nombre Proyecto | I1: Descripción Proyecto | J1: Cantidad de Ítems | K1: Nombre ítem | L1: Tipo compra | M1: Cantidad Productos | N1: Monto Unitario Ítem | O1: Monto Total Ítem Año 2026 | P1: Cantidad OC | Q1: Meses envío OC | R1: Nombre responsable | S1: Cargo responsable | T1: Teléfono responsable | U1: Correo responsable | V1: Fecha de Inicio Compra | W1: Fecha Publicación PAC 2026 | X1: Cantidad OC Asociadas Ítem 2026 | Y1: OC Asociada Item 2026 | Z1: Item De Arraste | AA1: Monto De Arrastre | AB1: Meses envio OC de Arraste | AC1: PAC | AD1: TIPO PAC
A2: SERVICIO DE SALUD OSORNO | B2: 1057532-156-PC24 | C2: Bienes y Servicios | D2: 1057532-156-PC24 | E2: Proyecto operacional | F2: Publicado | G2: 22.11.003 | H2: servicios de control de asistencia del servicio de salud osorno | I2: El presente proyecto tiene por objeto la contratación de un servicio de software y equipamiento de reloj control para todos los establecimientos dependientes de la Dirección del Servicio de Salud Osorno, por un período de 36 meses. | J2: 2 | K2: Servicio Control Asistencia | L2: 1 | M2: 1 | N2: 90000000 | O2: 2500000 | P2: 36 | Q2: 01-01-2024,01-02-2024,01-03-2024,01-04-2024,01-05-2024,01-06-2024,01-07-2024,01-08-2024,01-09-2024,01-10-2024,01-11-2024,01-12-2024,01-01-2025,01-02-2025,01-03-2025,01-04-2025,01-05-2025,01-06-2025,01-07-2025,01-08-2025,01-09-2025,01-10-2025,01-11-2025,01-12-2025,01-01-2026,01-02-2026,01-03-2026,01-04-2026,01-05-2026,01-06-2026,01-07-2026,01-08-2026,01-09-2026,01-10-2026,01-11-2026,01-12-2026 | R2: Bruno Ojeda Alvarez | S2: Jefe Depto. Tecnologías de la Información | T2: 64-2335840- | U2: bruno.ojeda@redsalud.gov.cl | V2: 45292 | W2: 45478 | X2: 54 | Y2: 1057532-268-SE25 | Z2: 1 | AA2: 2500000 | AB2: 46054 | AC2: Arrastre | AD2: =VLOOKUP(D2,Oficial!A:C,3,0) -> Arrastre
A3: SERVICIO DE SALUD OSORNO | B3: 1057532-156-PC24 | C3: Bienes y Servicios | D3: 1057532-156-PC24 | E3: Proyecto operacional | F3: Publicado | G3: 22.11.003 | H3: servicios de control de asistencia del servicio de salud osorno | I3: El presente proyecto tiene por objeto la contratación de un servicio de software y equipamiento de reloj control para todos los establecimientos dependientes de la Dirección del Servicio de Salud Osorno, por un período de 36 meses. | J3: 2 | K3: Servicio Control Asistencia | L3: 1 | M3: 1 | N3: 90000000 | O3: 2500000 | P3: 36 | Q3: 01-01-2024,01-02-2024,01-03-2024,01-04-2024,01-05-2024,01-06-2024,01-07-2024,01-08-2024,01-09-2024,01-10-2024,01-11-2024,01-12-2024,01-01-2025,01-02-2025,01-03-2025,01-04-2025,01-05-2025,01-06-2025,01-07-2025,01-08-2025,01-09-2025,01-10-2025,01-11-2025,01-12-2025,01-01-2026,01-02-2026,01-03-2026,01-04-2026,01-05-2026,01-06-2026,01-07-2026,01-08-2026,01-09-2026,01-10-2026,01-11-2026,01-12-2026 | R3: Bruno Ojeda Alvarez | S3: Jefe Depto. Tecnologías de la Información | T3: 64-2335840- | U3: bruno.ojeda@redsalud.gov.cl | V3: 45292 | W3: 45478 | X3: 54 | Y3: 1057532-268-SE25 | Z3: 1 | AA3: 2500000 | AB3: 46113 | AC3: Arrastre | AD3: =VLOOKUP(D3,Oficial!A:C,3,0) -> Arrastre
A4: SERVICIO DE SALUD OSORNO | B4: 1057532-156-PC24 | C4: Bienes y Servicios | D4: 1057532-156-PC24 | E4: Proyecto operacional | F4: Publicado | G4: 22.11.003 | H4: servicios de control de asistencia del servicio de salud osorno | I4: El presente proyecto tiene por objeto la contratación de un servicio de software y equipamiento de reloj control para todos los establecimientos dependientes de la Dirección del Servicio de Salud Osorno, por un período de 36 meses. | J4: 2 | K4: Servicio Control Asistencia | L4: 1 | M4: 1 | N4: 90000000 | O4: 2500000 | P4: 36 | Q4: 01-01-2024,01-02-2024,01-03-2024,01-04-2024,01-05-2024,01-06-2024,01-07-2024,01-08-2024,01-09-2024,01-10-2024,01-11-2024,01-12-2024,01-01-2025,01-02-2025,01-03-2025,01-04-2025,01-05-2025,01-06-2025,01-07-2025,01-08-2025,01-09-2025,01-10-2025,01-11-2025,01-12-2025,01-01-2026,01-02-2026,01-03-2026,01-04-2026,01-05-2026,01-06-2026,01-07-2026,01-08-2026,01-09-2026,01-10-2026,01-11-2026,01-12-2026 | R4: Bruno Ojeda Alvarez | S4: Jefe Depto. Tecnologías de la Información | T4: 64-2335840- | U4: bruno.ojeda@redsalud.gov.cl | V4: 45292 | W4: 45478 | X4: 54 | Y4: 1057532-266-SE25 | Z4: 1 | AA4: 2500000 | AB4: 46054 | AC4: Arrastre | AD4: =VLOOKUP(D4,Oficial!A:C,3,0) -> Arrastre
A5: SERVICIO DE SALUD OSORNO | B5: 1057532-156-PC24 | C5: Bienes y Servicios | D5: 1057532-156-PC24 | E5: Proyecto operacional | F5: Publicado | G5: 22.11.003 | H5: servicios de control de asistencia del servicio de salud osorno | I5: El presente proyecto tiene por objeto la contratación de un servicio de software y equipamiento de reloj control para todos los establecimientos dependientes de la Dirección del Servicio de Salud Osorno, por un período de 36 meses. | J5: 2 | K5: Servicio Control Asistencia | L5: 1 | M5: 1 | N5: 90000000 | O5: 2500000 | P5: 36 | Q5: 01-01-2024,01-02-2024,01-03-2024,01-04-2024,01-05-2024,01-06-2024,01-07-2024,01-08-2024,01-09-2024,01-10-2024,01-11-2024,01-12-2024,01-01-2025,01-02-2025,01-03-2025,01-04-2025,01-05-2025,01-06-2025,01-07-2025,01-08-2025,01-09-2025,01-10-2025,01-11-2025,01-12-2025,01-01-2026,01-02-2026,01-03-2026,01-04-2026,01-05-2026,01-06-2026,01-07-2026,01-08-2026,01-09-2026,01-10-2026,01-11-2026,01-12-2026 | R5: Bruno Ojeda Alvarez | S5: Jefe Depto. Tecnologías de la Información | T5: 64-2335840- | U5: bruno.ojeda@redsalud.gov.cl | V5: 45292 | W5: 45478 | X5: 54 | Y5: 1057532-266-SE25 | Z5: 1 | AA5: 2500000 | AB5: 46357 | AC5: Arrastre | AD5: =VLOOKUP(D5,Oficial!A:C,3,0) -> Arrastre
A6: SERVICIO DE SALUD OSORNO | B6: 1057532-156-PC24 | C6: Bienes y Servicios | D6: 1057532-156-PC24 | E6: Proyecto operacional | F6: Publicado | G6: 22.11.003 | H6: servicios de control de asistencia del servicio de salud osorno | I6: El presente proyecto tiene por objeto la contratación de un servicio de software y equipamiento de reloj control para todos los establecimientos dependientes de la Dirección del Servicio de Salud Osorno, por un período de 36 meses. | J6: 2 | K6: Servicio Control Asistencia | L6: 1 | M6: 1 | N6: 90000000 | O6: 2500000 | P6: 36 | Q6: 01-01-2024,01-02-2024,01-03-2024,01-04-2024,01-05-2024,01-06-2024,01-07-2024,01-08-2024,01-09-2024,01-10-2024,01-11-2024,01-12-2024,01-01-2025,01-02-2025,01-03-2025,01-04-2025,01-05-2025,01-06-2025,01-07-2025,01-08-2025,01-09-2025,01-10-2025,01-11-2025,01-12-2025,01-01-2026,01-02-2026,01-03-2026,01-04-2026,01-05-2026,01-06-2026,01-07-2026,01-08-2026,01-09-2026,01-10-2026,01-11-2026,01-12-2026 | R6: Bruno Ojeda Alvarez | S6: Jefe Depto. Tecnologías de la Información | T6: 64-2335840- | U6: bruno.ojeda@redsalud.gov.cl | V6: 45292 | W6: 45478 | X6: 54 | Y6: 1057532-267-SE25 | Z6: 1 | AA6: 2500000 | AB6: 46327 | AC6: Arrastre | AD6: =VLOOKUP(D6,Oficial!A:C,3,0) -> Arrastre
A7: SERVICIO DE SALUD OSORNO | B7: 1057532-156-PC24 | C7: Bienes y Servicios | D7: 1057532-156-PC24 | E7: Proyecto operacional | F7: Publicado | G7: 22.11.003 | H7: servicios de control de asistencia del servicio de salud osorno | I7: El presente proyecto tiene por objeto la contratación de un servicio de software y equipamiento de reloj control para todos los establecimientos dependientes de la Dirección del Servicio de Salud Osorno, por un período de 36 meses. | J7: 2 | K7: Servicio Control Asistencia | L7: 1 | M7: 1 | N7: 90000000 | O7: 2500000 | P7: 36 | Q7: 01-01-2024,01-02-2024,01-03-2024,01-04-2024,01-05-2024,01-06-2024,01-07-2024,01-08-2024,01-09-2024,01-10-2024,01-11-2024,01-12-2024,01-01-2025,01-02-2025,01-03-2025,01-04-2025,01-05-2025,01-06-2025,01-07-2025,01-08-2025,01-09-2025,01-10-2025,01-11-2025,01-12-2025,01-01-2026,01-02-2026,01-03-2026,01-04-2026,01-05-2026,01-06-2026,01-07-2026,01-08-2026,01-09-2026,01-10-2026,01-11-2026,01-12-2026 | R7: Bruno Ojeda Alvarez | S7: Jefe Depto. Tecnologías de la Información | T7: 64-2335840- | U7: bruno.ojeda@redsalud.gov.cl | V7: 45292 | W7: 45478 | X7: 54 | Y7: 1057532-268-SE25 | Z7: 1 | AA7: 2500000 | AB7: 46174 | AC7: Arrastre | AD7: =VLOOKUP(D7,Oficial!A:C,3,0) -> Arrastre
A8: SERVICIO DE SALUD OSORNO | B8: 1057532-156-PC24 | C8: Bienes y Servicios | D8: 1057532-156-PC24 | E8: Proyecto operacional | F8: Publicado | G8: 22.11.003 | H8: servicios de control de asistencia del servicio de salud osorno | I8: El presente proyecto tiene por objeto la contratación de un servicio de software y equipamiento de reloj control para todos los establecimientos dependientes de la Dirección del Servicio de Salud Osorno, por un período de 36 meses. | J8: 2 | K8: Servicio Control Asistencia | L8: 1 | M8: 1 | N8: 90000000 | O8: 2500000 | P8: 36 | Q8: 01-01-2024,01-02-2024,01-03-2024,01-04-2024,01-05-2024,01-06-2024,01-07-2024,01-08-2024,01-09-2024,01-10-2024,01-11-2024,01-12-2024,01-01-2025,01-02-2025,01-03-2025,01-04-2025,01-05-2025,01-06-2025,01-07-2025,01-08-2025,01-09-2025,01-10-2025,01-11-2025,01-12-2025,01-01-2026,01-02-2026,01-03-2026,01-04-2026,01-05-2026,01-06-2026,01-07-2026,01-08-2026,01-09-2026,01-10-2026,01-11-2026,01-12-2026 | R8: Bruno Ojeda Alvarez | S8: Jefe Depto. Tecnologías de la Información | T8: 64-2335840- | U8: bruno.ojeda@redsalud.gov.cl | V8: 45292 | W8: 45478 | X8: 54 | Y8: 1057532-268-SE25 | Z8: 1 | AA8: 2500000 | AB8: 46327 | AC8: Arrastre | AD8: =VLOOKUP(D8,Oficial!A:C,3,0) -> Arrastre
A9: SERVICIO DE SALUD OSORNO | B9: 1057532-156-PC24 | C9: Bienes y Servicios | D9: 1057532-156-PC24 | E9: Proyecto operacional | F9: Publicado | G9: 22.11.003 | H9: servicios de control de asistencia del servicio de salud osorno | I9: El presente proyecto tiene por objeto la contratación de un servicio de software y equipamiento de reloj control para todos los establecimientos dependientes de la Dirección del Servicio de Salud Osorno, por un período de 36 meses. | J9: 2 | K9: Servicio Control Asistencia | L9: 1 | M9: 1 | N9: 90000000 | O9: 2500000 | P9: 36 | Q9: 01-01-2024,01-02-2024,01-03-2024,01-04-2024,01-05-2024,01-06-2024,01-07-2024,01-08-2024,01-09-2024,01-10-2024,01-11-2024,01-12-2024,01-01-2025,01-02-2025,01-03-2025,01-04-2025,01-05-2025,01-06-2025,01-07-2025,01-08-2025,01-09-2025,01-10-2025,01-11-2025,01-12-2025,01-01-2026,01-02-2026,01-03-2026,01-04-2026,01-05-2026,01-06-2026,01-07-2026,01-08-2026,01-09-2026,01-10-2026,01-11-2026,01-12-2026 | R9: Bruno Ojeda Alvarez | S9: Jefe Depto. Tecnologías de la Información | T9: 64-2335840- | U9: bruno.ojeda@redsalud.gov.cl | V9: 45292 | W9: 45478 | X9: 54 | Y9: 1057532-266-SE25 | Z9: 1 | AA9: 2500000 | AB9: 46204 | AC9: Arrastre | AD9: =VLOOKUP(D9,Oficial!A:C,3,0) -> Arrastre
A10: SERVICIO DE SALUD OSORNO | B10: 1057532-156-PC24 | C10: Bienes y Servicios | D10: 1057532-156-PC24 | E10: Proyecto operacional | F10: Publicado | G10: 22.11.003 | H10: servicios de control de asistencia del servicio de salud osorno | I10: El presente proyecto tiene por objeto la contratación de un servicio de software y equipamiento de reloj control para todos los establecimientos dependientes de la Dirección del Servicio de Salud Osorno, por un período de 36 meses. | J10: 2 | K10: Servicio Control Asistencia | L10: 1 | M10: 1 | N10: 90000000 | O10: 2500000 | P10: 36 | Q10: 01-01-2024,01-02-2024,01-03-2024,01-04-2024,01-05-2024,01-06-2024,01-07-2024,01-08-2024,01-09-2024,01-10-2024,01-11-2024,01-12-2024,01-01-2025,01-02-2025,01-03-2025,01-04-2025,01-05-2025,01-06-2025,01-07-2025,01-08-2025,01-09-2025,01-10-2025,01-11-2025,01-12-2025,01-01-2026,01-02-2026,01-03-2026,01-04-2026,01-05-2026,01-06-2026,01-07-2026,01-08-2026,01-09-2026,01-10-2026,01-11-2026,01-12-2026 | R10: Bruno Ojeda Alvarez | S10: Jefe Depto. Tecnologías de la Información | T10: 64-2335840- | U10: bruno.ojeda@redsalud.gov.cl | V10: 45292 | W10: 45478 | X10: 54 | Y10: 1057532-266-SE25 | Z10: 1 | AA10: 2500000 | AB10: 46023 | AC10: Arrastre | AD10: =VLOOKUP(D10,Oficial!A:C,3,0) -> Arrastre
A11: SERVICIO DE SALUD OSORNO | B11: 1057532-156-PC24 | C11: Bienes y Servicios | D11: 1057532-156-PC24 | E11: Proyecto operacional | F11: Publicado | G11: 22.11.003 | H11: servicios de control de asistencia del servicio de salud osorno | I11: El presente proyecto tiene por objeto la contratación de un servicio de software y equipamiento de reloj control para todos los establecimientos dependientes de la Dirección del Servicio de Salud Osorno, por un período de 36 meses. | J11: 2 | K11: Servicio Control Asistencia | L11: 1 | M11: 1 | N11: 90000000 | O11: 2500000 | P11: 36 | Q11: 01-01-2024,01-02-2024,01-03-2024,01-04-2024,01-05-2024,01-06-2024,01-07-2024,01-08-2024,01-09-2024,01-10-2024,01-11-2024,01-12-2024,01-01-2025,01-02-2025,01-03-2025,01-04-2025,01-05-2025,01-06-2025,01-07-2025,01-08-2025,01-09-2025,01-10-2025,01-11-2025,01-12-2025,01-01-2026,01-02-2026,01-03-2026,01-04-2026,01-05-2026,01-06-2026,01-07-2026,01-08-2026,01-09-2026,01-10-2026,01-11-2026,01-12-2026 | R11: Bruno Ojeda Alvarez | S11: Jefe Depto. Tecnologías de la Información | T11: 64-2335840- | U11: bruno.ojeda@redsalud.gov.cl | V11: 45292 | W11: 45478 | X11: 54 | Y11: 1057532-266-SE25 | Z11: 1 | AA11: 2500000 | AB11: 46174 | AC11: Arrastre | AD11: =VLOOKUP(D11,Oficial!A:C,3,0) -> Arrastre
A12: SERVICIO DE SALUD OSORNO | B12: 1057532-156-PC24 | C12: Bienes y Servicios | D12: 1057532-156-PC24 | E12: Proyecto operacional | F12: Publicado | G12: 22.11.003 | H12: servicios de control de asistencia del servicio de salud osorno | I12: El presente proyecto tiene por objeto la contratación de un servicio de software y equipamiento de reloj control para todos los establecimientos dependientes de la Dirección del Servicio de Salud Osorno, por un período de 36 meses. | J12: 2 | K12: Servicio Control Asistencia | L12: 1 | M12: 1 | N12: 90000000 | O12: 2500000 | P12: 36 | Q12: 01-01-2024,01-02-2024,01-03-2024,01-04-2024,01-05-2024,01-06-2024,01-07-2024,01-08-2024,01-09-2024,01-10-2024,01-11-2024,01-12-2024,01-01-2025,01-02-2025,01-03-2025,01-04-2025,01-05-2025,01-06-2025,01-07-2025,01-08-2025,01-09-2025,01-10-2025,01-11-2025,01-12-2025,01-01-2026,01-02-2026,01-03-2026,01-04-2026,01-05-2026,01-06-2026,01-07-2026,01-08-2026,01-09-2026,01-10-2026,01-11-2026,01-12-2026 | R12: Bruno Ojeda Alvarez | S12: Jefe Depto. Tecnologías de la Información | T12: 64-2335840- | U12: bruno.ojeda@redsalud.gov.cl | V12: 45292 | W12: 45478 | X12: 54 | Y12: 1057532-267-SE25 | Z12: 1 | AA12: 2500000 | AB12: 46113 | AC12: Arrastre | AD12: =VLOOKUP(D12,Oficial!A:C,3,0) -> Arrastre
A13: SERVICIO DE SALUD OSORNO | B13: 1057532-156-PC24 | C13: Bienes y Servicios | D13: 1057532-156-PC24 | E13: Proyecto operacional | F13: Publicado | G13: 22.11.003 | H13: servicios de control de asistencia del servicio de salud osorno | I13: El presente proyecto tiene por objeto la contratación de un servicio de software y equipamiento de reloj control para todos los establecimientos dependientes de la Dirección del Servicio de Salud Osorno, por un período de 36 meses. | J13: 2 | K13: Servicio Control Asistencia | L13: 1 | M13: 1 | N13: 90000000 | O13: 2500000 | P13: 36 | Q13: 01-01-2024,01-02-2024,01-03-2024,01-04-2024,01-05-2024,01-06-2024,01-07-2024,01-08-2024,01-09-2024,01-10-2024,01-11-2024,01-12-2024,01-01-2025,01-02-2025,01-03-2025,01-04-2025,01-05-2025,01-06-2025,01-07-2025,01-08-2025,01-09-2025,01-10-2025,01-11-2025,01-12-2025,01-01-2026,01-02-2026,01-03-2026,01-04-2026,01-05-2026,01-06-2026,01-07-2026,01-08-2026,01-09-2026,01-10-2026,01-11-2026,01-12-2026 | R13: Bruno Ojeda Alvarez | S13: Jefe Depto. Tecnologías de la Información | T13: 64-2335840- | U13: bruno.ojeda@redsalud.gov.cl | V13: 45292 | W13: 45478 | X13: 54 | Y13: 1057532-266-SE25 | Z13: 1 | AA13: 2500000 | AB13: 46082 | AC13: Arrastre | AD13: =VLOOKUP(D13,Oficial!A:C,3,0) -> Arrastre
... A25: SERVICIO DE SALUD OSORNO | B25: 1057532-163-PC24 | C25: Bienes y Servicios | D25: 1057532-163-PC24 | E25: Proyecto estratégico | F25: Publicado | G25: 22.11.003 | H25: Servicio gestión flota vehicular SSO | I25: "Se requiere contar con sistema de control satelital (GPS) para la flota de vehículos motorizados (ambulancias, minibuses, camionetas, entre otros) correspondiente a los establecimientos de la Red del Servicio de Salud Osorno (Hospitales y Base SAMU), con la finalidad de realizar un adecuado control y gestión de flota, aumentando la eficiencia en la operación." | J25: 2 | K25: Control Flota | L25: 1 | M25: 1 | N25: 20136000 | O25: 559333 | P25: 36 | Q25: 01-01-2024,01-02-2024,01-03-2024,01-04-2024,01-05-2024,01-06-2024,01-07-2024,01-08-2024,01-09-2024,01-10-2024,01-11-2024,01-12-2024,01-01-2025,01-02-2025,01-03-2025,01-04-2025,01-05-2025,01-06-2025,01-07-2025,01-08-2025,01-09-2025,01-10-2025,01-11-2025,01-12-2025,01-01-2026,01-02-2026,01-03-2026,01-04-2026,01-05-2026,01-06-2026,01-07-2026,01-08-2026,01-09-2026,01-10-2026,01-11-2026,01-12-2026 | R25: Bruno Ojeda Alvarez | S25: Jefe Depto. | T25: 64-2335840- | U25: bruno.ojeda@redsalud.gov.cl | V25: 45200 | W25: 45478 | X25: 1 | Y25: 1057532-1544-SE24 | Z25: 1 | AA25: 559333 | AB25: 46357 | AC25: Arrastre | AD25: =VLOOKUP(D25,Oficial!A:C,3,0) -> Arrastre
A26: SERVICIO DE SALUD OSORNO | B26: 1057532-1-PC24 | C26: Bienes y Servicios | D26: 1057532-1-PC24 | E26: Proyecto operacional | F26: Publicado | G26: 22.11.003 | H26: Sistema control de flota vehicular del Servicio de Salud Osorno | I26: Tiene como finalidad realizar un adecuado control y gestión de flota de vehículos, aumentando la eficiencia en lo operacional, como también disminuyendo el riesgo de accidentes de tránsito. | J26: 1 | K26: Sistema de control de flota | L26: 1 | M26: 1 | N26: 20136000 | O26: 559345 | P26: 36 | Q26: 01-01-2024,01-02-2024,01-03-2024,01-04-2024,01-05-2024,01-06-2024,01-07-2024,01-08-2024,01-09-2024,01-10-2024,01-11-2024,01-12-2024,01-01-2025,01-02-2025,01-03-2025,01-04-2025,01-05-2025,01-06-2025,01-07-2025,01-08-2025,01-09-2025,01-10-2025,01-11-2025,01-12-2025,01-01-2026,01-02-2026,01-03-2026,01-04-2026,01-05-2026,01-06-2026,01-07-2026,01-08-2026,01-09-2026,01-10-2026,01-11-2026,01-12-2026 | R26: Felipe Salvo Barriga | S26: Enc. Sección Mant. de Vehículos | T26: 64-2565654- | U26: felipe.salvob@redsalud.gob.cl | V26: 45292 | W26: 45478 | X26: 0 | Z26: 1 | AA26: 559345 | AB26: 46357 | AC26: Arrastre | AD26: =VLOOKUP(D26,Oficial!A:C,3,0) -> Arrastre
A27: SERVICIO DE SALUD OSORNO | B27: 1057532-1-PC24 | C27: Bienes y Servicios | D27: 1057532-1-PC24 | E27: Proyecto operacional | F27: Publicado | G27: 22.11.003 | H27: Sistema control de flota vehicular del Servicio de Salud Osorno | I27: Tiene como finalidad realizar un adecuado control y gestión de flota de vehículos, aumentando la eficiencia en lo operacional, como también disminuyendo el riesgo de accidentes de tránsito. | J27: 1 | K27: Sistema de control de flota | L27: 1 | M27: 1 | N27: 20136000 | O27: 559333 | P27: 36 | Q27: 01-01-2024,01-02-2024,01-03-2024,01-04-2024,01-05-2024,01-06-2024,01-07-2024,01-08-2024,01-09-2024,01-10-2024,01-11-2024,01-12-2024,01-01-2025,01-02-2025,01-03-2025,01-04-2025,01-05-2025,01-06-2025,01-07-2025,01-08-2025,01-09-2025,01-10-2025,01-11-2025,01-12-2025,01-01-2026,01-02-2026,01-03-2026,01-04-2026,01-05-2026,01-06-2026,01-07-2026,01-08-2026,01-09-2026,01-10-2026,01-11-2026,01-12-2026 | R27: Felipe Salvo Barriga | S27: Enc. Sección Mant. de Vehículos | T27: 64-2565654- | U27: felipe.salvob@redsalud.gob.cl | V27: 45292 | W27: 45478 | X27: 0 | Z27: 1 | AA27: 559333 | AB27: 46143 | AC27: Arrastre | AD27: =VLOOKUP(D27,Oficial!A:C,3,0) -> Arrastre
A28: SERVICIO DE SALUD OSORNO | B28: 1057532-1-PC24 | C28: Bienes y Servicios | D28: 1057532-1-PC24 | E28: Proyecto operacional | F28: Publicado | G28: 22.11.003 | H28: Sistema control de flota vehicular del Servicio de Salud Osorno | I28: Tiene como finalidad realizar un adecuado control y gestión de flota de vehículos, aumentando la eficiencia en lo operacional, como también disminuyendo el riesgo de accidentes de tránsito. | J28: 1 | K28: Sistema de control de flota | L28: 1 | M28: 1 | N28: 20136000 | O28: 559333 | P28: 36 | Q28: 01-01-2024,01-02-2024,01-03-2024,01-04-2024,01-05-2024,01-06-2024,01-07-2024,01-08-2024,01-09-2024,01-10-2024,01-11-2024,01-12-2024,01-01-2025,01-02-2025,01-03-2025,01-04-2025,01-05-2025,01-06-2025,01-07-2025,01-08-2025,01-09-2025,01-10-2025,01-11-2025,01-12-2025,01-01-2026,01-02-2026,01-03-2026,01-04-2026,01-05-2026,01-06-2026,01-07-2026,01-08-2026,01-09-2026,01-10-2026,01-11-2026,01-12-2026 | R28: Felipe Salvo Barriga | S28: Enc. Sección Mant. de Vehículos | T28: 64-2565654- | U28: felipe.salvob@redsalud.gob.cl | V28: 45292 | W28: 45478 | X28: 0 | Z28: 1 | AA28: 559333 | AB28: 46082 | AC28: Arrastre | AD28: =VLOOKUP(D28,Oficial!A:C,3,0) -> Arrastre
A29: SERVICIO DE SALUD OSORNO | B29: 1057532-1-PC24 | C29: Bienes y Servicios | D29: 1057532-1-PC24 | E29: Proyecto operacional | F29: Publicado | G29: 22.11.003 | H29: Sistema control de flota vehicular del Servicio de Salud Osorno | I29: Tiene como finalidad realizar un adecuado control y gestión de flota de vehículos, aumentando la eficiencia en lo operacional, como también disminuyendo el riesgo de accidentes de tránsito. | J29: 1 | K29: Sistema de control de flota | L29: 1 | M29: 1 | N29: 20136000 | O29: 559333 | P29: 36 | Q29: 01-01-2024,01-02-2024,01-03-2024,01-04-2024,01-05-2024,01-06-2024,01-07-2024,01-08-2024,01-09-2024,01-10-2024,01-11-2024,01-12-2024,01-01-2025,01-02-2025,01-03-2025,01-04-2025,01-05-2025,01-06-2025,01-07-2025,01-08-2025,01-09-2025,01-10-2025,01-11-2025,01-12-2025,01-01-2026,01-02-2026,01-03-2026,01-04-2026,01-05-2026,01-06-2026,01-07-2026,01-08-2026,01-09-2026,01-10-2026,01-11-2026,01-12-2026 | R29: Felipe Salvo Barriga | S29: Enc. Sección Mant. de Vehículos | T29: 64-2565654- | U29: felipe.salvob@redsalud.gob.cl | V29: 45292 | W29: 45478 | X29: 0 | Z29: 1 | AA29: 559333 | AB29: 46054 | AC29: Arrastre | AD29: =VLOOKUP(D29,Oficial!A:C,3,0) -> Arrastre
A30: SERVICIO DE SALUD OSORNO | B30: 1057532-1-PC24 | C30: Bienes y Servicios | D30: 1057532-1-PC24 | E30: Proyecto operacional | F30: Publicado | G30: 22.11.003 | H30: Sistema control de flota vehicular del Servicio de Salud Osorno | I30: Tiene como finalidad realizar un adecuado control y gestión de flota de vehículos, aumentando la eficiencia en lo operacional, como también disminuyendo el riesgo de accidentes de tránsito. | J30: 1 | K30: Sistema de control de flota | L30: 1 | M30: 1 | N30: 20136000 | O30: 559333 | P30: 36 | Q30: 01-01-2024,01-02-2024,01-03-2024,01-04-2024,01-05-2024,01-06-2024,01-07-2024,01-08-2024,01-09-2024,01-10-2024,01-11-2024,01-12-2024,01-01-2025,01-02-2025,01-03-2025,01-04-2025,01-05-2025,01-06-2025,01-07-2025,01-08-2025,01-09-2025,01-10-2025,01-11-2025,01-12-2025,01-01-2026,01-02-2026,01-03-2026,01-04-2026,01-05-2026,01-06-2026,01-07-2026,01-08-2026,01-09-2026,01-10-2026,01-11-2026,01-12-2026 | R30: Felipe Salvo Barriga | S30: Enc. Sección Mant. de Vehículos | T30: 64-2565654- | U30: felipe.salvob@redsalud.gob.cl | V30: 45292 | W30: 45478 | X30: 0 | Z30: 1 | AA30: 559333 | AB30: 46174 | AC30: Arrastre | AD30: =VLOOKUP(D30,Oficial!A:C,3,0) -> Arrastre
A31: SERVICIO DE SALUD OSORNO | B31: 1057532-1-PC24 | C31: Bienes y Servicios | D31: 1057532-1-PC24 | E31: Proyecto operacional | F31: Publicado | G31: 22.11.003 | H31: Sistema control de flota vehicular del Servicio de Salud Osorno | I31: Tiene como finalidad realizar un adecuado control y gestión de flota de vehículos, aumentando la eficiencia en lo operacional, como también disminuyendo el riesgo de accidentes de tránsito. | J31: 1 | K31: Sistema de control de flota | L31: 1 | M31: 1 | N31: 20136000 | O31: 559333 | P31: 36 | Q31: 01-01-2024,01-02-2024,01-03-2024,01-04-2024,01-05-2024,01-06-2024,01-07-2024,01-08-2024,01-09-2024,01-10-2024,01-11-2024,01-12-2024,01-01-2025,01-02-2025,01-03-2025,01-04-2025,01-05-2025,01-06-2025,01-07-2025,01-08-2025,01-09-2025,01-10-2025,01-11-2025,01-12-2025,01-01-2026,01-02-2026,01-03-2026,01-04-2026,01-05-2026,01-06-2026,01-07-2026,01-08-2026,01-09-2026,01-10-2026,01-11-2026,01-12-2026 | R31: Felipe Salvo Barriga | S31: Enc. Sección Mant. de Vehículos | T31: 64-2565654- | U31: felipe.salvob@redsalud.gob.cl | V31: 45292 | W31: 45478 | X31: 0 | Z31: 1 | AA31: 559333 | AB31: 46023 | AC31: Arrastre | AD31: =VLOOKUP(D31,Oficial!A:C,3,0) -> Arrastre
A32: SERVICIO DE SALUD OSORNO | B32: 1057532-1-PC24 | C32: Bienes y Servicios | D32: 1057532-1-PC24 | E32: Proyecto operacional | F32: Publicado | G32: 22.11.003 | H32: Sistema control de flota vehicular del Servicio de Salud Osorno | I32: Tiene como finalidad realizar un adecuado control y gestión de flota de vehículos, aumentando la eficiencia en lo operacional, como también disminuyendo el riesgo de accidentes de tránsito. | J32: 1 | K32: Sistema de control de flota | L32: 1 | M32: 1 | N32: 20136000 | O32: 559333 | P32: 36 | Q32: 01-01-2024,01-02-2024,01-03-2024,01-04-2024,01-05-2024,01-06-2024,01-07-2024,01-08-2024,01-09-2024,01-10-2024,01-11-2024,01-12-2024,01-01-2025,01-02-2025,01-03-2025,01-04-2025,01-05-2025,01-06-2025,01-07-2025,01-08-2025,01-09-2025,01-10-2025,01-11-2025,01-12-2025,01-01-2026,01-02-2026,01-03-2026,01-04-2026,01-05-2026,01-06-2026,01-07-2026,01-08-2026,01-09-2026,01-10-2026,01-11-2026,01-12-2026 | R32: Felipe Salvo Barriga | S32: Enc. Sección Mant. de Vehículos | T32: 64-2565654- | U32: felipe.salvob@redsalud.gob.cl | V32: 45292 | W32: 45478 | X32: 0 | Z32: 1 | AA32: 559333 | AB32: 46204 | AC32: Arrastre | AD32: =VLOOKUP(D32,Oficial!A:C,3,0) -> Arrastre
A33: SERVICIO DE SALUD OSORNO | B33: 1057532-1-PC24 | C33: Bienes y Servicios | D33: 1057532-1-PC24 | E33: Proyecto operacional | F33: Publicado | G33: 22.11.003 | H33: Sistema control de flota vehicular del Servicio de Salud Osorno | I33: Tiene como finalidad realizar un adecuado control y gestión de flota de vehículos, aumentando la eficiencia en lo operacional, como también disminuyendo el riesgo de accidentes de tránsito. | J33: 1 | K33: Sistema de control de flota | L33: 1 | M33: 1 | N33: 20136000 | O33: 559333 | P33: 36 | Q33: 01-01-2024,01-02-2024,01-03-2024,01-04-2024,01-05-2024,01-06-2024,01-07-2024,01-08-2024,01-09-2024,01-10-2024,01-11-2024,01-12-2024,01-01-2025,01-02-2025,01-03-2025,01-04-2025,01-05-2025,01-06-2025,01-07-2025,01-08-2025,01-09-2025,01-10-2025,01-11-2025,01-12-2025,01-01-2026,01-02-2026,01-03-2026,01-04-2026,01-05-2026,01-06-2026,01-07-2026,01-08-2026,01-09-2026,01-10-2026,01-11-2026,01-12-2026 | R33: Felipe Salvo Barriga | S33: Enc. Sección Mant. de Vehículos | T33: 64-2565654- | U33: felipe.salvob@redsalud.gob.cl | V33: 45292 | W33: 45478 | X33: 0 | Z33: 1 | AA33: 559333 | AB33: 46113 | AC33: Arrastre | AD33: =VLOOKUP(D33,Oficial!A:C,3,0) -> Arrastre
A34: SERVICIO DE SALUD OSORNO | B34: 1057532-1-PC24 | C34: Bienes y Servicios | D34: 1057532-1-PC24 | E34: Proyecto operacional | F34: Publicado | G34: 22.11.003 | H34: Sistema control de flota vehicular del Servicio de Salud Osorno | I34: Tiene como finalidad realizar un adecuado control y gestión de flota de vehículos, aumentando la eficiencia en lo operacional, como también disminuyendo el riesgo de accidentes de tránsito. | J34: 1 | K34: Sistema de control de flota | L34: 1 | M34: 1 | N34: 20136000 | O34: 559333 | P34: 36 | Q34: 01-01-2024,01-02-2024,01-03-2024,01-04-2024,01-05-2024,01-06-2024,01-07-2024,01-08-2024,01-09-2024,01-10-2024,01-11-2024,01-12-2024,01-01-2025,01-02-2025,01-03-2025,01-04-2025,01-05-2025,01-06-2025,01-07-2025,01-08-2025,01-09-2025,01-10-2025,01-11-2025,01-12-2025,01-01-2026,01-02-2026,01-03-2026,01-04-2026,01-05-2026,01-06-2026,01-07-2026,01-08-2026,01-09-2026,01-10-2026,01-11-2026,01-12-2026 | R34: Felipe Salvo Barriga | S34: Enc. Sección Mant. de Vehículos | T34: 64-2565654- | U34: felipe.salvob@redsalud.gob.cl | V34: 45292 | W34: 45478 | X34: 0 | Z34: 1 | AA34: 559333 | AB34: 46235 | AC34: Arrastre | AD34: =VLOOKUP(D34,Oficial!A:C,3,0) -> Arrastre
A35: SERVICIO DE SALUD OSORNO | B35: 1057532-1-PC24 | C35: Bienes y Servicios | D35: 1057532-1-PC24 | E35: Proyecto operacional | F35: Publicado | G35: 22.11.003 | H35: Sistema control de flota vehicular del Servicio de Salud Osorno | I35: Tiene como finalidad realizar un adecuado control y gestión de flota de vehículos, aumentando la eficiencia en lo operacional, como también disminuyendo el riesgo de accidentes de tránsito. | J35: 1 | K35: Sistema de control de flota | L35: 1 | M35: 1 | N35: 20136000 | O35: 559333 | P35: 36 | Q35: 01-01-2024,01-02-2024,01-03-2024,01-04-2024,01-05-2024,01-06-2024,01-07-2024,01-08-2024,01-09-2024,01-10-2024,01-11-2024,01-12-2024,01-01-2025,01-02-2025,01-03-2025,01-04-2025,01-05-2025,01-06-2025,01-07-2025,01-08-2025,01-09-2025,01-10-2025,01-11-2025,01-12-2025,01-01-2026,01-02-2026,01-03-2026,01-04-2026,01-05-2026,01-06-2026,01-07-2026,01-08-2026,01-09-2026,01-10-2026,01-11-2026,01-12-2026 | R35: Felipe Salvo Barriga | S35: Enc. Sección Mant. de Vehículos | T35: 64-2565654- | U35: felipe.salvob@redsalud.gob.cl | V35: 45292 | W35: 45478 | X35: 0 | Z35: 1 | AA35: 559333 | AB35: 46296 | AC35: Arrastre | AD35: =VLOOKUP(D35,Oficial!A:C,3,0) -> Arrastre
A36: SERVICIO DE SALUD OSORNO | B36: 1057532-1-PC24 | C36: Bienes y Servicios | D36: 1057532-1-PC24 | E36: Proyecto operacional | F36: Publicado | G36: 22.11.003 | H36: Sistema control de flota vehicular del Servicio de Salud Osorno | I36: Tiene como finalidad realizar un adecuado control y gestión de flota de vehículos, aumentando la eficiencia en lo operacional, como también disminuyendo el riesgo de accidentes de tránsito. | J36: 1 | K36: Sistema de control de flota | L36: 1 | M36: 1 | N36: 20136000 | O36: 559333 | P36: 36 | Q36: 01-01-2024,01-02-2024,01-03-2024,01-04-2024,01-05-2024,01-06-2024,01-07-2024,01-08-2024,01-09-2024,01-10-2024,01-11-2024,01-12-2024,01-01-2025,01-02-2025,01-03-2025,01-04-2025,01-05-2025,01-06-2025,01-07-2025,01-08-2025,01-09-2025,01-10-2025,01-11-2025,01-12-2025,01-01-2026,01-02-2026,01-03-2026,01-04-2026,01-05-2026,01-06-2026,01-07-2026,01-08-2026,01-09-2026,01-10-2026,01-11-2026,01-12-2026 | R36: Felipe Salvo Barriga | S36: Enc. Sección Mant. de Vehículos | T36: 64-2565654- | U36: felipe.salvob@redsalud.gob.cl | V36: 45292 | W36: 45478 | X36: 0 | Z36: 1 | AA36: 559333 | AB36: 46266 | AC36: Arrastre | AD36: =VLOOKUP(D36,Oficial!A:C,3,0) -> Arrastre
A37: SERVICIO DE SALUD OSORNO | B37: 1057532-1-PC24 | C37: Bienes y Servicios | D37: 1057532-1-PC24 | E37: Proyecto operacional | F37: Publicado | G37: 22.11.003 | H37: Sistema control de flota vehicular del Servicio de Salud Osorno | I37: Tiene como finalidad realizar un adecuado control y gestión de flota de vehículos, aumentando la eficiencia en lo operacional, como también disminuyendo el riesgo de accidentes de tránsito. | J37: 1 | K37: Sistema de control de flota | L37: 1 | M37: 1 | N37: 20136000 | O37: 559333 | P37: 36 | Q37: 01-01-2024,01-02-2024,01-03-2024,01-04-2024,01-05-2024,01-06-2024,01-07-2024,01-08-2024,01-09-2024,01-10-2024,01-11-2024,01-12-2024,01-01-2025,01-02-2025,01-03-2025,01-04-2025,01-05-2025,01-06-2025,01-07-2025,01-08-2025,01-09-2025,01-10-2025,01-11-2025,01-12-2025,01-01-2026,01-02-2026,01-03-2026,01-04-2026,01-05-2026,01-06-2026,01-07-2026,01-08-2026,01-09-2026,01-10-2026,01-11-2026,01-12-2026 | R37: Felipe Salvo Barriga | S37: Enc. Sección Mant. de Vehículos | T37: 64-2565654- | U37: felipe.salvob@redsalud.gob.cl | V37: 45292 | W37: 45478 | X37: 0 | Z37: 1 | AA37: 559333 | AB37: 46327 | AC37: Arrastre | AD37: =VLOOKUP(D37,Oficial!A:C,3,0) -> Arrastre
... A49: SERVICIO DE SALUD OSORNO | B49: 1057532-30-PC24 | C49: Bienes y Servicios | D49: 1057532-30-PC24 | E49: Proyecto estratégico | F49: Publicado | G49: 22.11.003 | H49: SISTEMAS DE COMUNICACIONES LTE WAVE PTX SERVICIO DE SALUD OSORNO | I49: SERVICIO DE SUSCRIPCION WAVE PTX, INCLUYE INTERPERABILIDAD CON SISTEMA VHF, GATEWAY, INSTALACION, LICENCIAS, GPS EN LOS EQUIPOS WAVE PTX. | J49: 1 | K49: Servicio | L49: 1 | M49: 1 | N49: 130000000 | O49: 3611111 | P49: 36 | Q49: 01-06-2024,01-07-2024,01-08-2024,01-09-2024,01-10-2024,01-11-2024,01-12-2024,01-01-2025,01-02-2025,01-03-2025,01-04-2025,01-05-2025,01-06-2025,01-07-2025,01-08-2025,01-09-2025,01-10-2025,01-11-2025,01-12-2025,01-01-2026,01-02-2026,01-03-2026,01-04-2026,01-05-2026,01-06-2026,01-07-2026,01-08-2026,01-09-2026,01-10-2026,01-11-2026,01-12-2026,01-01-2027,01-02-2027,01-03-2027,01-04-2027,01-05-2024 | R49: CATALINA VERA | S49: COORDINADORA EMERGENCIA | T49: 64-337728- | U49: CATALINA.VERAC@REDSALUD.GOB.CL | V49: 45413 | W49: 45478 | X49: 0 | Z49: 1 | AA49: 3611111 | AB49: 46296 | AC49: Arrastre | AD49: =VLOOKUP(D49,Oficial!A:C,3,0) -> Arrastre
A50: SERVICIO DE SALUD OSORNO | B50: 1057532-308-PC24 | C50: Bienes y Servicios | D50: 1057532-308-PC24 | E50: Proyecto operacional | F50: Publicado | G50: 22.12.999.022 | H50: Convenio - 3 cupos Residencia Protegida para el Servicio de Salud Osorno en la Región Metropolitana | I50: 3 cupos Residencia Protegida por 24 meses, en la Región Metropolitana, por un total de 2190 días de residencia protegida. | J50: 1 | K50: Residencia | L50: 1 | M50: 1 | N50: 80865750 | O50: 3369406 | P50: 24 | Q50: 01-01-2025,01-02-2025,01-03-2025,01-04-2025,01-05-2025,01-06-2025,01-07-2025,01-08-2025,01-09-2025,01-10-2025,01-11-2025,01-12-2025,01-01-2026,01-02-2026,01-03-2026,01-04-2026,01-05-2026,01-06-2026,01-07-2026,01-08-2026,01-09-2026,01-10-2026,01-11-2026,01-12-2026 | R50: Antonia Caifil | S50: Jefa Subdepto. Gestión Clinica y Adm. | T50: 64-335813- | U50: antonia.caifil@redsalud.gob.cl | V50: 45474 | W50: 45478 | X50: 12 | Y50: 1057532-1987-SE24 | Z50: 1 | AA50: 3369406 | AB50: 46054 | AC50: Arrastre | AD50: =VLOOKUP(D50,Oficial!A:C,3,0) -> Arrastre
A51: SERVICIO DE SALUD OSORNO | B51: 1057532-308-PC24 | C51: Bienes y Servicios | D51: 1057532-308-PC24 | E51: Proyecto operacional | F51: Publicado | G51: 22.12.999.022 | H51: Convenio - 3 cupos Residencia Protegida para el Servicio de Salud Osorno en la Región Metropolitana | I51: 3 cupos Residencia Protegida por 24 meses, en la Región Metropolitana, por un total de 2190 días de residencia protegida. | J51: 1 | K51: Residencia | L51: 1 | M51: 1 | N51: 80865750 | O51: 3369406 | P51: 24 | Q51: 01-01-2025,01-02-2025,01-03-2025,01-04-2025,01-05-2025,01-06-2025,01-07-2025,01-08-2025,01-09-2025,01-10-2025,01-11-2025,01-12-2025,01-01-2026,01-02-2026,01-03-2026,01-04-2026,01-05-2026,01-06-2026,01-07-2026,01-08-2026,01-09-2026,01-10-2026,01-11-2026,01-12-2026 | R51: Antonia Caifil | S51: Jefa Subdepto. Gestión Clinica y Adm. | T51: 64-335813- | U51: antonia.caifil@redsalud.gob.cl | V51: 45474 | W51: 45478 | X51: 12 | Y51: 1057532-1299-SE24 | Z51: 1 | AA51: 3369406 | AB51: 46082 | AC51: Arrastre | AD51: =VLOOKUP(D51,Oficial!A:C,3,0) -> Arrastre
A52: SERVICIO DE SALUD OSORNO | B52: 1057532-308-PC24 | C52: Bienes y Servicios | D52: 1057532-308-PC24 | E52: Proyecto operacional | F52: Publicado | G52: 22.12.999.022 | H52: Convenio - 3 cupos Residencia Protegida para el Servicio de Salud Osorno en la Región Metropolitana | I52: 3 cupos Residencia Protegida por 24 meses, en la Región Metropolitana, por un total de 2190 días de residencia protegida. | J52: 1 | K52: Residencia | L52: 1 | M52: 1 | N52: 80865750 | O52: 3369406 | P52: 24 | Q52: 01-01-2025,01-02-2025,01-03-2025,01-04-2025,01-05-2025,01-06-2025,01-07-2025,01-08-2025,01-09-2025,01-10-2025,01-11-2025,01-12-2025,01-01-2026,01-02-2026,01-03-2026,01-04-2026,01-05-2026,01-06-2026,01-07-2026,01-08-2026,01-09-2026,01-10-2026,01-11-2026,01-12-2026 | R52: Antonia Caifil | S52: Jefa Subdepto. Gestión Clinica y Adm. | T52: 64-335813- | U52: antonia.caifil@redsalud.gob.cl | V52: 45474 | W52: 45478 | X52: 12 | Y52: 1057532-1987-SE24 | Z52: 1 | AA52: 3369406 | AB52: 46204 | AC52: Arrastre | AD52: =VLOOKUP(D52,Oficial!A:C,3,0) -> Arrastre
A53: SERVICIO DE SALUD OSORNO | B53: 1057532-308-PC24 | C53: Bienes y Servicios | D53: 1057532-308-PC24 | E53: Proyecto operacional | F53: Publicado | G53: 22.12.999.022 | H53: Convenio - 3 cupos Residencia Protegida para el Servicio de Salud Osorno en la Región Metropolitana | I53: 3 cupos Residencia Protegida por 24 meses, en la Región Metropolitana, por un total de 2190 días de residencia protegida. | J53: 1 | K53: Residencia | L53: 1 | M53: 1 | N53: 80865750 | O53: 3369406 | P53: 24 | Q53: 01-01-2025,01-02-2025,01-03-2025,01-04-2025,01-05-2025,01-06-2025,01-07-2025,01-08-2025,01-09-2025,01-10-2025,01-11-2025,01-12-2025,01-01-2026,01-02-2026,01-03-2026,01-04-2026,01-05-2026,01-06-2026,01-07-2026,01-08-2026,01-09-2026,01-10-2026,01-11-2026,01-12-2026 | R53: Antonia Caifil | S53: Jefa Subdepto. Gestión Clinica y Adm. | T53: 64-335813- | U53: antonia.caifil@redsalud.gob.cl | V53: 45474 | W53: 45478 | X53: 12 | Y53: 1057532-1299-SE24 | Z53: 1 | AA53: 3369406 | AB53: 46174 | AC53: Arrastre | AD53: =VLOOKUP(D53,Oficial!A:C,3,0) -> Arrastre
A54: SERVICIO DE SALUD OSORNO | B54: 1057532-308-PC24 | C54: Bienes y Servicios | D54: 1057532-308-PC24 | E54: Proyecto operacional | F54: Publicado | G54: 22.12.999.022 | H54: Convenio - 3 cupos Residencia Protegida para el Servicio de Salud Osorno en la Región Metropolitana | I54: 3 cupos Residencia Protegida por 24 meses, en la Región Metropolitana, por un total de 2190 días de residencia protegida. | J54: 1 | K54: Residencia | L54: 1 | M54: 1 | N54: 80865750 | O54: 3369406 | P54: 24 | Q54: 01-01-2025,01-02-2025,01-03-2025,01-04-2025,01-05-2025,01-06-2025,01-07-2025,01-08-2025,01-09-2025,01-10-2025,01-11-2025,01-12-2025,01-01-2026,01-02-2026,01-03-2026,01-04-2026,01-05-2026,01-06-2026,01-07-2026,01-08-2026,01-09-2026,01-10-2026,01-11-2026,01-12-2026 | R54: Antonia Caifil | S54: Jefa Subdepto. Gestión Clinica y Adm. | T54: 64-335813- | U54: antonia.caifil@redsalud.gob.cl | V54: 45474 | W54: 45478 | X54: 12 | Y54: 1057532-1831-SE24 | Z54: 1 | AA54: 3369406 | AB54: 46174 | AC54: Arrastre | AD54: =VLOOKUP(D54,Oficial!A:C,3,0) -> Arrastre
A55: SERVICIO DE SALUD OSORNO | B55: 1057532-308-PC24 | C55: Bienes y Servicios | D55: 1057532-308-PC24 | E55: Proyecto operacional | F55: Publicado | G55: 22.12.999.022 | H55: Convenio - 3 cupos Residencia Protegida para el Servicio de Salud Osorno en la Región Metropolitana | I55: 3 cupos Residencia Protegida por 24 meses, en la Región Metropolitana, por un total de 2190 días de residencia protegida. | J55: 1 | K55: Residencia | L55: 1 | M55: 1 | N55: 80865750 | O55: 3369406 | P55: 24 | Q55: 01-01-2025,01-02-2025,01-03-2025,01-04-2025,01-05-2025,01-06-2025,01-07-2025,01-08-2025,01-09-2025,01-10-2025,01-11-2025,01-12-2025,01-01-2026,01-02-2026,01-03-2026,01-04-2026,01-05-2026,01-06-2026,01-07-2026,01-08-2026,01-09-2026,01-10-2026,01-11-2026,01-12-2026 | R55: Antonia Caifil | S55: Jefa Subdepto. Gestión Clinica y Adm. | T55: 64-335813- | U55: antonia.caifil@redsalud.gob.cl | V55: 45474 | W55: 45478 | X55: 12 | Y55: 1057532-1987-SE24 | Z55: 1 | AA55: 3369406 | AB55: 46327 | AC55: Arrastre | AD55: =VLOOKUP(D55,Oficial!A:C,3,0) -> Arrastre
A56: SERVICIO DE SALUD OSORNO | B56: 1057532-308-PC24 | C56: Bienes y Servicios | D56: 1057532-308-PC24 | E56: Proyecto operacional | F56: Publicado | G56: 22.12.999.022 | H56: Convenio - 3 cupos Residencia Protegida para el Servicio de Salud Osorno en la Región Metropolitana | I56: 3 cupos Residencia Protegida por 24 meses, en la Región Metropolitana, por un total de 2190 días de residencia protegida. | J56: 1 | K56: Residencia | L56: 1 | M56: 1 | N56: 80865750 | O56: 3369406 | P56: 24 | Q56: 01-01-2025,01-02-2025,01-03-2025,01-04-2025,01-05-2025,01-06-2025,01-07-2025,01-08-2025,01-09-2025,01-10-2025,01-11-2025,01-12-2025,01-01-2026,01-02-2026,01-03-2026,01-04-2026,01-05-2026,01-06-2026,01-07-2026,01-08-2026,01-09-2026,01-10-2026,01-11-2026,01-12-2026 | R56: Antonia Caifil | S56: Jefa Subdepto. Gestión Clinica y Adm. | T56: 64-335813- | U56: antonia.caifil@redsalud.gob.cl | V56: 45474 | W56: 45478 | X56: 12 | Y56: 1057532-1831-SE24 | Z56: 1 | AA56: 3369406 | AB56: 46204 | AC56: Arrastre | AD56: =VLOOKUP(D56,Oficial!A:C,3,0) -> Arrastre
A57: SERVICIO DE SALUD OSORNO | B57: 1057532-308-PC24 | C57: Bienes y Servicios | D57: 1057532-308-PC24 | E57: Proyecto operacional | F57: Publicado | G57: 22.12.999.022 | H57: Convenio - 3 cupos Residencia Protegida para el Servicio de Salud Osorno en la Región Metropolitana | I57: 3 cupos Residencia Protegida por 24 meses, en la Región Metropolitana, por un total de 2190 días de residencia protegida. | J57: 1 | K57: Residencia | L57: 1 | M57: 1 | N57: 80865750 | O57: 3369406 | P57: 24 | Q57: 01-01-2025,01-02-2025,01-03-2025,01-04-2025,01-05-2025,01-06-2025,01-07-2025,01-08-2025,01-09-2025,01-10-2025,01-11-2025,01-12-2025,01-01-2026,01-02-2026,01-03-2026,01-04-2026,01-05-2026,01-06-2026,01-07-2026,01-08-2026,01-09-2026,01-10-2026,01-11-2026,01-12-2026 | R57: Antonia Caifil | S57: Jefa Subdepto. Gestión Clinica y Adm. | T57: 64-335813- | U57: antonia.caifil@redsalud.gob.cl | V57: 45474 | W57: 45478 | X57: 12 | Y57: 1057532-4506-SE25 | Z57: 1 | AA57: 3369406 | AB57: 46054 | AC57: Arrastre | AD57: =VLOOKUP(D57,Oficial!A:C,3,0) -> Arrastre
A58: SERVICIO DE SALUD OSORNO | B58: 1057532-308-PC24 | C58: Bienes y Servicios | D58: 1057532-308-PC24 | E58: Proyecto operacional | F58: Publicado | G58: 22.12.999.022 | H58: Convenio - 3 cupos Residencia Protegida para el Servicio de Salud Osorno en la Región Metropolitana | I58: 3 cupos Residencia Protegida por 24 meses, en la Región Metropolitana, por un total de 2190 días de residencia protegida. | J58: 1 | K58: Residencia | L58: 1 | M58: 1 | N58: 80865750 | O58: 3369406 | P58: 24 | Q58: 01-01-2025,01-02-2025,01-03-2025,01-04-2025,01-05-2025,01-06-2025,01-07-2025,01-08-2025,01-09-2025,01-10-2025,01-11-2025,01-12-2025,01-01-2026,01-02-2026,01-03-2026,01-04-2026,01-05-2026,01-06-2026,01-07-2026,01-08-2026,01-09-2026,01-10-2026,01-11-2026,01-12-2026 | R58: Antonia Caifil | S58: Jefa Subdepto. Gestión Clinica y Adm. | T58: 64-335813- | U58: antonia.caifil@redsalud.gob.cl | V58: 45474 | W58: 45478 | X58: 12 | Y58: 1057532-1299-SE24 | Z58: 1 | AA58: 3369406 | AB58: 46054 | AC58: Arrastre | AD58: =VLOOKUP(D58,Oficial!A:C,3,0) -> Arrastre
A59: SERVICIO DE SALUD OSORNO | B59: 1057532-308-PC24 | C59: Bienes y Servicios | D59: 1057532-308-PC24 | E59: Proyecto operacional | F59: Publicado | G59: 22.12.999.022 | H59: Convenio - 3 cupos Residencia Protegida para el Servicio de Salud Osorno en la Región Metropolitana | I59: 3 cupos Residencia Protegida por 24 meses, en la Región Metropolitana, por un total de 2190 días de residencia protegida. | J59: 1 | K59: Residencia | L59: 1 | M59: 1 | N59: 80865750 | O59: 3369408 | P59: 24 | Q59: 01-01-2025,01-02-2025,01-03-2025,01-04-2025,01-05-2025,01-06-2025,01-07-2025,01-08-2025,01-09-2025,01-10-2025,01-11-2025,01-12-2025,01-01-2026,01-02-2026,01-03-2026,01-04-2026,01-05-2026,01-06-2026,01-07-2026,01-08-2026,01-09-2026,01-10-2026,01-11-2026,01-12-2026 | R59: Antonia Caifil | S59: Jefa Subdepto. Gestión Clinica y Adm. | T59: 64-335813- | U59: antonia.caifil@redsalud.gob.cl | V59: 45474 | W59: 45478 | X59: 12 | Y59: 1057532-1831-SE24 | Z59: 1 | AA59: 3369406 | AB59: 46235 | AC59: Arrastre | AD59: =VLOOKUP(D59,Oficial!A:C,3,0) -> Arrastre
A60: SERVICIO DE SALUD OSORNO | B60: 1057532-308-PC24 | C60: Bienes y Servicios | D60: 1057532-308-PC24 | E60: Proyecto operacional | F60: Publicado | G60: 22.12.999.022 | H60: Convenio - 3 cupos Residencia Protegida para el Servicio de Salud Osorno en la Región Metropolitana | I60: 3 cupos Residencia Protegida por 24 meses, en la Región Metropolitana, por un total de 2190 días de residencia protegida. | J60: 1 | K60: Residencia | L60: 1 | M60: 1 | N60: 80865750 | O60: 3369408 | P60: 24 | Q60: 01-01-2025,01-02-2025,01-03-2025,01-04-2025,01-05-2025,01-06-2025,01-07-2025,01-08-2025,01-09-2025,01-10-2025,01-11-2025,01-12-2025,01-01-2026,01-02-2026,01-03-2026,01-04-2026,01-05-2026,01-06-2026,01-07-2026,01-08-2026,01-09-2026,01-10-2026,01-11-2026,01-12-2026 | R60: Antonia Caifil | S60: Jefa Subdepto. Gestión Clinica y Adm. | T60: 64-335813- | U60: antonia.caifil@redsalud.gob.cl | V60: 45474 | W60: 45478 | X60: 12 | Y60: 1057532-1299-SE24 | Z60: 1 | AA60: 3369406 | AB60: 46327 | AC60: Arrastre | AD60: =VLOOKUP(D60,Oficial!A:C,3,0) -> Arrastre
A61: SERVICIO DE SALUD OSORNO | B61: 1057532-308-PC24 | C61: Bienes y Servicios | D61: 1057532-308-PC24 | E61: Proyecto operacional | F61: Publicado | G61: 22.12.999.022 | H61: Convenio - 3 cupos Residencia Protegida para el Servicio de Salud Osorno en la Región Metropolitana | I61: 3 cupos Residencia Protegida por 24 meses, en la Región Metropolitana, por un total de 2190 días de residencia protegida. | J61: 1 | K61: Residencia | L61: 1 | M61: 1 | N61: 80865750 | O61: 3369408 | P61: 24 | Q61: 01-01-2025,01-02-2025,01-03-2025,01-04-2025,01-05-2025,01-06-2025,01-07-2025,01-08-2025,01-09-2025,01-10-2025,01-11-2025,01-12-2025,01-01-2026,01-02-2026,01-03-2026,01-04-2026,01-05-2026,01-06-2026,01-07-2026,01-08-2026,01-09-2026,01-10-2026,01-11-2026,01-12-2026 | R61: Antonia Caifil | S61: Jefa Subdepto. Gestión Clinica y Adm. | T61: 64-335813- | U61: antonia.caifil@redsalud.gob.cl | V61: 45474 | W61: 45478 | X61: 12 | Y61: 1057532-1299-SE24 | Z61: 1 | AA61: 3369406 | AB61: 46143 | AC61: Arrastre | AD61: =VLOOKUP(D61,Oficial!A:C,3,0) -> Arrastre
... A169: SERVICIO DE SALUD OSORNO | B169: 1057532-356-PC24 | C169: Bienes y Servicios | D169: 1057532-356-PC24 | E169: Proyecto operacional | F169: Publicado | G169: 22.08 | H169: Convenio servicio de guardias para la DSSO y sus establecimientos y dispositivos dependientes | I169: Se requiere la contratación de un convenio de servicio de guardias para la DSSO y sus establecimientos y dispositivos dependientes, cumpliendo los estándares requeridos en concordancia con las bases administrativas, especificaciones técnicas, por un período de 24 meses. | J169: 1 | K169: Servicio de guardias | L169: 1 | M169: 1 | N169: 1810393810 | O169: 75433085 | P169: 24 | Q169: 01-01-2025,01-02-2025,01-03-2025,01-04-2025,01-05-2025,01-06-2025,01-07-2025,01-08-2025,01-09-2025,01-10-2025,01-11-2025,01-12-2025,01-01-2026,01-02-2026,01-03-2026,01-04-2026,01-05-2026,01-06-2026,01-07-2026,01-08-2026,01-09-2026,01-10-2026,01-11-2026,01-12-2026 | R169: Lorena Torres Castillo | S169: Encargada (S) Sección Administración de Contratos | T169: 64-2567381- | U169: lorena.torresc@redsalud.gob.cl | V169: 45444 | W169: 45478 | X169: 46 | Y169: 1057532-4652-TD25 | Z169: 1 | AA169: 75433075 | AB169: 46204 | AC169: Arrastre | AD169: =VLOOKUP(D169,Oficial!A:C,3,0) -> Arrastre
A170: SERVICIO DE SALUD OSORNO | B170: 1057532-193-PC25 | C170: Bienes y Servicios | D170: 1057532-193-PC25 | E170: Proyecto operacional | F170: Publicado | G170: 22.09.006 | H170: Convenio - ARRIENDO 159 EQUIPOS PC AIO PARA APOYAR LOS PROCESOS CLINICOS Y ADMINISTRATIVOS | I170: Licitar en modalidad el servicio de arriendo equipos computacionales PC AIO con licenciamiento de Sistema Operativo (Windows), Office 365 y antivirus. | J170: 2 | K170: Insumos | L170: 4 | M170: 159 | N170: 2096280 | O170: 9258570 | P170: 32 | Q170: 01-01-2026,01-02-2026,01-03-2026,01-04-2026,01-05-2026,01-06-2026,01-07-2026,01-08-2026,01-09-2026,01-10-2026,01-11-2026,01-12-2026,01-01-2027,01-02-2027,01-03-2027,01-04-2027,01-05-2027,01-06-2027,01-07-2027,01-08-2027,01-09-2027,01-10-2027,01-11-2027,01-12-2027,01-01-2028,01-02-2028,01-03-2028,01-04-2028,01-05-2028,01-06-2028,01-07-2028,01-08-2028 | R170: Alvaro Montecinos | S170: Jefe (S) Subdepto. Soporte TIC | T170: 64-2335838- | U170: alvaro.montecinos@redsalud.gob.cl | V170: 45992 | W170: 45889 | X170: 0 | Z170: 1 | AA170: 9258570 | AB170: 46235 | AC170: Arrastre | AD170: =VLOOKUP(D170,Oficial!A:C,3,0) -> Arrastre
A171: SERVICIO DE SALUD OSORNO | B171: 1057532-193-PC25 | C171: Bienes y Servicios | D171: 1057532-193-PC25 | E171: Proyecto operacional | F171: Publicado | G171: 22.09.006 | H171: Convenio - ARRIENDO 159 EQUIPOS PC AIO PARA APOYAR LOS PORCESOS CLINICOS Y ADMINISTRATIVOS | I171: Licitar en modalidad el servicio de arriendo equipos computacionales PC AIO con licenciamiento de Sistema Operativo (Windows), Office 365 y antivirus. | J171: 2 | K171: Insumos | L171: 4 | M171: 159 | N171: 2096280 | O171: 9258570 | P171: 1 | Q171: 01-01-2026,01-02-2026,01-03-2026,01-04-2026,01-05-2026,01-06-2026,01-07-2026,01-08-2026,01-09-2026,01-10-2026,01-11-2026,01-12-2026,01-01-2027,01-02-2027,01-03-2027,01-04-2027,01-05-2027,01-06-2027,01-07-2027,01-08-2027,01-09-2027,01-10-2027,01-11-2027,01-12-2027,01-01-2028,01-02-2028,01-03-2028,01-04-2028,01-05-2028,01-06-2028,01-07-2028,01-08-2028 | R171: Alvaro Montecinos | S171: Jefe (S) Subdepto. Soporte TIC | T171: 64-2335838- | U171: alvaro.montecinos@redsalud.gob.cl | V171: 45870 | W171: 45889 | X171: 0 | Z171: 1 | AA171: 9258570 | AB171: 46174 | AC171: Arrastre | AD171: =VLOOKUP(D171,Oficial!A:C,3,0) -> Arrastre
A172: SERVICIO DE SALUD OSORNO | B172: 1057532-193-PC25 | C172: Bienes y Servicios | D172: 1057532-193-PC25 | E172: Proyecto operacional | F172: Publicado | G172: 22.09.006 | H172: Convenio - ARRIENDO 159 EQUIPOS PC AIO PARA APOYAR LOS PROCESOS CLINICOS Y ADMINISTRATIVOS | I172: Licitar en modalidad el servicio de arriendo equipos computacionales PC AIO con licenciamiento de Sistema Operativo (Windows), Office 365 y antivirus. | J172: 2 | K172: Insumos | L172: 4 | M172: 159 | N172: 2096280 | O172: 9258570 | P172: 32 | Q172: 01-01-2026,01-02-2026,01-03-2026,01-04-2026,01-05-2026,01-06-2026,01-07-2026,01-08-2026,01-09-2026,01-10-2026,01-11-2026,01-12-2026,01-01-2027,01-02-2027,01-03-2027,01-04-2027,01-05-2027,01-06-2027,01-07-2027,01-08-2027,01-09-2027,01-10-2027,01-11-2027,01-12-2027,01-01-2028,01-02-2028,01-03-2028,01-04-2028,01-05-2028,01-06-2028,01-07-2028,01-08-2028 | R172: Alvaro Montecinos | S172: Jefe (S) Subdepto. Soporte TIC | T172: 64-2335838- | U172: alvaro.montecinos@redsalud.gob.cl | V172: 45992 | W172: 45889 | X172: 0 | Z172: 1 | AA172: 9258570 | AB172: 46204 | AC172: Arrastre | AD172: =VLOOKUP(D172,Oficial!A:C,3,0) -> Arrastre
A173: SERVICIO DE SALUD OSORNO | B173: 1057532-193-PC25 | C173: Bienes y Servicios | D173: 1057532-193-PC25 | E173: Proyecto operacional | F173: Publicado | G173: 22.09.006 | H173: Convenio - ARRIENDO 159 EQUIPOS PC AIO PARA APOYAR LOS PROCESOS CLINICOS Y ADMINISTRATIVOS | I173: Licitar en modalidad el servicio de arriendo equipos computacionales PC AIO con licenciamiento de Sistema Operativo (Windows), Office 365 y antivirus. | J173: 2 | K173: Insumos | L173: 4 | M173: 159 | N173: 2096280 | O173: 9258570 | P173: 32 | Q173: 01-01-2026,01-02-2026,01-03-2026,01-04-2026,01-05-2026,01-06-2026,01-07-2026,01-08-2026,01-09-2026,01-10-2026,01-11-2026,01-12-2026,01-01-2027,01-02-2027,01-03-2027,01-04-2027,01-05-2027,01-06-2027,01-07-2027,01-08-2027,01-09-2027,01-10-2027,01-11-2027,01-12-2027,01-01-2028,01-02-2028,01-03-2028,01-04-2028,01-05-2028,01-06-2028,01-07-2028,01-08-2028 | R173: Alvaro Montecinos | S173: Jefe (S) Subdepto. Soporte TIC | T173: 64-2335838- | U173: alvaro.montecinos@redsalud.gob.cl | V173: 45992 | W173: 45889 | X173: 0 | Z173: 1 | AA173: 9258570 | AB173: 46023 | AC173: Arrastre | AD173: =VLOOKUP(D173,Oficial!A:C,3,0) -> Arrastre
A174: SERVICIO DE SALUD OSORNO | B174: 1057532-193-PC25 | C174: Bienes y Servicios | D174: 1057532-193-PC25 | E174: Proyecto operacional | F174: Publicado | G174: 22.09.006 | H174: Convenio - ARRIENDO 159 EQUIPOS PC AIO PARA APOYAR LOS PORCESOS CLINICOS Y ADMINISTRATIVOS | I174: Licitar en modalidad el servicio de arriendo equipos computacionales PC AIO con licenciamiento de Sistema Operativo (Windows), Office 365 y antivirus. | J174: 2 | K174: Insumos | L174: 4 | M174: 159 | N174: 2096280 | O174: 9258570 | P174: 1 | Q174: 01-01-2026,01-02-2026,01-03-2026,01-04-2026,01-05-2026,01-06-2026,01-07-2026,01-08-2026,01-09-2026,01-10-2026,01-11-2026,01-12-2026,01-01-2027,01-02-2027,01-03-2027,01-04-2027,01-05-2027,01-06-2027,01-07-2027,01-08-2027,01-09-2027,01-10-2027,01-11-2027,01-12-2027,01-01-2028,01-02-2028,01-03-2028,01-04-2028,01-05-2028,01-06-2028,01-07-2028,01-08-2028 | R174: Alvaro Montecinos | S174: Jefe (S) Subdepto. Soporte TIC | T174: 64-2335838- | U174: alvaro.montecinos@redsalud.gob.cl | V174: 45870 | W174: 45889 | X174: 0 | Z174: 1 | AA174: 9258570 | AB174: 46023 | AC174: Arrastre | AD174: =VLOOKUP(D174,Oficial!A:C,3,0) -> Arrastre
A175: SERVICIO DE SALUD OSORNO | B175: 1057532-193-PC25 | C175: Bienes y Servicios | D175: 1057532-193-PC25 | E175: Proyecto operacional | F175: Publicado | G175: 22.09.006 | H175: Convenio - ARRIENDO 159 EQUIPOS PC AIO PARA APOYAR LOS PORCESOS CLINICOS Y ADMINISTRATIVOS | I175: Licitar en modalidad el servicio de arriendo equipos computacionales PC AIO con licenciamiento de Sistema Operativo (Windows), Office 365 y antivirus. | J175: 2 | K175: Insumos | L175: 4 | M175: 159 | N175: 2096280 | O175: 9258570 | P175: 1 | Q175: 01-01-2026,01-02-2026,01-03-2026,01-04-2026,01-05-2026,01-06-2026,01-07-2026,01-08-2026,01-09-2026,01-10-2026,01-11-2026,01-12-2026,01-01-2027,01-02-2027,01-03-2027,01-04-2027,01-05-2027,01-06-2027,01-07-2027,01-08-2027,01-09-2027,01-10-2027,01-11-2027,01-12-2027,01-01-2028,01-02-2028,01-03-2028,01-04-2028,01-05-2028,01-06-2028,01-07-2028,01-08-2028 | R175: Alvaro Montecinos | S175: Jefe (S) Subdepto. Soporte TIC | T175: 64-2335838- | U175: alvaro.montecinos@redsalud.gob.cl | V175: 45870 | W175: 45889 | X175: 0 | Z175: 1 | AA175: 9258570 | AB175: 46143 | AC175: Arrastre | AD175: =VLOOKUP(D175,Oficial!A:C,3,0) -> Arrastre
A176: SERVICIO DE SALUD OSORNO | B176: 1057532-193-PC25 | C176: Bienes y Servicios | D176: 1057532-193-PC25 | E176: Proyecto operacional | F176: Publicado | G176: 22.09.006 | H176: Convenio - ARRIENDO 159 EQUIPOS PC AIO PARA APOYAR LOS PORCESOS CLINICOS Y ADMINISTRATIVOS | I176: Licitar en modalidad el servicio de arriendo equipos computacionales PC AIO con licenciamiento de Sistema Operativo (Windows), Office 365 y antivirus. | J176: 2 | K176: Insumos | L176: 4 | M176: 159 | N176: 2096280 | O176: 9258570 | P176: 1 | Q176: 01-01-2026,01-02-2026,01-03-2026,01-04-2026,01-05-2026,01-06-2026,01-07-2026,01-08-2026,01-09-2026,01-10-2026,01-11-2026,01-12-2026,01-01-2027,01-02-2027,01-03-2027,01-04-2027,01-05-2027,01-06-2027,01-07-2027,01-08-2027,01-09-2027,01-10-2027,01-11-2027,01-12-2027,01-01-2028,01-02-2028,01-03-2028,01-04-2028,01-05-2028,01-06-2028,01-07-2028,01-08-2028 | R176: Alvaro Montecinos | S176: Jefe (S) Subdepto. Soporte TIC | T176: 64-2335838- | U176: alvaro.montecinos@redsalud.gob.cl | V176: 45870 | W176: 45889 | X176: 0 | Z176: 1 | AA176: 9258570 | AB176: 46113 | AC176: Arrastre | AD176: =VLOOKUP(D176,Oficial!A:C,3,0) -> Arrastre
A177: SERVICIO DE SALUD OSORNO | B177: 1057532-193-PC25 | C177: Bienes y Servicios | D177: 1057532-193-PC25 | E177: Proyecto operacional | F177: Publicado | G177: 22.09.006 | H177: Convenio - ARRIENDO 159 EQUIPOS PC AIO PARA APOYAR LOS PORCESOS CLINICOS Y ADMINISTRATIVOS | I177: Licitar en modalidad el servicio de arriendo equipos computacionales PC AIO con licenciamiento de Sistema Operativo (Windows), Office 365 y antivirus. | J177: 2 | K177: Insumos | L177: 4 | M177: 159 | N177: 2096280 | O177: 9258570 | P177: 1 | Q177: 01-01-2026,01-02-2026,01-03-2026,01-04-2026,01-05-2026,01-06-2026,01-07-2026,01-08-2026,01-09-2026,01-10-2026,01-11-2026,01-12-2026,01-01-2027,01-02-2027,01-03-2027,01-04-2027,01-05-2027,01-06-2027,01-07-2027,01-08-2027,01-09-2027,01-10-2027,01-11-2027,01-12-2027,01-01-2028,01-02-2028,01-03-2028,01-04-2028,01-05-2028,01-06-2028,01-07-2028,01-08-2028 | R177: Alvaro Montecinos | S177: Jefe (S) Subdepto. Soporte TIC | T177: 64-2335838- | U177: alvaro.montecinos@redsalud.gob.cl | V177: 45870 | W177: 45889 | X177: 0 | Z177: 1 | AA177: 9258570 | AB177: 46357 | AC177: Arrastre | AD177: =VLOOKUP(D177,Oficial!A:C,3,0) -> Arrastre
A178: SERVICIO DE SALUD OSORNO | B178: 1057532-193-PC25 | C178: Bienes y Servicios | D178: 1057532-193-PC25 | E178: Proyecto operacional | F178: Publicado | G178: 22.09.006 | H178: Convenio - ARRIENDO 159 EQUIPOS PC AIO PARA APOYAR LOS PORCESOS CLINICOS Y ADMINISTRATIVOS | I178: Licitar en modalidad el servicio de arriendo equipos computacionales PC AIO con licenciamiento de Sistema Operativo (Windows), Office 365 y antivirus. | J178: 2 | K178: Insumos | L178: 4 | M178: 159 | N178: 2096280 | O178: 9258570 | P178: 1 | Q178: 01-01-2026,01-02-2026,01-03-2026,01-04-2026,01-05-2026,01-06-2026,01-07-2026,01-08-2026,01-09-2026,01-10-2026,01-11-2026,01-12-2026,01-01-2027,01-02-2027,01-03-2027,01-04-2027,01-05-2027,01-06-2027,01-07-2027,01-08-2027,01-09-2027,01-10-2027,01-11-2027,01-12-2027,01-01-2028,01-02-2028,01-03-2028,01-04-2028,01-05-2028,01-06-2028,01-07-2028,01-08-2028 | R178: Alvaro Montecinos | S178: Jefe (S) Subdepto. Soporte TIC | T178: 64-2335838- | U178: alvaro.montecinos@redsalud.gob.cl | V178: 45870 | W178: 45889 | X178: 0 | Z178: 1 | AA178: 9258570 | AB178: 46082 | AC178: Arrastre | AD178: =VLOOKUP(D178,Oficial!A:C,3,0) -> Arrastre
A179: SERVICIO DE SALUD OSORNO | B179: 1057532-193-PC25 | C179: Bienes y Servicios | D179: 1057532-193-PC25 | E179: Proyecto operacional | F179: Publicado | G179: 22.09.006 | H179: Convenio - ARRIENDO 159 EQUIPOS PC AIO PARA APOYAR LOS PORCESOS CLINICOS Y ADMINISTRATIVOS | I179: Licitar en modalidad el servicio de arriendo equipos computacionales PC AIO con licenciamiento de Sistema Operativo (Windows), Office 365 y antivirus. | J179: 2 | K179: Insumos | L179: 4 | M179: 159 | N179: 2096280 | O179: 9258570 | P179: 1 | Q179: 01-01-2026,01-02-2026,01-03-2026,01-04-2026,01-05-2026,01-06-2026,01-07-2026,01-08-2026,01-09-2026,01-10-2026,01-11-2026,01-12-2026,01-01-2027,01-02-2027,01-03-2027,01-04-2027,01-05-2027,01-06-2027,01-07-2027,01-08-2027,01-09-2027,01-10-2027,01-11-2027,01-12-2027,01-01-2028,01-02-2028,01-03-2028,01-04-2028,01-05-2028,01-06-2028,01-07-2028,01-08-2028 | R179: Alvaro Montecinos | S179: Jefe (S) Subdepto. Soporte TIC | T179: 64-2335838- | U179: alvaro.montecinos@redsalud.gob.cl | V179: 45870 | W179: 45889 | X179: 0 | Z179: 1 | AA179: 9258570 | AB179: 46054 | AC179: Arrastre | AD179: =VLOOKUP(D179,Oficial!A:C,3,0) -> Arrastre
A180: SERVICIO DE SALUD OSORNO | B180: 1057532-193-PC25 | C180: Bienes y Servicios | D180: 1057532-193-PC25 | E180: Proyecto operacional | F180: Publicado | G180: 22.09.006 | H180: Convenio - ARRIENDO 159 EQUIPOS PC AIO PARA APOYAR LOS PROCESOS CLINICOS Y ADMINISTRATIVOS | I180: Licitar en modalidad el servicio de arriendo equipos computacionales PC AIO con licenciamiento de Sistema Operativo (Windows), Office 365 y antivirus. | J180: 2 | K180: Insumos | L180: 4 | M180: 159 | N180: 2096280 | O180: 9258570 | P180: 32 | Q180: 01-01-2026,01-02-2026,01-03-2026,01-04-2026,01-05-2026,01-06-2026,01-07-2026,01-08-2026,01-09-2026,01-10-2026,01-11-2026,01-12-2026,01-01-2027,01-02-2027,01-03-2027,01-04-2027,01-05-2027,01-06-2027,01-07-2027,01-08-2027,01-09-2027,01-10-2027,01-11-2027,01-12-2027,01-01-2028,01-02-2028,01-03-2028,01-04-2028,01-05-2028,01-06-2028,01-07-2028,01-08-2028 | R180: Alvaro Montecinos | S180: Jefe (S) Subdepto. Soporte TIC | T180: 64-2335838- | U180: alvaro.montecinos@redsalud.gob.cl | V180: 45992 | W180: 45889 | X180: 0 | Z180: 1 | AA180: 9258570 | AB180: 46266 | AC180: Arrastre | AD180: =VLOOKUP(D180,Oficial!A:C,3,0) -> Arrastre
A181: SERVICIO DE SALUD OSORNO | B181: 1057532-193-PC25 | C181: Bienes y Servicios | D181: 1057532-193-PC25 | E181: Proyecto operacional | F181: Publicado | G181: 22.09.006 | H181: Convenio - ARRIENDO 159 EQUIPOS PC AIO PARA APOYAR LOS PORCESOS CLINICOS Y ADMINISTRATIVOS | I181: Licitar en modalidad el servicio de arriendo equipos computacionales PC AIO con licenciamiento de Sistema Operativo (Windows), Office 365 y antivirus. | J181: 2 | K181: Insumos | L181: 4 | M181: 159 | N181: 2096280 | O181: 9258570 | P181: 1 | Q181: 01-01-2026,01-02-2026,01-03-2026,01-04-2026,01-05-2026,01-06-2026,01-07-2026,01-08-2026,01-09-2026,01-10-2026,01-11-2026,01-12-2026,01-01-2027,01-02-2027,01-03-2027,01-04-2027,01-05-2027,01-06-2027,01-07-2027,01-08-2027,01-09-2027,01-10-2027,01-11-2027,01-12-2027,01-01-2028,01-02-2028,01-03-2028,01-04-2028,01-05-2028,01-06-2028,01-07-2028,01-08-2028 | R181: Alvaro Montecinos | S181: Jefe (S) Subdepto. Soporte TIC | T181: 64-2335838- | U181: alvaro.montecinos@redsalud.gob.cl | V181: 45870 | W181: 45889 | X181: 0 | Z181: 1 | AA181: 9258570 | AB181: 46327 | AC181: Arrastre | AD181: =VLOOKUP(D181,Oficial!A:C,3,0) -> Arrastre
A182: SERVICIO DE SALUD OSORNO | B182: 1057532-195-PC25 | C182: Bienes y Servicios | D182: 1057532-195-PC25 | E182: Proyecto operacional | F182: Publicado | G182: 22.08.001 | H182: Convenio - SERVICIO DE ASEO PARA LA DSSO (BASE SAMU, EDIFICIO PLAZA SUR Y EDIFICIO M. RODRIGUEZ) POR 18 MESES (DESDE 01 JULIO 2025) | I182: Se requiere contar con servicios de aseo en los Edificios Plaza Sur, Manuel Rodriguez y Base SAMU, dependientes de la Dirección del Servicio de Salud Osorno. Todo lo anterior, por un periodo de 18 meses (desde el 01 de julio 2025 hasta el 31 de diciembre del 2026) | J182: 2 | K182: Aseo | L182: 4 | M182: 54 | N182: 1953705 | O182: 5861115 | P182: 18 | Q182: 01-07-2025,01-08-2025,01-09-2025,01-10-2025,01-11-2025,01-12-2025,01-01-2026,01-02-2026,01-03-2026,01-04-2026,01-05-2026,01-06-2026,01-07-2026,01-08-2026,01-09-2026,01-10-2026,01-11-2026,01-12-2026 | R182: Lorena Torres Castillo | S182: Encargada (s) Sección Administración de Contratos | T182: 64-2337381- | U182: lorena.torresc@redsalud.gob.cl | V182: 45658 | W182: 45889 | X182: 16 | Y182: 1057532-4942-SE25 | Z182: 1 | AA182: 5861115 | AB182: 46023 | AC182: Arrastre | AD182: =VLOOKUP(D182,Oficial!A:C,3,0) -> Arrastre
A183: SERVICIO DE SALUD OSORNO | B183: 1057532-195-PC25 | C183: Bienes y Servicios | D183: 1057532-195-PC25 | E183: Proyecto operacional | F183: Publicado | G183: 22.08.001 | H183: Convenio - SERVICIO DE ASEO PARA LA DSSO (BASE SAMU, EDIFICIO PLAZA SUR Y EDIFICIO M. RODRIGUEZ) POR 18 MESES (DESDE 01 JULIO 2025) | I183: Se requiere contar con servicios de aseo en los Edificios Plaza Sur, Manuel Rodriguez y Base SAMU, dependientes de la Dirección del Servicio de Salud Osorno. Todo lo anterior, por un periodo de 18 meses (desde el 01 de julio 2025 hasta el 31 de diciembre del 2026) | J183: 2 | K183: Aseo | L183: 4 | M183: 54 | N183: 1953705 | O183: 5861115 | P183: 18 | Q183: 01-07-2025,01-08-2025,01-09-2025,01-10-2025,01-11-2025,01-12-2025,01-01-2026,01-02-2026,01-03-2026,01-04-2026,01-05-2026,01-06-2026,01-07-2026,01-08-2026,01-09-2026,01-10-2026,01-11-2026,01-12-2026 | R183: Lorena Torres Castillo | S183: Encargada (s) Sección Administración de Contratos | T183: 64-2337381- | U183: lorena.torresc@redsalud.gob.cl | V183: 45658 | W183: 45889 | X183: 16 | Y183: 1057532-4948-SE25 | Z183: 1 | AA183: 5861115 | AB183: 46023 | AC183: Arrastre | AD183: =VLOOKUP(D183,Oficial!A:C,3,0) -> Arrastre
A184: SERVICIO DE SALUD OSORNO | B184: 1057532-195-PC25 | C184: Bienes y Servicios | D184: 1057532-195-PC25 | E184: Proyecto operacional | F184: Publicado | G184: 22.08.001 | H184: Convenio - SERVICIO DE ASEO PARA LA DSSO (BASE SAMU, EDIFICIO PLAZA SUR Y EDIFICIO M. RODRIGUEZ) POR 18 MESES (DESDE 01 JULIO 2025) | I184: Se requiere contar con servicios de aseo en los Edificios Plaza Sur, Manuel Rodriguez y Base SAMU, dependientes de la Dirección del Servicio de Salud Osorno. Todo lo anterior, por un periodo de 18 meses (desde el 01 de julio 2025 hasta el 31 de diciembre del 2026) | J184: 2 | K184: Aseo | L184: 4 | M184: 54 | N184: 1953705 | O184: 5861115 | P184: 18 | Q184: 01-07-2025,01-08-2025,01-09-2025,01-10-2025,01-11-2025,01-12-2025,01-01-2026,01-02-2026,01-03-2026,01-04-2026,01-05-2026,01-06-2026,01-07-2026,01-08-2026,01-09-2026,01-10-2026,01-11-2026,01-12-2026 | R184: Lorena Torres Castillo | S184: Encargada (s) Sección Administración de Contratos | T184: 64-2337381- | U184: lorena.torresc@redsalud.gob.cl | V184: 45658 | W184: 45889 | X184: 16 | Y184: 1057532-4604-SE25 | Z184: 1 | AA184: 5861115 | AB184: 46023 | AC184: Arrastre | AD184: =VLOOKUP(D184,Oficial!A:C,3,0) -> Arrastre
A185: SERVICIO DE SALUD OSORNO | B185: 1057532-195-PC25 | C185: Bienes y Servicios | D185: 1057532-195-PC25 | E185: Proyecto operacional | F185: Publicado | G185: 22.08.001 | H185: Convenio - SERVICIO DE ASEO PARA LA DSSO (BASE SAMU, EDIFICIO PLAZA SUR Y EDIFICIO M. RODRIGUEZ) POR 18 MESES (DESDE 01 JULIO 2025) | I185: Se requiere contar con servicios de aseo en los Edificios Plaza Sur, Manuel Rodriguez y Base SAMU, dependientes de la Dirección del Servicio de Salud Osorno. Todo lo anterior, por un periodo de 18 meses (desde el 01 de julio 2025 hasta el 31 de diciembre del 2026) | J185: 2 | K185: Aseo | L185: 4 | M185: 54 | N185: 1953705 | O185: 5861115 | P185: 18 | Q185: 01-07-2025,01-08-2025,01-09-2025,01-10-2025,01-11-2025,01-12-2025,01-01-2026,01-02-2026,01-03-2026,01-04-2026,01-05-2026,01-06-2026,01-07-2026,01-08-2026,01-09-2026,01-10-2026,01-11-2026,01-12-2026 | R185: Lorena Torres Castillo | S185: Encargada (s) Sección Administración de Contratos | T185: 64-2337381- | U185: lorena.torresc@redsalud.gob.cl | V185: 45658 | W185: 45889 | X185: 16 | Y185: 1057532-4942-SE25 | Z185: 1 | AA185: 5861115 | AB185: 46143 | AC185: Arrastre | AD185: =VLOOKUP(D185,Oficial!A:C,3,0) -> Arrastre
A186: SERVICIO DE SALUD OSORNO | B186: 1057532-195-PC25 | C186: Bienes y Servicios | D186: 1057532-195-PC25 | E186: Proyecto operacional | F186: Publicado | G186: 22.08.001 | H186: Convenio - SERVICIO DE ASEO PARA LA DSSO (BASE SAMU, EDIFICIO PLAZA SUR Y EDIFICIO M. RODRIGUEZ) POR 18 MESES (DESDE 01 JULIO 2025) | I186: Se requiere contar con servicios de aseo en los Edificios Plaza Sur, Manuel Rodriguez y Base SAMU, dependientes de la Dirección del Servicio de Salud Osorno. Todo lo anterior, por un periodo de 18 meses (desde el 01 de julio 2025 hasta el 31 de diciembre del 2026) | J186: 2 | K186: Aseo | L186: 4 | M186: 54 | N186: 1953705 | O186: 5861115 | P186: 18 | Q186: 01-07-2025,01-08-2025,01-09-2025,01-10-2025,01-11-2025,01-12-2025,01-01-2026,01-02-2026,01-03-2026,01-04-2026,01-05-2026,01-06-2026,01-07-2026,01-08-2026,01-09-2026,01-10-2026,01-11-2026,01-12-2026 | R186: Lorena Torres Castillo | S186: Encargada (s) Sección Administración de Contratos | T186: 64-2337381- | U186: lorena.torresc@redsalud.gob.cl | V186: 45658 | W186: 45889 | X186: 16 | Y186: 1057532-4604-SE25 | Z186: 1 | AA186: 5861115 | AB186: 46054 | AC186: Arrastre | AD186: =VLOOKUP(D186,Oficial!A:C,3,0) -> Arrastre
A187: SERVICIO DE SALUD OSORNO | B187: 1057532-195-PC25 | C187: Bienes y Servicios | D187: 1057532-195-PC25 | E187: Proyecto operacional | F187: Publicado | G187: 22.08.001 | H187: Convenio - SERVICIO DE ASEO PARA LA DSSO (BASE SAMU, EDIFICIO PLAZA SUR Y EDIFICIO M. RODRIGUEZ) POR 18 MESES (DESDE 01 JULIO 2025) | I187: Se requiere contar con servicios de aseo en los Edificios Plaza Sur, Manuel Rodriguez y Base SAMU, dependientes de la Dirección del Servicio de Salud Osorno. Todo lo anterior, por un periodo de 18 meses (desde el 01 de julio 2025 hasta el 31 de diciembre del 2026) | J187: 2 | K187: Aseo | L187: 4 | M187: 54 | N187: 1953705 | O187: 5861115 | P187: 18 | Q187: 01-07-2025,01-08-2025,01-09-2025,01-10-2025,01-11-2025,01-12-2025,01-01-2026,01-02-2026,01-03-2026,01-04-2026,01-05-2026,01-06-2026,01-07-2026,01-08-2026,01-09-2026,01-10-2026,01-11-2026,01-12-2026 | R187: Lorena Torres Castillo | S187: Encargada (s) Sección Administración de Contratos | T187: 64-2337381- | U187: lorena.torresc@redsalud.gob.cl | V187: 45658 | W187: 45889 | X187: 16 | Y187: 1057532-5193-SE25 | Z187: 1 | AA187: 5861115 | AB187: 46357 | AC187: Arrastre | AD187: =VLOOKUP(D187,Oficial!A:C,3,0) -> Arrastre
A188: SERVICIO DE SALUD OSORNO | B188: 1057532-195-PC25 | C188: Bienes y Servicios | D188: 1057532-195-PC25 | E188: Proyecto operacional | F188: Publicado | G188: 22.08.001 | H188: Convenio - SERVICIO DE ASEO PARA LA DSSO (BASE SAMU, EDIFICIO PLAZA SUR Y EDIFICIO M. RODRIGUEZ) POR 18 MESES (DESDE 01 JULIO 2025) | I188: Se requiere contar con servicios de aseo en los Edificios Plaza Sur, Manuel Rodriguez y Base SAMU, dependientes de la Dirección del Servicio de Salud Osorno. Todo lo anterior, por un periodo de 18 meses (desde el 01 de julio 2025 hasta el 31 de diciembre del 2026) | J188: 2 | K188: Aseo | L188: 4 | M188: 54 | N188: 1953705 | O188: 5861115 | P188: 18 | Q188: 01-07-2025,01-08-2025,01-09-2025,01-10-2025,01-11-2025,01-12-2025,01-01-2026,01-02-2026,01-03-2026,01-04-2026,01-05-2026,01-06-2026,01-07-2026,01-08-2026,01-09-2026,01-10-2026,01-11-2026,01-12-2026 | R188: Lorena Torres Castillo | S188: Encargada (s) Sección Administración de Contratos | T188: 64-2337381- | U188: lorena.torresc@redsalud.gob.cl | V188: 45658 | W188: 45889 | X188: 16 | Y188: 1057532-4942-SE25 | Z188: 1 | AA188: 5861115 | AB188: 46113 | AC188: Arrastre | AD188: =VLOOKUP(D188,Oficial!A:C,3,0) -> Arrastre
